Workbook

Sheet 🗂 Ichiran
B2: 🗂 ICHIRAN — PAINEL DE CONTROLE CENTRAL
B3: Mês base = Mês de Referência do Dashboard | 🔵 Fundo azul = você digita (PREVISTO) | Texto azul = automático das Movimentações
B5: 📅 Coluna D = mês do Dashboard | E-I = meses seguintes | Altere o mês no Dashboard (aba 📊) para navegar | 🔵 Azul escuro = digite aqui | Texto azul = automático
B6: ITEM | C6: TIPO | D6: =TEXT(DATE(YEAR($D$200)+INT((MONTH($D$200)+0-1)/12),MOD(MONTH($D$200)+0-1,12)+1,1),"MMM/YY") -> May/25 | E6: =TEXT(DATE(YEAR($D$200)+INT((MONTH($D$200)+1-1)/12),MOD(MONTH($D$200)+1-1,12)+1,1),"MMM/YY") -> Jun/25 | F6: =TEXT(DATE(YEAR($D$200)+INT((MONTH($D$200)+2-1)/12),MOD(MONTH($D$200)+2-1,12)+1,1),"MMM/YY") -> Jul/25 | G6: =TEXT(DATE(YEAR($D$200)+INT((MONTH($D$200)+3-1)/12),MOD(MONTH($D$200)+3-1,12)+1,1),"MMM/YY") -> Aug/25 | H6: =TEXT(DATE(YEAR($D$200)+INT((MONTH($D$200)+4-1)/12),MOD(MONTH($D$200)+4-1,12)+1,1),"MMM/YY") -> Sep/25 | I6: =TEXT(DATE(YEAR($D$200)+INT((MONTH($D$200)+5-1)/12),MOD(MONTH($D$200)+5-1,12)+1,1),"MMM/YY") -> Oct/25 | J6: TOTAL ANO
B8: ▲ RENDA
B9: Salário | C9: PREV | D9: 374000 | E9: 0 | F9: 0 | G9: 0 | H9: 0 | I9: 0 | J9: =SUM(D9,E9,F9,G9,H9,I9) -> 374000
C10: REAL | D10: =IFERROR(SUMIFS('📋 Movimentações'!$F$15:$F$514,'📋 Movimentações'!$B$15:$B$514,">="&DATE(YEAR($D$200)+INT((MONTH($D$200)+0-1)/12),MOD(MONTH($D$200)+0-1,12)+1,1),'📋 Movimentações'!$B$15:$B$514,"<="&EOMONTH(DATE(YEAR($D$200)+INT((MONTH($D$200)+0-1)/12),MOD(MONTH($D$200)+0-1,12)+1,1),0),'📋 Movimentações'!$E$15:$E$514,"Entrada",'📋 Movimentações'!$D$15:$D$514,"Salário"),0) -> 374000 | E10: =IFERROR(SUMIFS('📋 Movimentações'!$F$15:$F$514,'📋 Movimentações'!$B$15:$B$514,">="&DATE(YEAR($D$200)+INT((MONTH($D$200)+1-1)/12),MOD(MONTH($D$200)+1-1,12)+1,1),'📋 Movimentações'!$B$15:$B$514,"<="&EOMONTH(DATE(YEAR($D$200)+INT((MONTH($D$200)+1-1)/12),MOD(MONTH($D$200)+1-1,12)+1,1),0),'📋 Movimentações'!$E$15:$E$514,"Entrada",'📋 Movimentações'!$D$15:$D$514,"Salário"),0) -> 0 | F10: =IFERROR(SUMIFS('📋 Movimentações'!$F$15:$F$514,'📋 Movimentações'!$B$15:$B$514,">="&DATE(YEAR($D$200)+INT((MONTH($D$200)+2-1)/12),MOD(MONTH($D$200)+2-1,12)+1,1),'📋 Movimentações'!$B$15:$B$514,"<="&EOMONTH(DATE(YEAR($D$200)+INT((MONTH($D$200)+2-1)/12),MOD(MONTH($D$200)+2-1,12)+1,1),0),'📋 Movimentações'!$E$15:$E$514,"Entrada",'📋 Movimentações'!$D$15:$D$514,"Salário"),0) -> 0 | G10: =IFERROR(SUMIFS('📋 Movimentações'!$F$15:$F$514,'📋 Movimentações'!$B$15:$B$514,">="&DATE(YEAR($D$200)+INT((MONTH($D$200)+3-1)/12),MOD(MONTH($D$200)+3-1,12)+1,1),'📋 Movimentações'!$B$15:$B$514,"<="&EOMONTH(DATE(YEAR($D$200)+INT((MONTH($D$200)+3-1)/12),MOD(MONTH($D$200)+3-1,12)+1,1),0),'📋 Movimentações'!$E$15:$E$514,"Entrada",'📋 Movimentações'!$D$15:$D$514,"Salário"),0) -> 0 | H10: =IFERROR(SUMIFS('📋 Movimentações'!$F$15:$F$514,'📋 Movimentações'!$B$15:$B$514,">="&DATE(YEAR($D$200)+INT((MONTH($D$200)+4-1)/12),MOD(MONTH($D$200)+4-1,12)+1,1),'📋 Movimentações'!$B$15:$B$514,"<="&EOMONTH(DATE(YEAR($D$200)+INT((MONTH($D$200)+4-1)/12),MOD(MONTH($D$200)+4-1,12)+1,1),0),'📋 Movimentações'!$E$15:$E$514,"Entrada",'📋 Movimentações'!$D$15:$D$514,"Salário"),0) -> 0 | I10: =IFERROR(SUMIFS('📋 Movimentações'!$F$15:$F$514,'📋 Movimentações'!$B$15:$B$514,">="&DATE(YEAR($D$200)+INT((MONTH($D$200)+5-1)/12),MOD(MONTH($D$200)+5-1,12)+1,1),'📋 Movimentações'!$B$15:$B$514,"<="&EOMONTH(DATE(YEAR($D$200)+INT((MONTH($D$200)+5-1)/12),MOD(MONTH($D$200)+5-1,12)+1,1),0),'📋 Movimentações'!$E$15:$E$514,"Entrada",'📋 Movimentações'!$D$15:$D$514,"Salário"),0) -> 0 | J10: =SUM(D10,E10,F10,G10,H10,I10) -> 374000
B11: Hora Extra | C11: PREV | D11: 20000 | E11: 0 | F11: 0 | G11: 0 | H11: 0 | I11: 0 | J11: =SUM(D11,E11,F11,G11,H11,I11) -> 20000
C12: REAL | D12: =IFERROR(SUMIFS('📋 Movimentações'!$F$15:$F$514,'📋 Movimentações'!$B$15:$B$514,">="&DATE(YEAR($D$200)+INT((MONTH($D$200)+0-1)/12),MOD(MONTH($D$200)+0-1,12)+1,1),'📋 Movimentações'!$B$15:$B$514,"<="&EOMONTH(DATE(YEAR($D$200)+INT((MONTH($D$200)+0-1)/12),MOD(MONTH($D$200)+0-1,12)+1,1),0),'📋 Movimentações'!$E$15:$E$514,"Entrada",'📋 Movimentações'!$D$15:$D$514,"Hora Extra"),0) -> 0 | E12: =IFERROR(SUMIFS('📋 Movimentações'!$F$15:$F$514,'📋 Movimentações'!$B$15:$B$514,">="&DATE(YEAR($D$200)+INT((MONTH($D$200)+1-1)/12),MOD(MONTH($D$200)+1-1,12)+1,1),'📋 Movimentações'!$B$15:$B$514,"<="&EOMONTH(DATE(YEAR($D$200)+INT((MONTH($D$200)+1-1)/12),MOD(MONTH($D$200)+1-1,12)+1,1),0),'📋 Movimentações'!$E$15:$E$514,"Entrada",'📋 Movimentações'!$D$15:$D$514,"Hora Extra"),0) -> 0 | F12: =IFERROR(SUMIFS('📋 Movimentações'!$F$15:$F$514,'📋 Movimentações'!$B$15:$B$514,">="&DATE(YEAR($D$200)+INT((MONTH($D$200)+2-1)/12),MOD(MONTH($D$200)+2-1,12)+1,1),'📋 Movimentações'!$B$15:$B$514,"<="&EOMONTH(DATE(YEAR($D$200)+INT((MONTH($D$200)+2-1)/12),MOD(MONTH($D$200)+2-1,12)+1,1),0),'📋 Movimentações'!$E$15:$E$514,"Entrada",'📋 Movimentações'!$D$15:$D$514,"Hora Extra"),0) -> 0 | G12: =IFERROR(SUMIFS('📋 Movimentações'!$F$15:$F$514,'📋 Movimentações'!$B$15:$B$514,">="&DATE(YEAR($D$200)+INT((MONTH($D$200)+3-1)/12),MOD(MONTH($D$200)+3-1,12)+1,1),'📋 Movimentações'!$B$15:$B$514,"<="&EOMONTH(DATE(YEAR($D$200)+INT((MONTH($D$200)+3-1)/12),MOD(MONTH($D$200)+3-1,12)+1,1),0),'📋 Movimentações'!$E$15:$E$514,"Entrada",'📋 Movimentações'!$D$15:$D$514,"Hora Extra"),0) -> 0 | H12: =IFERROR(SUMIFS('📋 Movimentações'!$F$15:$F$514,'📋 Movimentações'!$B$15:$B$514,">="&DATE(YEAR($D$200)+INT((MONTH($D$200)+4-1)/12),MOD(MONTH($D$200)+4-1,12)+1,1),'📋 Movimentações'!$B$15:$B$514,"<="&EOMONTH(DATE(YEAR($D$200)+INT((MONTH($D$200)+4-1)/12),MOD(MONTH($D$200)+4-1,12)+1,1),0),'📋 Movimentações'!$E$15:$E$514,"Entrada",'📋 Movimentações'!$D$15:$D$514,"Hora Extra"),0) -> 0 | I12: =IFERROR(SUMIFS('📋 Movimentações'!$F$15:$F$514,'📋 Movimentações'!$B$15:$B$514,">="&DATE(YEAR($D$200)+INT((MONTH($D$200)+5-1)/12),MOD(MONTH($D$200)+5-1,12)+1,1),'📋 Movimentações'!$B$15:$B$514,"<="&EOMONTH(DATE(YEAR($D$200)+INT((MONTH($D$200)+5-1)/12),MOD(MONTH($D$200)+5-1,12)+1,1),0),'📋 Movimentações'!$E$15:$E$514,"Entrada",'📋 Movimentações'!$D$15:$D$514,"Hora Extra"),0) -> 0 | J12: =SUM(D12,E12,F12,G12,H12,I12) -> 0
B13: Bônus | C13: PREV | D13: 0 | E13: 0 | F13: 0 | G13: 0 | H13: 0 | I13: 0 | J13: =SUM(D13,E13,F13,G13,H13,I13) -> 0
C14: REAL | D14: =IFERROR(SUMIFS('📋 Movimentações'!$F$15:$F$514,'📋 Movimentações'!$B$15:$B$514,">="&DATE(YEAR($D$200)+INT((MONTH($D$200)+0-1)/12),MOD(MONTH($D$200)+0-1,12)+1,1),'📋 Movimentações'!$B$15:$B$514,"<="&EOMONTH(DATE(YEAR($D$200)+INT((MONTH($D$200)+0-1)/12),MOD(MONTH($D$200)+0-1,12)+1,1),0),'📋 Movimentações'!$E$15:$E$514,"Entrada",'📋 Movimentações'!$D$15:$D$514,"Bônus"),0) -> 55000 | E14: =IFERROR(SUMIFS('📋 Movimentações'!$F$15:$F$514,'📋 Movimentações'!$B$15:$B$514,">="&DATE(YEAR($D$200)+INT((MONTH($D$200)+1-1)/12),MOD(MONTH($D$200)+1-1,12)+1,1),'📋 Movimentações'!$B$15:$B$514,"<="&EOMONTH(DATE(YEAR($D$200)+INT((MONTH($D$200)+1-1)/12),MOD(MONTH($D$200)+1-1,12)+1,1),0),'📋 Movimentações'!$E$15:$E$514,"Entrada",'📋 Movimentações'!$D$15:$D$514,"Bônus"),0) -> 0 | F14: =IFERROR(SUMIFS('📋 Movimentações'!$F$15:$F$514,'📋 Movimentações'!$B$15:$B$514,">="&DATE(YEAR($D$200)+INT((MONTH($D$200)+2-1)/12),MOD(MONTH($D$200)+2-1,12)+1,1),'📋 Movimentações'!$B$15:$B$514,"<="&EOMONTH(DATE(YEAR($D$200)+INT((MONTH($D$200)+2-1)/12),MOD(MONTH($D$200)+2-1,12)+1,1),0),'📋 Movimentações'!$E$15:$E$514,"Entrada",'📋 Movimentações'!$D$15:$D$514,"Bônus"),0) -> 0 | G14: =IFERROR(SUMIFS('📋 Movimentações'!$F$15:$F$514,'📋 Movimentações'!$B$15:$B$514,">="&DATE(YEAR($D$200)+INT((MONTH($D$200)+3-1)/12),MOD(MONTH($D$200)+3-1,12)+1,1),'📋 Movimentações'!$B$15:$B$514,"<="&EOMONTH(DATE(YEAR($D$200)+INT((MONTH($D$200)+3-1)/12),MOD(MONTH($D$200)+3-1,12)+1,1),0),'📋 Movimentações'!$E$15:$E$514,"Entrada",'📋 Movimentações'!$D$15:$D$514,"Bônus"),0) -> 0 | H14: =IFERROR(SUMIFS('📋 Movimentações'!$F$15:$F$514,'📋 Movimentações'!$B$15:$B$514,">="&DATE(YEAR($D$200)+INT((MONTH($D$200)+4-1)/12),MOD(MONTH($D$200)+4-1,12)+1,1),'📋 Movimentações'!$B$15:$B$514,"<="&EOMONTH(DATE(YEAR($D$200)+INT((MONTH($D$200)+4-1)/12),MOD(MONTH($D$200)+4-1,12)+1,1),0),'📋 Movimentações'!$E$15:$E$514,"Entrada",'📋 Movimentações'!$D$15:$D$514,"Bônus"),0) -> 0 | I14: =IFERROR(SUMIFS('📋 Movimentações'!$F$15:$F$514,'📋 Movimentações'!$B$15:$B$514,">="&DATE(YEAR($D$200)+INT((MONTH($D$200)+5-1)/12),MOD(MONTH($D$200)+5-1,12)+1,1),'📋 Movimentações'!$B$15:$B$514,"<="&EOMONTH(DATE(YEAR($D$200)+INT((MONTH($D$200)+5-1)/12),MOD(MONTH($D$200)+5-1,12)+1,1),0),'📋 Movimentações'!$E$15:$E$514,"Entrada",'📋 Movimentações'!$D$15:$D$514,"Bônus"),0) -> 0 | J14: =SUM(D14,E14,F14,G14,H14,I14) -> 55000
B15: Arubaito / Extra | C15: PREV | D15: 0 | E15: 0 | F15: 0 | G15: 0 | H15: 0 | I15: 0 | J15: =SUM(D15,E15,F15,G15,H15,I15) -> 0
C16: REAL | D16: =IFERROR(SUMIFS('📋 Movimentações'!$F$15:$F$514,'📋 Movimentações'!$B$15:$B$514,">="&DATE(YEAR($D$200)+INT((MONTH($D$200)+0-1)/12),MOD(MONTH($D$200)+0-1,12)+1,1),'📋 Movimentações'!$B$15:$B$514,"<="&EOMONTH(DATE(YEAR($D$200)+INT((MONTH($D$200)+0-1)/12),MOD(MONTH($D$200)+0-1,12)+1,1),0),'📋 Movimentações'!$E$15:$E$514,"Entrada",'📋 Movimentações'!$D$15:$D$514,"Arubaito/Extra"),0) -> 0 | E16: =IFERROR(SUMIFS('📋 Movimentações'!$F$15:$F$514,'📋 Movimentações'!$B$15:$B$514,">="&DATE(YEAR($D$200)+INT((MONTH($D$200)+1-1)/12),MOD(MONTH($D$200)+1-1,12)+1,1),'📋 Movimentações'!$B$15:$B$514,"<="&EOMONTH(DATE(YEAR($D$200)+INT((MONTH($D$200)+1-1)/12),MOD(MONTH($D$200)+1-1,12)+1,1),0),'📋 Movimentações'!$E$15:$E$514,"Entrada",'📋 Movimentações'!$D$15:$D$514,"Arubaito/Extra"),0) -> 0 | F16: =IFERROR(SUMIFS('📋 Movimentações'!$F$15:$F$514,'📋 Movimentações'!$B$15:$B$514,">="&DATE(YEAR($D$200)+INT((MONTH($D$200)+2-1)/12),MOD(MONTH($D$200)+2-1,12)+1,1),'📋 Movimentações'!$B$15:$B$514,"<="&EOMONTH(DATE(YEAR($D$200)+INT((MONTH($D$200)+2-1)/12),MOD(MONTH($D$200)+2-1,12)+1,1),0),'📋 Movimentações'!$E$15:$E$514,"Entrada",'📋 Movimentações'!$D$15:$D$514,"Arubaito/Extra"),0) -> 0 | G16: =IFERROR(SUMIFS('📋 Movimentações'!$F$15:$F$514,'📋 Movimentações'!$B$15:$B$514,">="&DATE(YEAR($D$200)+INT((MONTH($D$200)+3-1)/12),MOD(MONTH($D$200)+3-1,12)+1,1),'📋 Movimentações'!$B$15:$B$514,"<="&EOMONTH(DATE(YEAR($D$200)+INT((MONTH($D$200)+3-1)/12),MOD(MONTH($D$200)+3-1,12)+1,1),0),'📋 Movimentações'!$E$15:$E$514,"Entrada",'📋 Movimentações'!$D$15:$D$514,"Arubaito/Extra"),0) -> 0 | H16: =IFERROR(SUMIFS('📋 Movimentações'!$F$15:$F$514,'📋 Movimentações'!$B$15:$B$514,">="&DATE(YEAR($D$200)+INT((MONTH($D$200)+4-1)/12),MOD(MONTH($D$200)+4-1,12)+1,1),'📋 Movimentações'!$B$15:$B$514,"<="&EOMONTH(DATE(YEAR($D$200)+INT((MONTH($D$200)+4-1)/12),MOD(MONTH($D$200)+4-1,12)+1,1),0),'📋 Movimentações'!$E$15:$E$514,"Entrada",'📋 Movimentações'!$D$15:$D$514,"Arubaito/Extra"),0) -> 0 | I16: =IFERROR(SUMIFS('📋 Movimentações'!$F$15:$F$514,'📋 Movimentações'!$B$15:$B$514,">="&DATE(YEAR($D$200)+INT((MONTH($D$200)+5-1)/12),MOD(MONTH($D$200)+5-1,12)+1,1),'📋 Movimentações'!$B$15:$B$514,"<="&EOMONTH(DATE(YEAR($D$200)+INT((MONTH($D$200)+5-1)/12),MOD(MONTH($D$200)+5-1,12)+1,1),0),'📋 Movimentações'!$E$15:$E$514,"Entrada",'📋 Movimentações'!$D$15:$D$514,"Arubaito/Extra"),0) -> 0 | J16: =SUM(D16,E16,F16,G16,H16,I16) -> 0
B17: Reembolso | C17: PREV | D17: 0 | E17: 0 | F17: 0 | G17: 0 | H17: 0 | I17: 0 | J17: =SUM(D17,E17,F17,G17,H17,I17) -> 0
C18: REAL | D18: =IFERROR(SUMIFS('📋 Movimentações'!$F$15:$F$514,'📋 Movimentações'!$B$15:$B$514,">="&DATE(YEAR($D$200)+INT((MONTH($D$200)+0-1)/12),MOD(MONTH($D$200)+0-1,12)+1,1),'📋 Movimentações'!$B$15:$B$514,"<="&EOMONTH(DATE(YEAR($D$200)+INT((MONTH($D$200)+0-1)/12),MOD(MONTH($D$200)+0-1,12)+1,1),0),'📋 Movimentações'!$E$15:$E$514,"Entrada",'📋 Movimentações'!$D$15:$D$514,"Reembolso"),0) -> 0 | E18: =IFERROR(SUMIFS('📋 Movimentações'!$F$15:$F$514,'📋 Movimentações'!$B$15:$B$514,">="&DATE(YEAR($D$200)+INT((MONTH($D$200)+1-1)/12),MOD(MONTH($D$200)+1-1,12)+1,1),'📋 Movimentações'!$B$15:$B$514,"<="&EOMONTH(DATE(YEAR($D$200)+INT((MONTH($D$200)+1-1)/12),MOD(MONTH($D$200)+1-1,12)+1,1),0),'📋 Movimentações'!$E$15:$E$514,"Entrada",'📋 Movimentações'!$D$15:$D$514,"Reembolso"),0) -> 0 | F18: =IFERROR(SUMIFS('📋 Movimentações'!$F$15:$F$514,'📋 Movimentações'!$B$15:$B$514,">="&DATE(YEAR($D$200)+INT((MONTH($D$200)+2-1)/12),MOD(MONTH($D$200)+2-1,12)+1,1),'📋 Movimentações'!$B$15:$B$514,"<="&EOMONTH(DATE(YEAR($D$200)+INT((MONTH($D$200)+2-1)/12),MOD(MONTH($D$200)+2-1,12)+1,1),0),'📋 Movimentações'!$E$15:$E$514,"Entrada",'📋 Movimentações'!$D$15:$D$514,"Reembolso"),0) -> 0 | G18: =IFERROR(SUMIFS('📋 Movimentações'!$F$15:$F$514,'📋 Movimentações'!$B$15:$B$514,">="&DATE(YEAR($D$200)+INT((MONTH($D$200)+3-1)/12),MOD(MONTH($D$200)+3-1,12)+1,1),'📋 Movimentações'!$B$15:$B$514,"<="&EOMONTH(DATE(YEAR($D$200)+INT((MONTH($D$200)+3-1)/12),MOD(MONTH($D$200)+3-1,12)+1,1),0),'📋 Movimentações'!$E$15:$E$514,"Entrada",'📋 Movimentações'!$D$15:$D$514,"Reembolso"),0) -> 0 | H18: =IFERROR(SUMIFS('📋 Movimentações'!$F$15:$F$514,'📋 Movimentações'!$B$15:$B$514,">="&DATE(YEAR($D$200)+INT((MONTH($D$200)+4-1)/12),MOD(MONTH($D$200)+4-1,12)+1,1),'📋 Movimentações'!$B$15:$B$514,"<="&EOMONTH(DATE(YEAR($D$200)+INT((MONTH($D$200)+4-1)/12),MOD(MONTH($D$200)+4-1,12)+1,1),0),'📋 Movimentações'!$E$15:$E$514,"Entrada",'📋 Movimentações'!$D$15:$D$514,"Reembolso"),0) -> 0 | I18: =IFERROR(SUMIFS('📋 Movimentações'!$F$15:$F$514,'📋 Movimentações'!$B$15:$B$514,">="&DATE(YEAR($D$200)+INT((MONTH($D$200)+5-1)/12),MOD(MONTH($D$200)+5-1,12)+1,1),'📋 Movimentações'!$B$15:$B$514,"<="&EOMONTH(DATE(YEAR($D$200)+INT((MONTH($D$200)+5-1)/12),MOD(MONTH($D$200)+5-1,12)+1,1),0),'📋 Movimentações'!$E$15:$E$514,"Entrada",'📋 Movimentações'!$D$15:$D$514,"Reembolso"),0) -> 0 | J18: =SUM(D18,E18,F18,G18,H18,I18) -> 0
B19: TOTAL RENDA | C19: ∑ | D19: =D9+D11+D13+D15+D17 -> 394000 | E19: =E9+E11+E13+E15+E17 -> 0 | F19: =F9+F11+F13+F15+F17 -> 0 | G19: =G9+G11+G13+G15+G17 -> 0 | H19: =H9+H11+H13+H15+H17 -> 0 | I19: =I9+I11+I13+I15+I17 -> 0 | J19: =SUM(D19:I19) -> 394000
C20: REAL | D20: =D10+D12+D14+D16+D18 -> 429000 | E20: =E10+E12+E14+E16+E18 -> 0 | F20: =F10+F12+F14+F16+F18 -> 0 | G20: =G10+G12+G14+G16+G18 -> 0 | H20: =H10+H12+H14+H16+H18 -> 0 | I20: =I10+I12+I14+I16+I18 -> 0 | J20: =SUM(D20:I20) -> 429000
B23: 🏠 GASTOS FIXOS
B24: Aluguel | C24: PREV | D24: ='🏠 Gastos Fixos'!C5 -> 30100 | E24: ='🏠 Gastos Fixos'!C5 -> 30100 | F24: ='🏠 Gastos Fixos'!C5 -> 30100 | G24: ='🏠 Gastos Fixos'!C5 -> 30100 | H24: ='🏠 Gastos Fixos'!C5 -> 30100 | I24: ='🏠 Gastos Fixos'!C5 -> 30100 | J24: ='🏠 Gastos Fixos'!C5*6 -> 180600
C25: REAL | D25: =IFERROR(SUMIFS('📋 Movimentações'!$F$15:$F$514,'📋 Movimentações'!$B$15:$B$514,">="&DATE(YEAR($D$200)+INT((MONTH($D$200)+0-1)/12),MOD(MONTH($D$200)+0-1,12)+1,1),'📋 Movimentações'!$B$15:$B$514,"<="&EOMONTH(DATE(YEAR($D$200)+INT((MONTH($D$200)+0-1)/12),MOD(MONTH($D$200)+0-1,12)+1,1),0),'📋 Movimentações'!$E$15:$E$514,"Saída",'📋 Movimentações'!$D$15:$D$514,"Aluguel"),0) -> 30000 | E25: =IFERROR(SUMIFS('📋 Movimentações'!$F$15:$F$514,'📋 Movimentações'!$B$15:$B$514,">="&DATE(YEAR($D$200)+INT((MONTH($D$200)+1-1)/12),MOD(MONTH($D$200)+1-1,12)+1,1),'📋 Movimentações'!$B$15:$B$514,"<="&EOMONTH(DATE(YEAR($D$200)+INT((MONTH($D$200)+1-1)/12),MOD(MONTH($D$200)+1-1,12)+1,1),0),'📋 Movimentações'!$E$15:$E$514,"Saída",'📋 Movimentações'!$D$15:$D$514,"Aluguel"),0) -> 0 | F25: =IFERROR(SUMIFS('📋 Movimentações'!$F$15:$F$514,'📋 Movimentações'!$B$15:$B$514,">="&DATE(YEAR($D$200)+INT((MONTH($D$200)+2-1)/12),MOD(MONTH($D$200)+2-1,12)+1,1),'📋 Movimentações'!$B$15:$B$514,"<="&EOMONTH(DATE(YEAR($D$200)+INT((MONTH($D$200)+2-1)/12),MOD(MONTH($D$200)+2-1,12)+1,1),0),'📋 Movimentações'!$E$15:$E$514,"Saída",'📋 Movimentações'!$D$15:$D$514,"Aluguel"),0) -> 0 | G25: =IFERROR(SUMIFS('📋 Movimentações'!$F$15:$F$514,'📋 Movimentações'!$B$15:$B$514,">="&DATE(YEAR($D$200)+INT((MONTH($D$200)+3-1)/12),MOD(MONTH($D$200)+3-1,12)+1,1),'📋 Movimentações'!$B$15:$B$514,"<="&EOMONTH(DATE(YEAR($D$200)+INT((MONTH($D$200)+3-1)/12),MOD(MONTH($D$200)+3-1,12)+1,1),0),'📋 Movimentações'!$E$15:$E$514,"Saída",'📋 Movimentações'!$D$15:$D$514,"Aluguel"),0) -> 0 | H25: =IFERROR(SUMIFS('📋 Movimentações'!$F$15:$F$514,'📋 Movimentações'!$B$15:$B$514,">="&DATE(YEAR($D$200)+INT((MONTH($D$200)+4-1)/12),MOD(MONTH($D$200)+4-1,12)+1,1),'📋 Movimentações'!$B$15:$B$514,"<="&EOMONTH(DATE(YEAR($D$200)+INT((MONTH($D$200)+4-1)/12),MOD(MONTH($D$200)+4-1,12)+1,1),0),'📋 Movimentações'!$E$15:$E$514,"Saída",'📋 Movimentações'!$D$15:$D$514,"Aluguel"),0) -> 0 | I25: =IFERROR(SUMIFS('📋 Movimentações'!$F$15:$F$514,'📋 Movimentações'!$B$15:$B$514,">="&DATE(YEAR($D$200)+INT((MONTH($D$200)+5-1)/12),MOD(MONTH($D$200)+5-1,12)+1,1),'📋 Movimentações'!$B$15:$B$514,"<="&EOMONTH(DATE(YEAR($D$200)+INT((MONTH($D$200)+5-1)/12),MOD(MONTH($D$200)+5-1,12)+1,1),0),'📋 Movimentações'!$E$15:$E$514,"Saída",'📋 Movimentações'!$D$15:$D$514,"Aluguel"),0) -> 0 | J25: =SUM(D25,E25,F25,G25,H25,I25) -> 30000
B26: Luz | C26: PREV | D26: ='🏠 Gastos Fixos'!C6 -> 0 | E26: ='🏠 Gastos Fixos'!C6 -> 0 | F26: ='🏠 Gastos Fixos'!C6 -> 0 | G26: ='🏠 Gastos Fixos'!C6 -> 0 | H26: ='🏠 Gastos Fixos'!C6 -> 0 | I26: ='🏠 Gastos Fixos'!C6 -> 0 | J26: ='🏠 Gastos Fixos'!C6*6 -> 0
C27: REAL | D27: =IFERROR(SUMIFS('📋 Movimentações'!$F$15:$F$514,'📋 Movimentações'!$B$15:$B$514,">="&DATE(YEAR($D$200)+INT((MONTH($D$200)+0-1)/12),MOD(MONTH($D$200)+0-1,12)+1,1),'📋 Movimentações'!$B$15:$B$514,"<="&EOMONTH(DATE(YEAR($D$200)+INT((MONTH($D$200)+0-1)/12),MOD(MONTH($D$200)+0-1,12)+1,1),0),'📋 Movimentações'!$E$15:$E$514,"Saída",'📋 Movimentações'!$D$15:$D$514,"Luz"),0) -> 0 | E27: =IFERROR(SUMIFS('📋 Movimentações'!$F$15:$F$514,'📋 Movimentações'!$B$15:$B$514,">="&DATE(YEAR($D$200)+INT((MONTH($D$200)+1-1)/12),MOD(MONTH($D$200)+1-1,12)+1,1),'📋 Movimentações'!$B$15:$B$514,"<="&EOMONTH(DATE(YEAR($D$200)+INT((MONTH($D$200)+1-1)/12),MOD(MONTH($D$200)+1-1,12)+1,1),0),'📋 Movimentações'!$E$15:$E$514,"Saída",'📋 Movimentações'!$D$15:$D$514,"Luz"),0) -> 0 | F27: =IFERROR(SUMIFS('📋 Movimentações'!$F$15:$F$514,'📋 Movimentações'!$B$15:$B$514,">="&DATE(YEAR($D$200)+INT((MONTH($D$200)+2-1)/12),MOD(MONTH($D$200)+2-1,12)+1,1),'📋 Movimentações'!$B$15:$B$514,"<="&EOMONTH(DATE(YEAR($D$200)+INT((MONTH($D$200)+2-1)/12),MOD(MONTH($D$200)+2-1,12)+1,1),0),'📋 Movimentações'!$E$15:$E$514,"Saída",'📋 Movimentações'!$D$15:$D$514,"Luz"),0) -> 0 | G27: =IFERROR(SUMIFS('📋 Movimentações'!$F$15:$F$514,'📋 Movimentações'!$B$15:$B$514,">="&DATE(YEAR($D$200)+INT((MONTH($D$200)+3-1)/12),MOD(MONTH($D$200)+3-1,12)+1,1),'📋 Movimentações'!$B$15:$B$514,"<="&EOMONTH(DATE(YEAR($D$200)+INT((MONTH($D$200)+3-1)/12),MOD(MONTH($D$200)+3-1,12)+1,1),0),'📋 Movimentações'!$E$15:$E$514,"Saída",'📋 Movimentações'!$D$15:$D$514,"Luz"),0) -> 0 | H27: =IFERROR(SUMIFS('📋 Movimentações'!$F$15:$F$514,'📋 Movimentações'!$B$15:$B$514,">="&DATE(YEAR($D$200)+INT((MONTH($D$200)+4-1)/12),MOD(MONTH($D$200)+4-1,12)+1,1),'📋 Movimentações'!$B$15:$B$514,"<="&EOMONTH(DATE(YEAR($D$200)+INT((MONTH($D$200)+4-1)/12),MOD(MONTH($D$200)+4-1,12)+1,1),0),'📋 Movimentações'!$E$15:$E$514,"Saída",'📋 Movimentações'!$D$15:$D$514,"Luz"),0) -> 0 | I27: =IFERROR(SUMIFS('📋 Movimentações'!$F$15:$F$514,'📋 Movimentações'!$B$15:$B$514,">="&DATE(YEAR($D$200)+INT((MONTH($D$200)+5-1)/12),MOD(MONTH($D$200)+5-1,12)+1,1),'📋 Movimentações'!$B$15:$B$514,"<="&EOMONTH(DATE(YEAR($D$200)+INT((MONTH($D$200)+5-1)/12),MOD(MONTH($D$200)+5-1,12)+1,1),0),'📋 Movimentações'!$E$15:$E$514,"Saída",'📋 Movimentações'!$D$15:$D$514,"Luz"),0) -> 0 | J27: =SUM(D27,E27,F27,G27,H27,I27) -> 0
B28: Água | C28: PREV | D28: ='🏠 Gastos Fixos'!C7 -> 8581 | E28: ='🏠 Gastos Fixos'!C7 -> 8581 | F28: ='🏠 Gastos Fixos'!C7 -> 8581 | G28: ='🏠 Gastos Fixos'!C7 -> 8581 | H28: ='🏠 Gastos Fixos'!C7 -> 8581 | I28: ='🏠 Gastos Fixos'!C7 -> 8581 | J28: ='🏠 Gastos Fixos'!C7*6 -> 51486
C29: REAL | D29: =IFERROR(SUMIFS('📋 Movimentações'!$F$15:$F$514,'📋 Movimentações'!$B$15:$B$514,">="&DATE(YEAR($D$200)+INT((MONTH($D$200)+0-1)/12),MOD(MONTH($D$200)+0-1,12)+1,1),'📋 Movimentações'!$B$15:$B$514,"<="&EOMONTH(DATE(YEAR($D$200)+INT((MONTH($D$200)+0-1)/12),MOD(MONTH($D$200)+0-1,12)+1,1),0),'📋 Movimentações'!$E$15:$E$514,"Saída",'📋 Movimentações'!$D$15:$D$514,"Água"),0) -> 0 | E29: =IFERROR(SUMIFS('📋 Movimentações'!$F$15:$F$514,'📋 Movimentações'!$B$15:$B$514,">="&DATE(YEAR($D$200)+INT((MONTH($D$200)+1-1)/12),MOD(MONTH($D$200)+1-1,12)+1,1),'📋 Movimentações'!$B$15:$B$514,"<="&EOMONTH(DATE(YEAR($D$200)+INT((MONTH($D$200)+1-1)/12),MOD(MONTH($D$200)+1-1,12)+1,1),0),'📋 Movimentações'!$E$15:$E$514,"Saída",'📋 Movimentações'!$D$15:$D$514,"Água"),0) -> 0 | F29: =IFERROR(SUMIFS('📋 Movimentações'!$F$15:$F$514,'📋 Movimentações'!$B$15:$B$514,">="&DATE(YEAR($D$200)+INT((MONTH($D$200)+2-1)/12),MOD(MONTH($D$200)+2-1,12)+1,1),'📋 Movimentações'!$B$15:$B$514,"<="&EOMONTH(DATE(YEAR($D$200)+INT((MONTH($D$200)+2-1)/12),MOD(MONTH($D$200)+2-1,12)+1,1),0),'📋 Movimentações'!$E$15:$E$514,"Saída",'📋 Movimentações'!$D$15:$D$514,"Água"),0) -> 0 | G29: =IFERROR(SUMIFS('📋 Movimentações'!$F$15:$F$514,'📋 Movimentações'!$B$15:$B$514,">="&DATE(YEAR($D$200)+INT((MONTH($D$200)+3-1)/12),MOD(MONTH($D$200)+3-1,12)+1,1),'📋 Movimentações'!$B$15:$B$514,"<="&EOMONTH(DATE(YEAR($D$200)+INT((MONTH($D$200)+3-1)/12),MOD(MONTH($D$200)+3-1,12)+1,1),0),'📋 Movimentações'!$E$15:$E$514,"Saída",'📋 Movimentações'!$D$15:$D$514,"Água"),0) -> 0 | H29: =IFERROR(SUMIFS('📋 Movimentações'!$F$15:$F$514,'📋 Movimentações'!$B$15:$B$514,">="&DATE(YEAR($D$200)+INT((MONTH($D$200)+4-1)/12),MOD(MONTH($D$200)+4-1,12)+1,1),'📋 Movimentações'!$B$15:$B$514,"<="&EOMONTH(DATE(YEAR($D$200)+INT((MONTH($D$200)+4-1)/12),MOD(MONTH($D$200)+4-1,12)+1,1),0),'📋 Movimentações'!$E$15:$E$514,"Saída",'📋 Movimentações'!$D$15:$D$514,"Água"),0) -> 0 | I29: =IFERROR(SUMIFS('📋 Movimentações'!$F$15:$F$514,'📋 Movimentações'!$B$15:$B$514,">="&DATE(YEAR($D$200)+INT((MONTH($D$200)+5-1)/12),MOD(MONTH($D$200)+5-1,12)+1,1),'📋 Movimentações'!$B$15:$B$514,"<="&EOMONTH(DATE(YEAR($D$200)+INT((MONTH($D$200)+5-1)/12),MOD(MONTH($D$200)+5-1,12)+1,1),0),'📋 Movimentações'!$E$15:$E$514,"Saída",'📋 Movimentações'!$D$15:$D$514,"Água"),0) -> 0 | J29: =SUM(D29,E29,F29,G29,H29,I29) -> 0
B30: Gás | C30: PREV | D30: ='🏠 Gastos Fixos'!C8 -> 4800 | E30: ='🏠 Gastos Fixos'!C8 -> 4800 | F30: ='🏠 Gastos Fixos'!C8 -> 4800 | G30: ='🏠 Gastos Fixos'!C8 -> 4800 | H30: ='🏠 Gastos Fixos'!C8 -> 4800 | I30: ='🏠 Gastos Fixos'!C8 -> 4800 | J30: ='🏠 Gastos Fixos'!C8*6 -> 28800
C31: REAL | D31: =IFERROR(SUMIFS('📋 Movimentações'!$F$15:$F$514,'📋 Movimentações'!$B$15:$B$514,">="&DATE(YEAR($D$200)+INT((MONTH($D$200)+0-1)/12),MOD(MONTH($D$200)+0-1,12)+1,1),'📋 Movimentações'!$B$15:$B$514,"<="&EOMONTH(DATE(YEAR($D$200)+INT((MONTH($D$200)+0-1)/12),MOD(MONTH($D$200)+0-1,12)+1,1),0),'📋 Movimentações'!$E$15:$E$514,"Saída",'📋 Movimentações'!$D$15:$D$514,"Gás"),0) -> 0 | E31: =IFERROR(SUMIFS('📋 Movimentações'!$F$15:$F$514,'📋 Movimentações'!$B$15:$B$514,">="&DATE(YEAR($D$200)+INT((MONTH($D$200)+1-1)/12),MOD(MONTH($D$200)+1-1,12)+1,1),'📋 Movimentações'!$B$15:$B$514,"<="&EOMONTH(DATE(YEAR($D$200)+INT((MONTH($D$200)+1-1)/12),MOD(MONTH($D$200)+1-1,12)+1,1),0),'📋 Movimentações'!$E$15:$E$514,"Saída",'📋 Movimentações'!$D$15:$D$514,"Gás"),0) -> 0 | F31: =IFERROR(SUMIFS('📋 Movimentações'!$F$15:$F$514,'📋 Movimentações'!$B$15:$B$514,">="&DATE(YEAR($D$200)+INT((MONTH($D$200)+2-1)/12),MOD(MONTH($D$200)+2-1,12)+1,1),'📋 Movimentações'!$B$15:$B$514,"<="&EOMONTH(DATE(YEAR($D$200)+INT((MONTH($D$200)+2-1)/12),MOD(MONTH($D$200)+2-1,12)+1,1),0),'📋 Movimentações'!$E$15:$E$514,"Saída",'📋 Movimentações'!$D$15:$D$514,"Gás"),0) -> 0 | G31: =IFERROR(SUMIFS('📋 Movimentações'!$F$15:$F$514,'📋 Movimentações'!$B$15:$B$514,">="&DATE(YEAR($D$200)+INT((MONTH($D$200)+3-1)/12),MOD(MONTH($D$200)+3-1,12)+1,1),'📋 Movimentações'!$B$15:$B$514,"<="&EOMONTH(DATE(YEAR($D$200)+INT((MONTH($D$200)+3-1)/12),MOD(MONTH($D$200)+3-1,12)+1,1),0),'📋 Movimentações'!$E$15:$E$514,"Saída",'📋 Movimentações'!$D$15:$D$514,"Gás"),0) -> 0 | H31: =IFERROR(SUMIFS('📋 Movimentações'!$F$15:$F$514,'📋 Movimentações'!$B$15:$B$514,">="&DATE(YEAR($D$200)+INT((MONTH($D$200)+4-1)/12),MOD(MONTH($D$200)+4-1,12)+1,1),'📋 Movimentações'!$B$15:$B$514,"<="&EOMONTH(DATE(YEAR($D$200)+INT((MONTH($D$200)+4-1)/12),MOD(MONTH($D$200)+4-1,12)+1,1),0),'📋 Movimentações'!$E$15:$E$514,"Saída",'📋 Movimentações'!$D$15:$D$514,"Gás"),0) -> 0 | I31: =IFERROR(SUMIFS('📋 Movimentações'!$F$15:$F$514,'📋 Movimentações'!$B$15:$B$514,">="&DATE(YEAR($D$200)+INT((MONTH($D$200)+5-1)/12),MOD(MONTH($D$200)+5-1,12)+1,1),'📋 Movimentações'!$B$15:$B$514,"<="&EOMONTH(DATE(YEAR($D$200)+INT((MONTH($D$200)+5-1)/12),MOD(MONTH($D$200)+5-1,12)+1,1),0),'📋 Movimentações'!$E$15:$E$514,"Saída",'📋 Movimentações'!$D$15:$D$514,"Gás"),0) -> 0 | J31: =SUM(D31,E31,F31,G31,H31,I31) -> 0
B32: Internet | C32: PREV | D32: ='🏠 Gastos Fixos'!C9 -> 6000 | E32: ='🏠 Gastos Fixos'!C9 -> 6000 | F32: ='🏠 Gastos Fixos'!C9 -> 6000 | G32: ='🏠 Gastos Fixos'!C9 -> 6000 | H32: ='🏠 Gastos Fixos'!C9 -> 6000 | I32: ='🏠 Gastos Fixos'!C9 -> 6000 | J32: ='🏠 Gastos Fixos'!C9*6 -> 36000
C33: REAL | D33: =IFERROR(SUMIFS('📋 Movimentações'!$F$15:$F$514,'📋 Movimentações'!$B$15:$B$514,">="&DATE(YEAR($D$200)+INT((MONTH($D$200)+0-1)/12),MOD(MONTH($D$200)+0-1,12)+1,1),'📋 Movimentações'!$B$15:$B$514,"<="&EOMONTH(DATE(YEAR($D$200)+INT((MONTH($D$200)+0-1)/12),MOD(MONTH($D$200)+0-1,12)+1,1),0),'📋 Movimentações'!$E$15:$E$514,"Saída",'📋 Movimentações'!$D$15:$D$514,"Internet"),0) -> 0 | E33: =IFERROR(SUMIFS('📋 Movimentações'!$F$15:$F$514,'📋 Movimentações'!$B$15:$B$514,">="&DATE(YEAR($D$200)+INT((MONTH($D$200)+1-1)/12),MOD(MONTH($D$200)+1-1,12)+1,1),'📋 Movimentações'!$B$15:$B$514,"<="&EOMONTH(DATE(YEAR($D$200)+INT((MONTH($D$200)+1-1)/12),MOD(MONTH($D$200)+1-1,12)+1,1),0),'📋 Movimentações'!$E$15:$E$514,"Saída",'📋 Movimentações'!$D$15:$D$514,"Internet"),0) -> 0 | F33: =IFERROR(SUMIFS('📋 Movimentações'!$F$15:$F$514,'📋 Movimentações'!$B$15:$B$514,">="&DATE(YEAR($D$200)+INT((MONTH($D$200)+2-1)/12),MOD(MONTH($D$200)+2-1,12)+1,1),'📋 Movimentações'!$B$15:$B$514,"<="&EOMONTH(DATE(YEAR($D$200)+INT((MONTH($D$200)+2-1)/12),MOD(MONTH($D$200)+2-1,12)+1,1),0),'📋 Movimentações'!$E$15:$E$514,"Saída",'📋 Movimentações'!$D$15:$D$514,"Internet"),0) -> 0 | G33: =IFERROR(SUMIFS('📋 Movimentações'!$F$15:$F$514,'📋 Movimentações'!$B$15:$B$514,">="&DATE(YEAR($D$200)+INT((MONTH($D$200)+3-1)/12),MOD(MONTH($D$200)+3-1,12)+1,1),'📋 Movimentações'!$B$15:$B$514,"<="&EOMONTH(DATE(YEAR($D$200)+INT((MONTH($D$200)+3-1)/12),MOD(MONTH($D$200)+3-1,12)+1,1),0),'📋 Movimentações'!$E$15:$E$514,"Saída",'📋 Movimentações'!$D$15:$D$514,"Internet"),0) -> 0 | H33: =IFERROR(SUMIFS('📋 Movimentações'!$F$15:$F$514,'📋 Movimentações'!$B$15:$B$514,">="&DATE(YEAR($D$200)+INT((MONTH($D$200)+4-1)/12),MOD(MONTH($D$200)+4-1,12)+1,1),'📋 Movimentações'!$B$15:$B$514,"<="&EOMONTH(DATE(YEAR($D$200)+INT((MONTH($D$200)+4-1)/12),MOD(MONTH($D$200)+4-1,12)+1,1),0),'📋 Movimentações'!$E$15:$E$514,"Saída",'📋 Movimentações'!$D$15:$D$514,"Internet"),0) -> 0 | I33: =IFERROR(SUMIFS('📋 Movimentações'!$F$15:$F$514,'📋 Movimentações'!$B$15:$B$514,">="&DATE(YEAR($D$200)+INT((MONTH($D$200)+5-1)/12),MOD(MONTH($D$200)+5-1,12)+1,1),'📋 Movimentações'!$B$15:$B$514,"<="&EOMONTH(DATE(YEAR($D$200)+INT((MONTH($D$200)+5-1)/12),MOD(MONTH($D$200)+5-1,12)+1,1),0),'📋 Movimentações'!$E$15:$E$514,"Saída",'📋 Movimentações'!$D$15:$D$514,"Internet"),0) -> 0 | J33: =SUM(D33,E33,F33,G33,H33,I33) -> 0
B34: Celular | C34: PREV | D34: ='🏠 Gastos Fixos'!C10 -> 32412 | E34: ='🏠 Gastos Fixos'!C10 -> 32412 | F34: ='🏠 Gastos Fixos'!C10 -> 32412 | G34: ='🏠 Gastos Fixos'!C10 -> 32412 | H34: ='🏠 Gastos Fixos'!C10 -> 32412 | I34: ='🏠 Gastos Fixos'!C10 -> 32412 | J34: ='🏠 Gastos Fixos'!C10*6 -> 194472
C35: REAL | D35: =IFERROR(SUMIFS('📋 Movimentações'!$F$15:$F$514,'📋 Movimentações'!$B$15:$B$514,">="&DATE(YEAR($D$200)+INT((MONTH($D$200)+0-1)/12),MOD(MONTH($D$200)+0-1,12)+1,1),'📋 Movimentações'!$B$15:$B$514,"<="&EOMONTH(DATE(YEAR($D$200)+INT((MONTH($D$200)+0-1)/12),MOD(MONTH($D$200)+0-1,12)+1,1),0),'📋 Movimentações'!$E$15:$E$514,"Saída",'📋 Movimentações'!$D$15:$D$514,"Celular"),0) -> 32412 | E35: =IFERROR(SUMIFS('📋 Movimentações'!$F$15:$F$514,'📋 Movimentações'!$B$15:$B$514,">="&DATE(YEAR($D$200)+INT((MONTH($D$200)+1-1)/12),MOD(MONTH($D$200)+1-1,12)+1,1),'📋 Movimentações'!$B$15:$B$514,"<="&EOMONTH(DATE(YEAR($D$200)+INT((MONTH($D$200)+1-1)/12),MOD(MONTH($D$200)+1-1,12)+1,1),0),'📋 Movimentações'!$E$15:$E$514,"Saída",'📋 Movimentações'!$D$15:$D$514,"Celular"),0) -> 0 | F35: =IFERROR(SUMIFS('📋 Movimentações'!$F$15:$F$514,'📋 Movimentações'!$B$15:$B$514,">="&DATE(YEAR($D$200)+INT((MONTH($D$200)+2-1)/12),MOD(MONTH($D$200)+2-1,12)+1,1),'📋 Movimentações'!$B$15:$B$514,"<="&EOMONTH(DATE(YEAR($D$200)+INT((MONTH($D$200)+2-1)/12),MOD(MONTH($D$200)+2-1,12)+1,1),0),'📋 Movimentações'!$E$15:$E$514,"Saída",'📋 Movimentações'!$D$15:$D$514,"Celular"),0) -> 0 | G35: =IFERROR(SUMIFS('📋 Movimentações'!$F$15:$F$514,'📋 Movimentações'!$B$15:$B$514,">="&DATE(YEAR($D$200)+INT((MONTH($D$200)+3-1)/12),MOD(MONTH($D$200)+3-1,12)+1,1),'📋 Movimentações'!$B$15:$B$514,"<="&EOMONTH(DATE(YEAR($D$200)+INT((MONTH($D$200)+3-1)/12),MOD(MONTH($D$200)+3-1,12)+1,1),0),'📋 Movimentações'!$E$15:$E$514,"Saída",'📋 Movimentações'!$D$15:$D$514,"Celular"),0) -> 0 | H35: =IFERROR(SUMIFS('📋 Movimentações'!$F$15:$F$514,'📋 Movimentações'!$B$15:$B$514,">="&DATE(YEAR($D$200)+INT((MONTH($D$200)+4-1)/12),MOD(MONTH($D$200)+4-1,12)+1,1),'📋 Movimentações'!$B$15:$B$514,"<="&EOMONTH(DATE(YEAR($D$200)+INT((MONTH($D$200)+4-1)/12),MOD(MONTH($D$200)+4-1,12)+1,1),0),'📋 Movimentações'!$E$15:$E$514,"Saída",'📋 Movimentações'!$D$15:$D$514,"Celular"),0) -> 0 | I35: =IFERROR(SUMIFS('📋 Movimentações'!$F$15:$F$514,'📋 Movimentações'!$B$15:$B$514,">="&DATE(YEAR($D$200)+INT((MONTH($D$200)+5-1)/12),MOD(MONTH($D$200)+5-1,12)+1,1),'📋 Movimentações'!$B$15:$B$514,"<="&EOMONTH(DATE(YEAR($D$200)+INT((MONTH($D$200)+5-1)/12),MOD(MONTH($D$200)+5-1,12)+1,1),0),'📋 Movimentações'!$E$15:$E$514,"Saída",'📋 Movimentações'!$D$15:$D$514,"Celular"),0) -> 0 | J35: =SUM(D35,E35,F35,G35,H35,I35) -> 32412
B36: Academia | C36: PREV | D36: ='🏠 Gastos Fixos'!C11 -> 6000 | E36: ='🏠 Gastos Fixos'!C11 -> 6000 | F36: ='🏠 Gastos Fixos'!C11 -> 6000 | G36: ='🏠 Gastos Fixos'!C11 -> 6000 | H36: ='🏠 Gastos Fixos'!C11 -> 6000 | I36: ='🏠 Gastos Fixos'!C11 -> 6000 | J36: ='🏠 Gastos Fixos'!C11*6 -> 36000
C37: REAL | D37: =IFERROR(SUMIFS('📋 Movimentações'!$F$15:$F$514,'📋 Movimentações'!$B$15:$B$514,">="&DATE(YEAR($D$200)+INT((MONTH($D$200)+0-1)/12),MOD(MONTH($D$200)+0-1,12)+1,1),'📋 Movimentações'!$B$15:$B$514,"<="&EOMONTH(DATE(YEAR($D$200)+INT((MONTH($D$200)+0-1)/12),MOD(MONTH($D$200)+0-1,12)+1,1),0),'📋 Movimentações'!$E$15:$E$514,"Saída",'📋 Movimentações'!$D$15:$D$514,"Academia"),0) -> 6000 | E37: =IFERROR(SUMIFS('📋 Movimentações'!$F$15:$F$514,'📋 Movimentações'!$B$15:$B$514,">="&DATE(YEAR($D$200)+INT((MONTH($D$200)+1-1)/12),MOD(MONTH($D$200)+1-1,12)+1,1),'📋 Movimentações'!$B$15:$B$514,"<="&EOMONTH(DATE(YEAR($D$200)+INT((MONTH($D$200)+1-1)/12),MOD(MONTH($D$200)+1-1,12)+1,1),0),'📋 Movimentações'!$E$15:$E$514,"Saída",'📋 Movimentações'!$D$15:$D$514,"Academia"),0) -> 0 | F37: =IFERROR(SUMIFS('📋 Movimentações'!$F$15:$F$514,'📋 Movimentações'!$B$15:$B$514,">="&DATE(YEAR($D$200)+INT((MONTH($D$200)+2-1)/12),MOD(MONTH($D$200)+2-1,12)+1,1),'📋 Movimentações'!$B$15:$B$514,"<="&EOMONTH(DATE(YEAR($D$200)+INT((MONTH($D$200)+2-1)/12),MOD(MONTH($D$200)+2-1,12)+1,1),0),'📋 Movimentações'!$E$15:$E$514,"Saída",'📋 Movimentações'!$D$15:$D$514,"Academia"),0) -> 0 | G37: =IFERROR(SUMIFS('📋 Movimentações'!$F$15:$F$514,'📋 Movimentações'!$B$15:$B$514,">="&DATE(YEAR($D$200)+INT((MONTH($D$200)+3-1)/12),MOD(MONTH($D$200)+3-1,12)+1,1),'📋 Movimentações'!$B$15:$B$514,"<="&EOMONTH(DATE(YEAR($D$200)+INT((MONTH($D$200)+3-1)/12),MOD(MONTH($D$200)+3-1,12)+1,1),0),'📋 Movimentações'!$E$15:$E$514,"Saída",'📋 Movimentações'!$D$15:$D$514,"Academia"),0) -> 0 | H37: =IFERROR(SUMIFS('📋 Movimentações'!$F$15:$F$514,'📋 Movimentações'!$B$15:$B$514,">="&DATE(YEAR($D$200)+INT((MONTH($D$200)+4-1)/12),MOD(MONTH($D$200)+4-1,12)+1,1),'📋 Movimentações'!$B$15:$B$514,"<="&EOMONTH(DATE(YEAR($D$200)+INT((MONTH($D$200)+4-1)/12),MOD(MONTH($D$200)+4-1,12)+1,1),0),'📋 Movimentações'!$E$15:$E$514,"Saída",'📋 Movimentações'!$D$15:$D$514,"Academia"),0) -> 0 | I37: =IFERROR(SUMIFS('📋 Movimentações'!$F$15:$F$514,'📋 Movimentações'!$B$15:$B$514,">="&DATE(YEAR($D$200)+INT((MONTH($D$200)+5-1)/12),MOD(MONTH($D$200)+5-1,12)+1,1),'📋 Movimentações'!$B$15:$B$514,"<="&EOMONTH(DATE(YEAR($D$200)+INT((MONTH($D$200)+5-1)/12),MOD(MONTH($D$200)+5-1,12)+1,1),0),'📋 Movimentações'!$E$15:$E$514,"Saída",'📋 Movimentações'!$D$15:$D$514,"Academia"),0) -> 0 | J37: =SUM(D37,E37,F37,G37,H37,I37) -> 6000
B38: Seguro de Vida | C38: PREV | D38: ='🏠 Gastos Fixos'!C12 -> 0 | E38: ='🏠 Gastos Fixos'!C12 -> 0 | F38: ='🏠 Gastos Fixos'!C12 -> 0 | G38: ='🏠 Gastos Fixos'!C12 -> 0 | H38: ='🏠 Gastos Fixos'!C12 -> 0 | I38: ='🏠 Gastos Fixos'!C12 -> 0 | J38: ='🏠 Gastos Fixos'!C12*6 -> 0
C39: REAL | D39: =IFERROR(SUMIFS('📋 Movimentações'!$F$15:$F$514,'📋 Movimentações'!$B$15:$B$514,">="&DATE(YEAR($D$200)+INT((MONTH($D$200)+0-1)/12),MOD(MONTH($D$200)+0-1,12)+1,1),'📋 Movimentações'!$B$15:$B$514,"<="&EOMONTH(DATE(YEAR($D$200)+INT((MONTH($D$200)+0-1)/12),MOD(MONTH($D$200)+0-1,12)+1,1),0),'📋 Movimentações'!$E$15:$E$514,"Saída",'📋 Movimentações'!$D$15:$D$514,"Saúde"),0) -> 0 | E39: =IFERROR(SUMIFS('📋 Movimentações'!$F$15:$F$514,'📋 Movimentações'!$B$15:$B$514,">="&DATE(YEAR($D$200)+INT((MONTH($D$200)+1-1)/12),MOD(MONTH($D$200)+1-1,12)+1,1),'📋 Movimentações'!$B$15:$B$514,"<="&EOMONTH(DATE(YEAR($D$200)+INT((MONTH($D$200)+1-1)/12),MOD(MONTH($D$200)+1-1,12)+1,1),0),'📋 Movimentações'!$E$15:$E$514,"Saída",'📋 Movimentações'!$D$15:$D$514,"Saúde"),0) -> 0 | F39: =IFERROR(SUMIFS('📋 Movimentações'!$F$15:$F$514,'📋 Movimentações'!$B$15:$B$514,">="&DATE(YEAR($D$200)+INT((MONTH($D$200)+2-1)/12),MOD(MONTH($D$200)+2-1,12)+1,1),'📋 Movimentações'!$B$15:$B$514,"<="&EOMONTH(DATE(YEAR($D$200)+INT((MONTH($D$200)+2-1)/12),MOD(MONTH($D$200)+2-1,12)+1,1),0),'📋 Movimentações'!$E$15:$E$514,"Saída",'📋 Movimentações'!$D$15:$D$514,"Saúde"),0) -> 0 | G39: =IFERROR(SUMIFS('📋 Movimentações'!$F$15:$F$514,'📋 Movimentações'!$B$15:$B$514,">="&DATE(YEAR($D$200)+INT((MONTH($D$200)+3-1)/12),MOD(MONTH($D$200)+3-1,12)+1,1),'📋 Movimentações'!$B$15:$B$514,"<="&EOMONTH(DATE(YEAR($D$200)+INT((MONTH($D$200)+3-1)/12),MOD(MONTH($D$200)+3-1,12)+1,1),0),'📋 Movimentações'!$E$15:$E$514,"Saída",'📋 Movimentações'!$D$15:$D$514,"Saúde"),0) -> 0 | H39: =IFERROR(SUMIFS('📋 Movimentações'!$F$15:$F$514,'📋 Movimentações'!$B$15:$B$514,">="&DATE(YEAR($D$200)+INT((MONTH($D$200)+4-1)/12),MOD(MONTH($D$200)+4-1,12)+1,1),'📋 Movimentações'!$B$15:$B$514,"<="&EOMONTH(DATE(YEAR($D$200)+INT((MONTH($D$200)+4-1)/12),MOD(MONTH($D$200)+4-1,12)+1,1),0),'📋 Movimentações'!$E$15:$E$514,"Saída",'📋 Movimentações'!$D$15:$D$514,"Saúde"),0) -> 0 | I39: =IFERROR(SUMIFS('📋 Movimentações'!$F$15:$F$514,'📋 Movimentações'!$B$15:$B$514,">="&DATE(YEAR($D$200)+INT((MONTH($D$200)+5-1)/12),MOD(MONTH($D$200)+5-1,12)+1,1),'📋 Movimentações'!$B$15:$B$514,"<="&EOMONTH(DATE(YEAR($D$200)+INT((MONTH($D$200)+5-1)/12),MOD(MONTH($D$200)+5-1,12)+1,1),0),'📋 Movimentações'!$E$15:$E$514,"Saída",'📋 Movimentações'!$D$15:$D$514,"Saúde"),0) -> 0 | J39: =SUM(D39,E39,F39,G39,H39,I39) -> 0
B40: Seguro do Carro | C40: PREV | D40: ='🏠 Gastos Fixos'!C13 -> 16000 | E40: ='🏠 Gastos Fixos'!C13 -> 16000 | F40: ='🏠 Gastos Fixos'!C13 -> 16000 | G40: ='🏠 Gastos Fixos'!C13 -> 16000 | H40: ='🏠 Gastos Fixos'!C13 -> 16000 | I40: ='🏠 Gastos Fixos'!C13 -> 16000 | J40: ='🏠 Gastos Fixos'!C13*6 -> 96000
C41: REAL | D41: =IFERROR(SUMIFS('📋 Movimentações'!$F$15:$F$514,'📋 Movimentações'!$B$15:$B$514,">="&DATE(YEAR($D$200)+INT((MONTH($D$200)+0-1)/12),MOD(MONTH($D$200)+0-1,12)+1,1),'📋 Movimentações'!$B$15:$B$514,"<="&EOMONTH(DATE(YEAR($D$200)+INT((MONTH($D$200)+0-1)/12),MOD(MONTH($D$200)+0-1,12)+1,1),0),'📋 Movimentações'!$E$15:$E$514,"Saída",'📋 Movimentações'!$D$15:$D$514,"Seguro do Carro"),0) -> 0 | E41: =IFERROR(SUMIFS('📋 Movimentações'!$F$15:$F$514,'📋 Movimentações'!$B$15:$B$514,">="&DATE(YEAR($D$200)+INT((MONTH($D$200)+1-1)/12),MOD(MONTH($D$200)+1-1,12)+1,1),'📋 Movimentações'!$B$15:$B$514,"<="&EOMONTH(DATE(YEAR($D$200)+INT((MONTH($D$200)+1-1)/12),MOD(MONTH($D$200)+1-1,12)+1,1),0),'📋 Movimentações'!$E$15:$E$514,"Saída",'📋 Movimentações'!$D$15:$D$514,"Seguro do Carro"),0) -> 0 | F41: =IFERROR(SUMIFS('📋 Movimentações'!$F$15:$F$514,'📋 Movimentações'!$B$15:$B$514,">="&DATE(YEAR($D$200)+INT((MONTH($D$200)+2-1)/12),MOD(MONTH($D$200)+2-1,12)+1,1),'📋 Movimentações'!$B$15:$B$514,"<="&EOMONTH(DATE(YEAR($D$200)+INT((MONTH($D$200)+2-1)/12),MOD(MONTH($D$200)+2-1,12)+1,1),0),'📋 Movimentações'!$E$15:$E$514,"Saída",'📋 Movimentações'!$D$15:$D$514,"Seguro do Carro"),0) -> 0 | G41: =IFERROR(SUMIFS('📋 Movimentações'!$F$15:$F$514,'📋 Movimentações'!$B$15:$B$514,">="&DATE(YEAR($D$200)+INT((MONTH($D$200)+3-1)/12),MOD(MONTH($D$200)+3-1,12)+1,1),'📋 Movimentações'!$B$15:$B$514,"<="&EOMONTH(DATE(YEAR($D$200)+INT((MONTH($D$200)+3-1)/12),MOD(MONTH($D$200)+3-1,12)+1,1),0),'📋 Movimentações'!$E$15:$E$514,"Saída",'📋 Movimentações'!$D$15:$D$514,"Seguro do Carro"),0) -> 0 | H41: =IFERROR(SUMIFS('📋 Movimentações'!$F$15:$F$514,'📋 Movimentações'!$B$15:$B$514,">="&DATE(YEAR($D$200)+INT((MONTH($D$200)+4-1)/12),MOD(MONTH($D$200)+4-1,12)+1,1),'📋 Movimentações'!$B$15:$B$514,"<="&EOMONTH(DATE(YEAR($D$200)+INT((MONTH($D$200)+4-1)/12),MOD(MONTH($D$200)+4-1,12)+1,1),0),'📋 Movimentações'!$E$15:$E$514,"Saída",'📋 Movimentações'!$D$15:$D$514,"Seguro do Carro"),0) -> 0 | I41: =IFERROR(SUMIFS('📋 Movimentações'!$F$15:$F$514,'📋 Movimentações'!$B$15:$B$514,">="&DATE(YEAR($D$200)+INT((MONTH($D$200)+5-1)/12),MOD(MONTH($D$200)+5-1,12)+1,1),'📋 Movimentações'!$B$15:$B$514,"<="&EOMONTH(DATE(YEAR($D$200)+INT((MONTH($D$200)+5-1)/12),MOD(MONTH($D$200)+5-1,12)+1,1),0),'📋 Movimentações'!$E$15:$E$514,"Saída",'📋 Movimentações'!$D$15:$D$514,"Seguro do Carro"),0) -> 0 | J41: =SUM(D41,E41,F41,G41,H41,I41) -> 0
B42: Netflix / Disney+ | C42: PREV | D42: ='🏠 Gastos Fixos'!C14 -> 1000 | E42: ='🏠 Gastos Fixos'!C14 -> 1000 | F42: ='🏠 Gastos Fixos'!C14 -> 1000 | G42: ='🏠 Gastos Fixos'!C14 -> 1000 | H42: ='🏠 Gastos Fixos'!C14 -> 1000 | I42: ='🏠 Gastos Fixos'!C14 -> 1000 | J42: ='🏠 Gastos Fixos'!C14*6 -> 6000
C43: REAL | D43: =IFERROR(SUMIFS('📋 Movimentações'!$F$15:$F$514,'📋 Movimentações'!$B$15:$B$514,">="&DATE(YEAR($D$200)+INT((MONTH($D$200)+0-1)/12),MOD(MONTH($D$200)+0-1,12)+1,1),'📋 Movimentações'!$B$15:$B$514,"<="&EOMONTH(DATE(YEAR($D$200)+INT((MONTH($D$200)+0-1)/12),MOD(MONTH($D$200)+0-1,12)+1,1),0),'📋 Movimentações'!$E$15:$E$514,"Saída",'📋 Movimentações'!$D$15:$D$514,"Assinatura"),0) -> 0 | E43: =IFERROR(SUMIFS('📋 Movimentações'!$F$15:$F$514,'📋 Movimentações'!$B$15:$B$514,">="&DATE(YEAR($D$200)+INT((MONTH($D$200)+1-1)/12),MOD(MONTH($D$200)+1-1,12)+1,1),'📋 Movimentações'!$B$15:$B$514,"<="&EOMONTH(DATE(YEAR($D$200)+INT((MONTH($D$200)+1-1)/12),MOD(MONTH($D$200)+1-1,12)+1,1),0),'📋 Movimentações'!$E$15:$E$514,"Saída",'📋 Movimentações'!$D$15:$D$514,"Assinatura"),0) -> 0 | F43: =IFERROR(SUMIFS('📋 Movimentações'!$F$15:$F$514,'📋 Movimentações'!$B$15:$B$514,">="&DATE(YEAR($D$200)+INT((MONTH($D$200)+2-1)/12),MOD(MONTH($D$200)+2-1,12)+1,1),'📋 Movimentações'!$B$15:$B$514,"<="&EOMONTH(DATE(YEAR($D$200)+INT((MONTH($D$200)+2-1)/12),MOD(MONTH($D$200)+2-1,12)+1,1),0),'📋 Movimentações'!$E$15:$E$514,"Saída",'📋 Movimentações'!$D$15:$D$514,"Assinatura"),0) -> 0 | G43: =IFERROR(SUMIFS('📋 Movimentações'!$F$15:$F$514,'📋 Movimentações'!$B$15:$B$514,">="&DATE(YEAR($D$200)+INT((MONTH($D$200)+3-1)/12),MOD(MONTH($D$200)+3-1,12)+1,1),'📋 Movimentações'!$B$15:$B$514,"<="&EOMONTH(DATE(YEAR($D$200)+INT((MONTH($D$200)+3-1)/12),MOD(MONTH($D$200)+3-1,12)+1,1),0),'📋 Movimentações'!$E$15:$E$514,"Saída",'📋 Movimentações'!$D$15:$D$514,"Assinatura"),0) -> 0 | H43: =IFERROR(SUMIFS('📋 Movimentações'!$F$15:$F$514,'📋 Movimentações'!$B$15:$B$514,">="&DATE(YEAR($D$200)+INT((MONTH($D$200)+4-1)/12),MOD(MONTH($D$200)+4-1,12)+1,1),'📋 Movimentações'!$B$15:$B$514,"<="&EOMONTH(DATE(YEAR($D$200)+INT((MONTH($D$200)+4-1)/12),MOD(MONTH($D$200)+4-1,12)+1,1),0),'📋 Movimentações'!$E$15:$E$514,"Saída",'📋 Movimentações'!$D$15:$D$514,"Assinatura"),0) -> 0 | I43: =IFERROR(SUMIFS('📋 Movimentações'!$F$15:$F$514,'📋 Movimentações'!$B$15:$B$514,">="&DATE(YEAR($D$200)+INT((MONTH($D$200)+5-1)/12),MOD(MONTH($D$200)+5-1,12)+1,1),'📋 Movimentações'!$B$15:$B$514,"<="&EOMONTH(DATE(YEAR($D$200)+INT((MONTH($D$200)+5-1)/12),MOD(MONTH($D$200)+5-1,12)+1,1),0),'📋 Movimentações'!$E$15:$E$514,"Saída",'📋 Movimentações'!$D$15:$D$514,"Assinatura"),0) -> 0 | J43: =SUM(D43,E43,F43,G43,H43,I43) -> 0
B44: Spotify | C44: PREV | D44: ='🏠 Gastos Fixos'!C15 -> 0 | E44: ='🏠 Gastos Fixos'!C15 -> 0 | F44: ='🏠 Gastos Fixos'!C15 -> 0 | G44: ='🏠 Gastos Fixos'!C15 -> 0 | H44: ='🏠 Gastos Fixos'!C15 -> 0 | I44: ='🏠 Gastos Fixos'!C15 -> 0 | J44: ='🏠 Gastos Fixos'!C15*6 -> 0
C45: REAL | D45: =IFERROR(SUMIFS('📋 Movimentações'!$F$15:$F$514,'📋 Movimentações'!$B$15:$B$514,">="&DATE(YEAR($D$200)+INT((MONTH($D$200)+0-1)/12),MOD(MONTH($D$200)+0-1,12)+1,1),'📋 Movimentações'!$B$15:$B$514,"<="&EOMONTH(DATE(YEAR($D$200)+INT((MONTH($D$200)+0-1)/12),MOD(MONTH($D$200)+0-1,12)+1,1),0),'📋 Movimentações'!$E$15:$E$514,"Saída",'📋 Movimentações'!$D$15:$D$514,"Assinatura"),0) -> 0 | E45: =IFERROR(SUMIFS('📋 Movimentações'!$F$15:$F$514,'📋 Movimentações'!$B$15:$B$514,">="&DATE(YEAR($D$200)+INT((MONTH($D$200)+1-1)/12),MOD(MONTH($D$200)+1-1,12)+1,1),'📋 Movimentações'!$B$15:$B$514,"<="&EOMONTH(DATE(YEAR($D$200)+INT((MONTH($D$200)+1-1)/12),MOD(MONTH($D$200)+1-1,12)+1,1),0),'📋 Movimentações'!$E$15:$E$514,"Saída",'📋 Movimentações'!$D$15:$D$514,"Assinatura"),0) -> 0 | F45: =IFERROR(SUMIFS('📋 Movimentações'!$F$15:$F$514,'📋 Movimentações'!$B$15:$B$514,">="&DATE(YEAR($D$200)+INT((MONTH($D$200)+2-1)/12),MOD(MONTH($D$200)+2-1,12)+1,1),'📋 Movimentações'!$B$15:$B$514,"<="&EOMONTH(DATE(YEAR($D$200)+INT((MONTH($D$200)+2-1)/12),MOD(MONTH($D$200)+2-1,12)+1,1),0),'📋 Movimentações'!$E$15:$E$514,"Saída",'📋 Movimentações'!$D$15:$D$514,"Assinatura"),0) -> 0 | G45: =IFERROR(SUMIFS('📋 Movimentações'!$F$15:$F$514,'📋 Movimentações'!$B$15:$B$514,">="&DATE(YEAR($D$200)+INT((MONTH($D$200)+3-1)/12),MOD(MONTH($D$200)+3-1,12)+1,1),'📋 Movimentações'!$B$15:$B$514,"<="&EOMONTH(DATE(YEAR($D$200)+INT((MONTH($D$200)+3-1)/12),MOD(MONTH($D$200)+3-1,12)+1,1),0),'📋 Movimentações'!$E$15:$E$514,"Saída",'📋 Movimentações'!$D$15:$D$514,"Assinatura"),0) -> 0 | H45: =IFERROR(SUMIFS('📋 Movimentações'!$F$15:$F$514,'📋 Movimentações'!$B$15:$B$514,">="&DATE(YEAR($D$200)+INT((MONTH($D$200)+4-1)/12),MOD(MONTH($D$200)+4-1,12)+1,1),'📋 Movimentações'!$B$15:$B$514,"<="&EOMONTH(DATE(YEAR($D$200)+INT((MONTH($D$200)+4-1)/12),MOD(MONTH($D$200)+4-1,12)+1,1),0),'📋 Movimentações'!$E$15:$E$514,"Saída",'📋 Movimentações'!$D$15:$D$514,"Assinatura"),0) -> 0 | I45: =IFERROR(SUMIFS('📋 Movimentações'!$F$15:$F$514,'📋 Movimentações'!$B$15:$B$514,">="&DATE(YEAR($D$200)+INT((MONTH($D$200)+5-1)/12),MOD(MONTH($D$200)+5-1,12)+1,1),'📋 Movimentações'!$B$15:$B$514,"<="&EOMONTH(DATE(YEAR($D$200)+INT((MONTH($D$200)+5-1)/12),MOD(MONTH($D$200)+5-1,12)+1,1),0),'📋 Movimentações'!$E$15:$E$514,"Saída",'📋 Movimentações'!$D$15:$D$514,"Assinatura"),0) -> 0 | J45: =SUM(D45,E45,F45,G45,H45,I45) -> 0
B46: Escola / Creche | C46: PREV | D46: ='🏠 Gastos Fixos'!C16 -> 8000 | E46: ='🏠 Gastos Fixos'!C16 -> 8000 | F46: ='🏠 Gastos Fixos'!C16 -> 8000 | G46: ='🏠 Gastos Fixos'!C16 -> 8000 | H46: ='🏠 Gastos Fixos'!C16 -> 8000 | I46: ='🏠 Gastos Fixos'!C16 -> 8000 | J46: ='🏠 Gastos Fixos'!C16*6 -> 48000
C47: REAL | D47: =IFERROR(SUMIFS('📋 Movimentações'!$F$15:$F$514,'📋 Movimentações'!$B$15:$B$514,">="&DATE(YEAR($D$200)+INT((MONTH($D$200)+0-1)/12),MOD(MONTH($D$200)+0-1,12)+1,1),'📋 Movimentações'!$B$15:$B$514,"<="&EOMONTH(DATE(YEAR($D$200)+INT((MONTH($D$200)+0-1)/12),MOD(MONTH($D$200)+0-1,12)+1,1),0),'📋 Movimentações'!$E$15:$E$514,"Saída",'📋 Movimentações'!$D$15:$D$514,"Escola/Creche"),0) -> 0 | E47: =IFERROR(SUMIFS('📋 Movimentações'!$F$15:$F$514,'📋 Movimentações'!$B$15:$B$514,">="&DATE(YEAR($D$200)+INT((MONTH($D$200)+1-1)/12),MOD(MONTH($D$200)+1-1,12)+1,1),'📋 Movimentações'!$B$15:$B$514,"<="&EOMONTH(DATE(YEAR($D$200)+INT((MONTH($D$200)+1-1)/12),MOD(MONTH($D$200)+1-1,12)+1,1),0),'📋 Movimentações'!$E$15:$E$514,"Saída",'📋 Movimentações'!$D$15:$D$514,"Escola/Creche"),0) -> 0 | F47: =IFERROR(SUMIFS('📋 Movimentações'!$F$15:$F$514,'📋 Movimentações'!$B$15:$B$514,">="&DATE(YEAR($D$200)+INT((MONTH($D$200)+2-1)/12),MOD(MONTH($D$200)+2-1,12)+1,1),'📋 Movimentações'!$B$15:$B$514,"<="&EOMONTH(DATE(YEAR($D$200)+INT((MONTH($D$200)+2-1)/12),MOD(MONTH($D$200)+2-1,12)+1,1),0),'📋 Movimentações'!$E$15:$E$514,"Saída",'📋 Movimentações'!$D$15:$D$514,"Escola/Creche"),0) -> 0 | G47: =IFERROR(SUMIFS('📋 Movimentações'!$F$15:$F$514,'📋 Movimentações'!$B$15:$B$514,">="&DATE(YEAR($D$200)+INT((MONTH($D$200)+3-1)/12),MOD(MONTH($D$200)+3-1,12)+1,1),'📋 Movimentações'!$B$15:$B$514,"<="&EOMONTH(DATE(YEAR($D$200)+INT((MONTH($D$200)+3-1)/12),MOD(MONTH($D$200)+3-1,12)+1,1),0),'📋 Movimentações'!$E$15:$E$514,"Saída",'📋 Movimentações'!$D$15:$D$514,"Escola/Creche"),0) -> 0 | H47: =IFERROR(SUMIFS('📋 Movimentações'!$F$15:$F$514,'📋 Movimentações'!$B$15:$B$514,">="&DATE(YEAR($D$200)+INT((MONTH($D$200)+4-1)/12),MOD(MONTH($D$200)+4-1,12)+1,1),'📋 Movimentações'!$B$15:$B$514,"<="&EOMONTH(DATE(YEAR($D$200)+INT((MONTH($D$200)+4-1)/12),MOD(MONTH($D$200)+4-1,12)+1,1),0),'📋 Movimentações'!$E$15:$E$514,"Saída",'📋 Movimentações'!$D$15:$D$514,"Escola/Creche"),0) -> 0 | I47: =IFERROR(SUMIFS('📋 Movimentações'!$F$15:$F$514,'📋 Movimentações'!$B$15:$B$514,">="&DATE(YEAR($D$200)+INT((MONTH($D$200)+5-1)/12),MOD(MONTH($D$200)+5-1,12)+1,1),'📋 Movimentações'!$B$15:$B$514,"<="&EOMONTH(DATE(YEAR($D$200)+INT((MONTH($D$200)+5-1)/12),MOD(MONTH($D$200)+5-1,12)+1,1),0),'📋 Movimentações'!$E$15:$E$514,"Saída",'📋 Movimentações'!$D$15:$D$514,"Escola/Creche"),0) -> 0 | J47: =SUM(D47,E47,F47,G47,H47,I47) -> 0
B48: Financiamento | C48: PREV | D48: ='🏠 Gastos Fixos'!C17 -> 43160 | E48: ='🏠 Gastos Fixos'!C17 -> 43160 | F48: ='🏠 Gastos Fixos'!C17 -> 43160 | G48: ='🏠 Gastos Fixos'!C17 -> 43160 | H48: ='🏠 Gastos Fixos'!C17 -> 43160 | I48: ='🏠 Gastos Fixos'!C17 -> 43160 | J48: ='🏠 Gastos Fixos'!C17*6 -> 258960
C49: REAL | D49: =IFERROR(SUMIFS('📋 Movimentações'!$F$15:$F$514,'📋 Movimentações'!$B$15:$B$514,">="&DATE(YEAR($D$200)+INT((MONTH($D$200)+0-1)/12),MOD(MONTH($D$200)+0-1,12)+1,1),'📋 Movimentações'!$B$15:$B$514,"<="&EOMONTH(DATE(YEAR($D$200)+INT((MONTH($D$200)+0-1)/12),MOD(MONTH($D$200)+0-1,12)+1,1),0),'📋 Movimentações'!$E$15:$E$514,"Saída",'📋 Movimentações'!$D$15:$D$514,"Outros"),0) -> 0 | E49: =IFERROR(SUMIFS('📋 Movimentações'!$F$15:$F$514,'📋 Movimentações'!$B$15:$B$514,">="&DATE(YEAR($D$200)+INT((MONTH($D$200)+1-1)/12),MOD(MONTH($D$200)+1-1,12)+1,1),'📋 Movimentações'!$B$15:$B$514,"<="&EOMONTH(DATE(YEAR($D$200)+INT((MONTH($D$200)+1-1)/12),MOD(MONTH($D$200)+1-1,12)+1,1),0),'📋 Movimentações'!$E$15:$E$514,"Saída",'📋 Movimentações'!$D$15:$D$514,"Outros"),0) -> 0 | F49: =IFERROR(SUMIFS('📋 Movimentações'!$F$15:$F$514,'📋 Movimentações'!$B$15:$B$514,">="&DATE(YEAR($D$200)+INT((MONTH($D$200)+2-1)/12),MOD(MONTH($D$200)+2-1,12)+1,1),'📋 Movimentações'!$B$15:$B$514,"<="&EOMONTH(DATE(YEAR($D$200)+INT((MONTH($D$200)+2-1)/12),MOD(MONTH($D$200)+2-1,12)+1,1),0),'📋 Movimentações'!$E$15:$E$514,"Saída",'📋 Movimentações'!$D$15:$D$514,"Outros"),0) -> 0 | G49: =IFERROR(SUMIFS('📋 Movimentações'!$F$15:$F$514,'📋 Movimentações'!$B$15:$B$514,">="&DATE(YEAR($D$200)+INT((MONTH($D$200)+3-1)/12),MOD(MONTH($D$200)+3-1,12)+1,1),'📋 Movimentações'!$B$15:$B$514,"<="&EOMONTH(DATE(YEAR($D$200)+INT((MONTH($D$200)+3-1)/12),MOD(MONTH($D$200)+3-1,12)+1,1),0),'📋 Movimentações'!$E$15:$E$514,"Saída",'📋 Movimentações'!$D$15:$D$514,"Outros"),0) -> 0 | H49: =IFERROR(SUMIFS('📋 Movimentações'!$F$15:$F$514,'📋 Movimentações'!$B$15:$B$514,">="&DATE(YEAR($D$200)+INT((MONTH($D$200)+4-1)/12),MOD(MONTH($D$200)+4-1,12)+1,1),'📋 Movimentações'!$B$15:$B$514,"<="&EOMONTH(DATE(YEAR($D$200)+INT((MONTH($D$200)+4-1)/12),MOD(MONTH($D$200)+4-1,12)+1,1),0),'📋 Movimentações'!$E$15:$E$514,"Saída",'📋 Movimentações'!$D$15:$D$514,"Outros"),0) -> 0 | I49: =IFERROR(SUMIFS('📋 Movimentações'!$F$15:$F$514,'📋 Movimentações'!$B$15:$B$514,">="&DATE(YEAR($D$200)+INT((MONTH($D$200)+5-1)/12),MOD(MONTH($D$200)+5-1,12)+1,1),'📋 Movimentações'!$B$15:$B$514,"<="&EOMONTH(DATE(YEAR($D$200)+INT((MONTH($D$200)+5-1)/12),MOD(MONTH($D$200)+5-1,12)+1,1),0),'📋 Movimentações'!$E$15:$E$514,"Saída",'📋 Movimentações'!$D$15:$D$514,"Outros"),0) -> 0 | J49: =SUM(D49,E49,F49,G49,H49,I49) -> 0
B50: Outros Fixos | C50: PREV | D50: ='🏠 Gastos Fixos'!C18 -> 7000 | E50: ='🏠 Gastos Fixos'!C18 -> 7000 | F50: ='🏠 Gastos Fixos'!C18 -> 7000 | G50: ='🏠 Gastos Fixos'!C18 -> 7000 | H50: ='🏠 Gastos Fixos'!C18 -> 7000 | I50: ='🏠 Gastos Fixos'!C18 -> 7000 | J50: ='🏠 Gastos Fixos'!C18*6 -> 42000
C51: REAL | D51: =IFERROR(SUMIFS('📋 Movimentações'!$F$15:$F$514,'📋 Movimentações'!$B$15:$B$514,">="&DATE(YEAR($D$200)+INT((MONTH($D$200)+0-1)/12),MOD(MONTH($D$200)+0-1,12)+1,1),'📋 Movimentações'!$B$15:$B$514,"<="&EOMONTH(DATE(YEAR($D$200)+INT((MONTH($D$200)+0-1)/12),MOD(MONTH($D$200)+0-1,12)+1,1),0),'📋 Movimentações'!$E$15:$E$514,"Saída",'📋 Movimentações'!$D$15:$D$514,"Outros"),0) -> 0 | E51: =IFERROR(SUMIFS('📋 Movimentações'!$F$15:$F$514,'📋 Movimentações'!$B$15:$B$514,">="&DATE(YEAR($D$200)+INT((MONTH($D$200)+1-1)/12),MOD(MONTH($D$200)+1-1,12)+1,1),'📋 Movimentações'!$B$15:$B$514,"<="&EOMONTH(DATE(YEAR($D$200)+INT((MONTH($D$200)+1-1)/12),MOD(MONTH($D$200)+1-1,12)+1,1),0),'📋 Movimentações'!$E$15:$E$514,"Saída",'📋 Movimentações'!$D$15:$D$514,"Outros"),0) -> 0 | F51: =IFERROR(SUMIFS('📋 Movimentações'!$F$15:$F$514,'📋 Movimentações'!$B$15:$B$514,">="&DATE(YEAR($D$200)+INT((MONTH($D$200)+2-1)/12),MOD(MONTH($D$200)+2-1,12)+1,1),'📋 Movimentações'!$B$15:$B$514,"<="&EOMONTH(DATE(YEAR($D$200)+INT((MONTH($D$200)+2-1)/12),MOD(MONTH($D$200)+2-1,12)+1,1),0),'📋 Movimentações'!$E$15:$E$514,"Saída",'📋 Movimentações'!$D$15:$D$514,"Outros"),0) -> 0 | G51: =IFERROR(SUMIFS('📋 Movimentações'!$F$15:$F$514,'📋 Movimentações'!$B$15:$B$514,">="&DATE(YEAR($D$200)+INT((MONTH($D$200)+3-1)/12),MOD(MONTH($D$200)+3-1,12)+1,1),'📋 Movimentações'!$B$15:$B$514,"<="&EOMONTH(DATE(YEAR($D$200)+INT((MONTH($D$200)+3-1)/12),MOD(MONTH($D$200)+3-1,12)+1,1),0),'📋 Movimentações'!$E$15:$E$514,"Saída",'📋 Movimentações'!$D$15:$D$514,"Outros"),0) -> 0 | H51: =IFERROR(SUMIFS('📋 Movimentações'!$F$15:$F$514,'📋 Movimentações'!$B$15:$B$514,">="&DATE(YEAR($D$200)+INT((MONTH($D$200)+4-1)/12),MOD(MONTH($D$200)+4-1,12)+1,1),'📋 Movimentações'!$B$15:$B$514,"<="&EOMONTH(DATE(YEAR($D$200)+INT((MONTH($D$200)+4-1)/12),MOD(MONTH($D$200)+4-1,12)+1,1),0),'📋 Movimentações'!$E$15:$E$514,"Saída",'📋 Movimentações'!$D$15:$D$514,"Outros"),0) -> 0 | I51: =IFERROR(SUMIFS('📋 Movimentações'!$F$15:$F$514,'📋 Movimentações'!$B$15:$B$514,">="&DATE(YEAR($D$200)+INT((MONTH($D$200)+5-1)/12),MOD(MONTH($D$200)+5-1,12)+1,1),'📋 Movimentações'!$B$15:$B$514,"<="&EOMONTH(DATE(YEAR($D$200)+INT((MONTH($D$200)+5-1)/12),MOD(MONTH($D$200)+5-1,12)+1,1),0),'📋 Movimentações'!$E$15:$E$514,"Saída",'📋 Movimentações'!$D$15:$D$514,"Outros"),0) -> 0 | J51: =SUM(D51,E51,F51,G51,H51,I51) -> 0
B52: TOTAL FIXOS | C52: ∑ | D52: =D24+D26+D28+D30+D32+D34+D36+D38+D40+D42+D44+D46+D48+D50 -> 163053 | E52: =E24+E26+E28+E30+E32+E34+E36+E38+E40+E42+E44+E46+E48+E50 -> 163053 | F52: =F24+F26+F28+F30+F32+F34+F36+F38+F40+F42+F44+F46+F48+F50 -> 163053 | G52: =G24+G26+G28+G30+G32+G34+G36+G38+G40+G42+G44+G46+G48+G50 -> 163053 | H52: =H24+H26+H28+H30+H32+H34+H36+H38+H40+H42+H44+H46+H48+H50 -> 163053 | I52: =I24+I26+I28+I30+I32+I34+I36+I38+I40+I42+I44+I46+I48+I50 -> 163053 | J52: =SUM(D52:I52) -> 978318
C53: REAL | D53: =D25+D27+D29+D31+D33+D35+D37+D39+D41+D43+D45+D47+D49+D51 -> 68412 | E53: =E25+E27+E29+E31+E33+E35+E37+E39+E41+E43+E45+E47+E49+E51 -> 0 | F53: =F25+F27+F29+F31+F33+F35+F37+F39+F41+F43+F45+F47+F49+F51 -> 0 | G53: =G25+G27+G29+G31+G33+G35+G37+G39+G41+G43+G45+G47+G49+G51 -> 0 | H53: =H25+H27+H29+H31+H33+H35+H37+H39+H41+H43+H45+H47+H49+H51 -> 0 | I53: =I25+I27+I29+I31+I33+I35+I37+I39+I41+I43+I45+I47+I49+I51 -> 0 | J53: =SUM(D53:I53) -> 68412
B56: 🛒 GASTOS VARIÁVEIS
B57: Mercado / Konbini | C57: PREV | D57: 0 | E57: 0 | F57: 0 | G57: 0 | H57: 0 | I57: 0 | J57: =SUM(D57,E57,F57,G57,H57,I57) -> 0
C58: REAL | D58: =IFERROR(SUMIFS('📋 Movimentações'!$F$15:$F$514,'📋 Movimentações'!$B$15:$B$514,">="&DATE(YEAR($D$200)+INT((MONTH($D$200)+0-1)/12),MOD(MONTH($D$200)+0-1,12)+1,1),'📋 Movimentações'!$B$15:$B$514,"<="&EOMONTH(DATE(YEAR($D$200)+INT((MONTH($D$200)+0-1)/12),MOD(MONTH($D$200)+0-1,12)+1,1),0),'📋 Movimentações'!$E$15:$E$514,"Saída",'📋 Movimentações'!$D$15:$D$514,"Mercado")+SUMIFS('📋 Movimentações'!$F$15:$F$514,'📋 Movimentações'!$B$15:$B$514,">="&DATE(YEAR($D$200)+INT((MONTH($D$200)+0-1)/12),MOD(MONTH($D$200)+0-1,12)+1,1),'📋 Movimentações'!$B$15:$B$514,"<="&EOMONTH(DATE(YEAR($D$200)+INT((MONTH($D$200)+0-1)/12),MOD(MONTH($D$200)+0-1,12)+1,1),0),'📋 Movimentações'!$E$15:$E$514,"Saída",'📋 Movimentações'!$D$15:$D$514,"Konbini"),0) -> 0 | E58: =IFERROR(SUMIFS('📋 Movimentações'!$F$15:$F$514,'📋 Movimentações'!$B$15:$B$514,">="&DATE(YEAR($D$200)+INT((MONTH($D$200)+1-1)/12),MOD(MONTH($D$200)+1-1,12)+1,1),'📋 Movimentações'!$B$15:$B$514,"<="&EOMONTH(DATE(YEAR($D$200)+INT((MONTH($D$200)+1-1)/12),MOD(MONTH($D$200)+1-1,12)+1,1),0),'📋 Movimentações'!$E$15:$E$514,"Saída",'📋 Movimentações'!$D$15:$D$514,"Mercado")+SUMIFS('📋 Movimentações'!$F$15:$F$514,'📋 Movimentações'!$B$15:$B$514,">="&DATE(YEAR($D$200)+INT((MONTH($D$200)+1-1)/12),MOD(MONTH($D$200)+1-1,12)+1,1),'📋 Movimentações'!$B$15:$B$514,"<="&EOMONTH(DATE(YEAR($D$200)+INT((MONTH($D$200)+1-1)/12),MOD(MONTH($D$200)+1-1,12)+1,1),0),'📋 Movimentações'!$E$15:$E$514,"Saída",'📋 Movimentações'!$D$15:$D$514,"Konbini"),0) -> 0 | F58: =IFERROR(SUMIFS('📋 Movimentações'!$F$15:$F$514,'📋 Movimentações'!$B$15:$B$514,">="&DATE(YEAR($D$200)+INT((MONTH($D$200)+2-1)/12),MOD(MONTH($D$200)+2-1,12)+1,1),'📋 Movimentações'!$B$15:$B$514,"<="&EOMONTH(DATE(YEAR($D$200)+INT((MONTH($D$200)+2-1)/12),MOD(MONTH($D$200)+2-1,12)+1,1),0),'📋 Movimentações'!$E$15:$E$514,"Saída",'📋 Movimentações'!$D$15:$D$514,"Mercado")+SUMIFS('📋 Movimentações'!$F$15:$F$514,'📋 Movimentações'!$B$15:$B$514,">="&DATE(YEAR($D$200)+INT((MONTH($D$200)+2-1)/12),MOD(MONTH($D$200)+2-1,12)+1,1),'📋 Movimentações'!$B$15:$B$514,"<="&EOMONTH(DATE(YEAR($D$200)+INT((MONTH($D$200)+2-1)/12),MOD(MONTH($D$200)+2-1,12)+1,1),0),'📋 Movimentações'!$E$15:$E$514,"Saída",'📋 Movimentações'!$D$15:$D$514,"Konbini"),0) -> 0 | G58: =IFERROR(SUMIFS('📋 Movimentações'!$F$15:$F$514,'📋 Movimentações'!$B$15:$B$514,">="&DATE(YEAR($D$200)+INT((MONTH($D$200)+3-1)/12),MOD(MONTH($D$200)+3-1,12)+1,1),'📋 Movimentações'!$B$15:$B$514,"<="&EOMONTH(DATE(YEAR($D$200)+INT((MONTH($D$200)+3-1)/12),MOD(MONTH($D$200)+3-1,12)+1,1),0),'📋 Movimentações'!$E$15:$E$514,"Saída",'📋 Movimentações'!$D$15:$D$514,"Mercado")+SUMIFS('📋 Movimentações'!$F$15:$F$514,'📋 Movimentações'!$B$15:$B$514,">="&DATE(YEAR($D$200)+INT((MONTH($D$200)+3-1)/12),MOD(MONTH($D$200)+3-1,12)+1,1),'📋 Movimentações'!$B$15:$B$514,"<="&EOMONTH(DATE(YEAR($D$200)+INT((MONTH($D$200)+3-1)/12),MOD(MONTH($D$200)+3-1,12)+1,1),0),'📋 Movimentações'!$E$15:$E$514,"Saída",'📋 Movimentações'!$D$15:$D$514,"Konbini"),0) -> 0 | H58: =IFERROR(SUMIFS('📋 Movimentações'!$F$15:$F$514,'📋 Movimentações'!$B$15:$B$514,">="&DATE(YEAR($D$200)+INT((MONTH($D$200)+4-1)/12),MOD(MONTH($D$200)+4-1,12)+1,1),'📋 Movimentações'!$B$15:$B$514,"<="&EOMONTH(DATE(YEAR($D$200)+INT((MONTH($D$200)+4-1)/12),MOD(MONTH($D$200)+4-1,12)+1,1),0),'📋 Movimentações'!$E$15:$E$514,"Saída",'📋 Movimentações'!$D$15:$D$514,"Mercado")+SUMIFS('📋 Movimentações'!$F$15:$F$514,'📋 Movimentações'!$B$15:$B$514,">="&DATE(YEAR($D$200)+INT((MONTH($D$200)+4-1)/12),MOD(MONTH($D$200)+4-1,12)+1,1),'📋 Movimentações'!$B$15:$B$514,"<="&EOMONTH(DATE(YEAR($D$200)+INT((MONTH($D$200)+4-1)/12),MOD(MONTH($D$200)+4-1,12)+1,1),0),'📋 Movimentações'!$E$15:$E$514,"Saída",'📋 Movimentações'!$D$15:$D$514,"Konbini"),0) -> 0 | I58: =IFERROR(SUMIFS('📋 Movimentações'!$F$15:$F$514,'📋 Movimentações'!$B$15:$B$514,">="&DATE(YEAR($D$200)+INT((MONTH($D$200)+5-1)/12),MOD(MONTH($D$200)+5-1,12)+1,1),'📋 Movimentações'!$B$15:$B$514,"<="&EOMONTH(DATE(YEAR($D$200)+INT((MONTH($D$200)+5-1)/12),MOD(MONTH($D$200)+5-1,12)+1,1),0),'📋 Movimentações'!$E$15:$E$514,"Saída",'📋 Movimentações'!$D$15:$D$514,"Mercado")+SUMIFS('📋 Movimentações'!$F$15:$F$514,'📋 Movimentações'!$B$15:$B$514,">="&DATE(YEAR($D$200)+INT((MONTH($D$200)+5-1)/12),MOD(MONTH($D$200)+5-1,12)+1,1),'📋 Movimentações'!$B$15:$B$514,"<="&EOMONTH(DATE(YEAR($D$200)+INT((MONTH($D$200)+5-1)/12),MOD(MONTH($D$200)+5-1,12)+1,1),0),'📋 Movimentações'!$E$15:$E$514,"Saída",'📋 Movimentações'!$D$15:$D$514,"Konbini"),0) -> 0 | J58: =SUM(D58,E58,F58,G58,H58,I58) -> 0
B59: Transporte | C59: PREV | D59: 0 | E59: 0 | F59: 0 | G59: 0 | H59: 0 | I59: 0 | J59: =SUM(D59,E59,F59,G59,H59,I59) -> 0
C60: REAL | D60: =IFERROR(SUMIFS('📋 Movimentações'!$F$15:$F$514,'📋 Movimentações'!$B$15:$B$514,">="&DATE(YEAR($D$200)+INT((MONTH($D$200)+0-1)/12),MOD(MONTH($D$200)+0-1,12)+1,1),'📋 Movimentações'!$B$15:$B$514,"<="&EOMONTH(DATE(YEAR($D$200)+INT((MONTH($D$200)+0-1)/12),MOD(MONTH($D$200)+0-1,12)+1,1),0),'📋 Movimentações'!$E$15:$E$514,"Saída",'📋 Movimentações'!$D$15:$D$514,"Gasolina")+SUMIFS('📋 Movimentações'!$F$15:$F$514,'📋 Movimentações'!$B$15:$B$514,">="&DATE(YEAR($D$200)+INT((MONTH($D$200)+0-1)/12),MOD(MONTH($D$200)+0-1,12)+1,1),'📋 Movimentações'!$B$15:$B$514,"<="&EOMONTH(DATE(YEAR($D$200)+INT((MONTH($D$200)+0-1)/12),MOD(MONTH($D$200)+0-1,12)+1,1),0),'📋 Movimentações'!$E$15:$E$514,"Saída",'📋 Movimentações'!$D$15:$D$514,"Pedágio")+SUMIFS('📋 Movimentações'!$F$15:$F$514,'📋 Movimentações'!$B$15:$B$514,">="&DATE(YEAR($D$200)+INT((MONTH($D$200)+0-1)/12),MOD(MONTH($D$200)+0-1,12)+1,1),'📋 Movimentações'!$B$15:$B$514,"<="&EOMONTH(DATE(YEAR($D$200)+INT((MONTH($D$200)+0-1)/12),MOD(MONTH($D$200)+0-1,12)+1,1),0),'📋 Movimentações'!$E$15:$E$514,"Saída",'📋 Movimentações'!$D$15:$D$514,"Estacionamento"),0) -> 0 | E60: =IFERROR(SUMIFS('📋 Movimentações'!$F$15:$F$514,'📋 Movimentações'!$B$15:$B$514,">="&DATE(YEAR($D$200)+INT((MONTH($D$200)+1-1)/12),MOD(MONTH($D$200)+1-1,12)+1,1),'📋 Movimentações'!$B$15:$B$514,"<="&EOMONTH(DATE(YEAR($D$200)+INT((MONTH($D$200)+1-1)/12),MOD(MONTH($D$200)+1-1,12)+1,1),0),'📋 Movimentações'!$E$15:$E$514,"Saída",'📋 Movimentações'!$D$15:$D$514,"Gasolina")+SUMIFS('📋 Movimentações'!$F$15:$F$514,'📋 Movimentações'!$B$15:$B$514,">="&DATE(YEAR($D$200)+INT((MONTH($D$200)+1-1)/12),MOD(MONTH($D$200)+1-1,12)+1,1),'📋 Movimentações'!$B$15:$B$514,"<="&EOMONTH(DATE(YEAR($D$200)+INT((MONTH($D$200)+1-1)/12),MOD(MONTH($D$200)+1-1,12)+1,1),0),'📋 Movimentações'!$E$15:$E$514,"Saída",'📋 Movimentações'!$D$15:$D$514,"Pedágio")+SUMIFS('📋 Movimentações'!$F$15:$F$514,'📋 Movimentações'!$B$15:$B$514,">="&DATE(YEAR($D$200)+INT((MONTH($D$200)+1-1)/12),MOD(MONTH($D$200)+1-1,12)+1,1),'📋 Movimentações'!$B$15:$B$514,"<="&EOMONTH(DATE(YEAR($D$200)+INT((MONTH($D$200)+1-1)/12),MOD(MONTH($D$200)+1-1,12)+1,1),0),'📋 Movimentações'!$E$15:$E$514,"Saída",'📋 Movimentações'!$D$15:$D$514,"Estacionamento"),0) -> 0 | F60: =IFERROR(SUMIFS('📋 Movimentações'!$F$15:$F$514,'📋 Movimentações'!$B$15:$B$514,">="&DATE(YEAR($D$200)+INT((MONTH($D$200)+2-1)/12),MOD(MONTH($D$200)+2-1,12)+1,1),'📋 Movimentações'!$B$15:$B$514,"<="&EOMONTH(DATE(YEAR($D$200)+INT((MONTH($D$200)+2-1)/12),MOD(MONTH($D$200)+2-1,12)+1,1),0),'📋 Movimentações'!$E$15:$E$514,"Saída",'📋 Movimentações'!$D$15:$D$514,"Gasolina")+SUMIFS('📋 Movimentações'!$F$15:$F$514,'📋 Movimentações'!$B$15:$B$514,">="&DATE(YEAR($D$200)+INT((MONTH($D$200)+2-1)/12),MOD(MONTH($D$200)+2-1,12)+1,1),'📋 Movimentações'!$B$15:$B$514,"<="&EOMONTH(DATE(YEAR($D$200)+INT((MONTH($D$200)+2-1)/12),MOD(MONTH($D$200)+2-1,12)+1,1),0),'📋 Movimentações'!$E$15:$E$514,"Saída",'📋 Movimentações'!$D$15:$D$514,"Pedágio")+SUMIFS('📋 Movimentações'!$F$15:$F$514,'📋 Movimentações'!$B$15:$B$514,">="&DATE(YEAR($D$200)+INT((MONTH($D$200)+2-1)/12),MOD(MONTH($D$200)+2-1,12)+1,1),'📋 Movimentações'!$B$15:$B$514,"<="&EOMONTH(DATE(YEAR($D$200)+INT((MONTH($D$200)+2-1)/12),MOD(MONTH($D$200)+2-1,12)+1,1),0),'📋 Movimentações'!$E$15:$E$514,"Saída",'📋 Movimentações'!$D$15:$D$514,"Estacionamento"),0) -> 0 | G60: =IFERROR(SUMIFS('📋 Movimentações'!$F$15:$F$514,'📋 Movimentações'!$B$15:$B$514,">="&DATE(YEAR($D$200)+INT((MONTH($D$200)+3-1)/12),MOD(MONTH($D$200)+3-1,12)+1,1),'📋 Movimentações'!$B$15:$B$514,"<="&EOMONTH(DATE(YEAR($D$200)+INT((MONTH($D$200)+3-1)/12),MOD(MONTH($D$200)+3-1,12)+1,1),0),'📋 Movimentações'!$E$15:$E$514,"Saída",'📋 Movimentações'!$D$15:$D$514,"Gasolina")+SUMIFS('📋 Movimentações'!$F$15:$F$514,'📋 Movimentações'!$B$15:$B$514,">="&DATE(YEAR($D$200)+INT((MONTH($D$200)+3-1)/12),MOD(MONTH($D$200)+3-1,12)+1,1),'📋 Movimentações'!$B$15:$B$514,"<="&EOMONTH(DATE(YEAR($D$200)+INT((MONTH($D$200)+3-1)/12),MOD(MONTH($D$200)+3-1,12)+1,1),0),'📋 Movimentações'!$E$15:$E$514,"Saída",'📋 Movimentações'!$D$15:$D$514,"Pedágio")+SUMIFS('📋 Movimentações'!$F$15:$F$514,'📋 Movimentações'!$B$15:$B$514,">="&DATE(YEAR($D$200)+INT((MONTH($D$200)+3-1)/12),MOD(MONTH($D$200)+3-1,12)+1,1),'📋 Movimentações'!$B$15:$B$514,"<="&EOMONTH(DATE(YEAR($D$200)+INT((MONTH($D$200)+3-1)/12),MOD(MONTH($D$200)+3-1,12)+1,1),0),'📋 Movimentações'!$E$15:$E$514,"Saída",'📋 Movimentações'!$D$15:$D$514,"Estacionamento"),0) -> 0 | H60: =IFERROR(SUMIFS('📋 Movimentações'!$F$15:$F$514,'📋 Movimentações'!$B$15:$B$514,">="&DATE(YEAR($D$200)+INT((MONTH($D$200)+4-1)/12),MOD(MONTH($D$200)+4-1,12)+1,1),'📋 Movimentações'!$B$15:$B$514,"<="&EOMONTH(DATE(YEAR($D$200)+INT((MONTH($D$200)+4-1)/12),MOD(MONTH($D$200)+4-1,12)+1,1),0),'📋 Movimentações'!$E$15:$E$514,"Saída",'📋 Movimentações'!$D$15:$D$514,"Gasolina")+SUMIFS('📋 Movimentações'!$F$15:$F$514,'📋 Movimentações'!$B$15:$B$514,">="&DATE(YEAR($D$200)+INT((MONTH($D$200)+4-1)/12),MOD(MONTH($D$200)+4-1,12)+1,1),'📋 Movimentações'!$B$15:$B$514,"<="&EOMONTH(DATE(YEAR($D$200)+INT((MONTH($D$200)+4-1)/12),MOD(MONTH($D$200)+4-1,12)+1,1),0),'📋 Movimentações'!$E$15:$E$514,"Saída",'📋 Movimentações'!$D$15:$D$514,"Pedágio")+SUMIFS('📋 Movimentações'!$F$15:$F$514,'📋 Movimentações'!$B$15:$B$514,">="&DATE(YEAR($D$200)+INT((MONTH($D$200)+4-1)/12),MOD(MONTH($D$200)+4-1,12)+1,1),'📋 Movimentações'!$B$15:$B$514,"<="&EOMONTH(DATE(YEAR($D$200)+INT((MONTH($D$200)+4-1)/12),MOD(MONTH($D$200)+4-1,12)+1,1),0),'📋 Movimentações'!$E$15:$E$514,"Saída",'📋 Movimentações'!$D$15:$D$514,"Estacionamento"),0) -> 0 | I60: =IFERROR(SUMIFS('📋 Movimentações'!$F$15:$F$514,'📋 Movimentações'!$B$15:$B$514,">="&DATE(YEAR($D$200)+INT((MONTH($D$200)+5-1)/12),MOD(MONTH($D$200)+5-1,12)+1,1),'📋 Movimentações'!$B$15:$B$514,"<="&EOMONTH(DATE(YEAR($D$200)+INT((MONTH($D$200)+5-1)/12),MOD(MONTH($D$200)+5-1,12)+1,1),0),'📋 Movimentações'!$E$15:$E$514,"Saída",'📋 Movimentações'!$D$15:$D$514,"Gasolina")+SUMIFS('📋 Movimentações'!$F$15:$F$514,'📋 Movimentações'!$B$15:$B$514,">="&DATE(YEAR($D$200)+INT((MONTH($D$200)+5-1)/12),MOD(MONTH($D$200)+5-1,12)+1,1),'📋 Movimentações'!$B$15:$B$514,"<="&EOMONTH(DATE(YEAR($D$200)+INT((MONTH($D$200)+5-1)/12),MOD(MONTH($D$200)+5-1,12)+1,1),0),'📋 Movimentações'!$E$15:$E$514,"Saída",'📋 Movimentações'!$D$15:$D$514,"Pedágio")+SUMIFS('📋 Movimentações'!$F$15:$F$514,'📋 Movimentações'!$B$15:$B$514,">="&DATE(YEAR($D$200)+INT((MONTH($D$200)+5-1)/12),MOD(MONTH($D$200)+5-1,12)+1,1),'📋 Movimentações'!$B$15:$B$514,"<="&EOMONTH(DATE(YEAR($D$200)+INT((MONTH($D$200)+5-1)/12),MOD(MONTH($D$200)+5-1,12)+1,1),0),'📋 Movimentações'!$E$15:$E$514,"Saída",'📋 Movimentações'!$D$15:$D$514,"Estacionamento"),0) -> 0 | J60: =SUM(D60,E60,F60,G60,H60,I60) -> 0
B61: Restaurantes | C61: PREV | D61: 0 | E61: 0 | F61: 0 | G61: 0 | H61: 0 | I61: 0 | J61: =SUM(D61,E61,F61,G61,H61,I61) -> 0
C62: REAL | D62: =IFERROR(SUMIFS('📋 Movimentações'!$F$15:$F$514,'📋 Movimentações'!$B$15:$B$514,">="&DATE(YEAR($D$200)+INT((MONTH($D$200)+0-1)/12),MOD(MONTH($D$200)+0-1,12)+1,1),'📋 Movimentações'!$B$15:$B$514,"<="&EOMONTH(DATE(YEAR($D$200)+INT((MONTH($D$200)+0-1)/12),MOD(MONTH($D$200)+0-1,12)+1,1),0),'📋 Movimentações'!$E$15:$E$514,"Saída",'📋 Movimentações'!$D$15:$D$514,"Restaurantes"),0) -> 0 | E62: =IFERROR(SUMIFS('📋 Movimentações'!$F$15:$F$514,'📋 Movimentações'!$B$15:$B$514,">="&DATE(YEAR($D$200)+INT((MONTH($D$200)+1-1)/12),MOD(MONTH($D$200)+1-1,12)+1,1),'📋 Movimentações'!$B$15:$B$514,"<="&EOMONTH(DATE(YEAR($D$200)+INT((MONTH($D$200)+1-1)/12),MOD(MONTH($D$200)+1-1,12)+1,1),0),'📋 Movimentações'!$E$15:$E$514,"Saída",'📋 Movimentações'!$D$15:$D$514,"Restaurantes"),0) -> 0 | F62: =IFERROR(SUMIFS('📋 Movimentações'!$F$15:$F$514,'📋 Movimentações'!$B$15:$B$514,">="&DATE(YEAR($D$200)+INT((MONTH($D$200)+2-1)/12),MOD(MONTH($D$200)+2-1,12)+1,1),'📋 Movimentações'!$B$15:$B$514,"<="&EOMONTH(DATE(YEAR($D$200)+INT((MONTH($D$200)+2-1)/12),MOD(MONTH($D$200)+2-1,12)+1,1),0),'📋 Movimentações'!$E$15:$E$514,"Saída",'📋 Movimentações'!$D$15:$D$514,"Restaurantes"),0) -> 0 | G62: =IFERROR(SUMIFS('📋 Movimentações'!$F$15:$F$514,'📋 Movimentações'!$B$15:$B$514,">="&DATE(YEAR($D$200)+INT((MONTH($D$200)+3-1)/12),MOD(MONTH($D$200)+3-1,12)+1,1),'📋 Movimentações'!$B$15:$B$514,"<="&EOMONTH(DATE(YEAR($D$200)+INT((MONTH($D$200)+3-1)/12),MOD(MONTH($D$200)+3-1,12)+1,1),0),'📋 Movimentações'!$E$15:$E$514,"Saída",'📋 Movimentações'!$D$15:$D$514,"Restaurantes"),0) -> 0 | H62: =IFERROR(SUMIFS('📋 Movimentações'!$F$15:$F$514,'📋 Movimentações'!$B$15:$B$514,">="&DATE(YEAR($D$200)+INT((MONTH($D$200)+4-1)/12),MOD(MONTH($D$200)+4-1,12)+1,1),'📋 Movimentações'!$B$15:$B$514,"<="&EOMONTH(DATE(YEAR($D$200)+INT((MONTH($D$200)+4-1)/12),MOD(MONTH($D$200)+4-1,12)+1,1),0),'📋 Movimentações'!$E$15:$E$514,"Saída",'📋 Movimentações'!$D$15:$D$514,"Restaurantes"),0) -> 0 | I62: =IFERROR(SUMIFS('📋 Movimentações'!$F$15:$F$514,'📋 Movimentações'!$B$15:$B$514,">="&DATE(YEAR($D$200)+INT((MONTH($D$200)+5-1)/12),MOD(MONTH($D$200)+5-1,12)+1,1),'📋 Movimentações'!$B$15:$B$514,"<="&EOMONTH(DATE(YEAR($D$200)+INT((MONTH($D$200)+5-1)/12),MOD(MONTH($D$200)+5-1,12)+1,1),0),'📋 Movimentações'!$E$15:$E$514,"Saída",'📋 Movimentações'!$D$15:$D$514,"Restaurantes"),0) -> 0 | J62: =SUM(D62,E62,F62,G62,H62,I62) -> 0
B63: Lazer | C63: PREV | D63: 0 | E63: 0 | F63: 0 | G63: 0 | H63: 0 | I63: 0 | J63: =SUM(D63,E63,F63,G63,H63,I63) -> 0
C64: REAL | D64: =IFERROR(SUMIFS('📋 Movimentações'!$F$15:$F$514,'📋 Movimentações'!$B$15:$B$514,">="&DATE(YEAR($D$200)+INT((MONTH($D$200)+0-1)/12),MOD(MONTH($D$200)+0-1,12)+1,1),'📋 Movimentações'!$B$15:$B$514,"<="&EOMONTH(DATE(YEAR($D$200)+INT((MONTH($D$200)+0-1)/12),MOD(MONTH($D$200)+0-1,12)+1,1),0),'📋 Movimentações'!$E$15:$E$514,"Saída",'📋 Movimentações'!$D$15:$D$514,"Lazer"),0) -> 0 | E64: =IFERROR(SUMIFS('📋 Movimentações'!$F$15:$F$514,'📋 Movimentações'!$B$15:$B$514,">="&DATE(YEAR($D$200)+INT((MONTH($D$200)+1-1)/12),MOD(MONTH($D$200)+1-1,12)+1,1),'📋 Movimentações'!$B$15:$B$514,"<="&EOMONTH(DATE(YEAR($D$200)+INT((MONTH($D$200)+1-1)/12),MOD(MONTH($D$200)+1-1,12)+1,1),0),'📋 Movimentações'!$E$15:$E$514,"Saída",'📋 Movimentações'!$D$15:$D$514,"Lazer"),0) -> 0 | F64: =IFERROR(SUMIFS('📋 Movimentações'!$F$15:$F$514,'📋 Movimentações'!$B$15:$B$514,">="&DATE(YEAR($D$200)+INT((MONTH($D$200)+2-1)/12),MOD(MONTH($D$200)+2-1,12)+1,1),'📋 Movimentações'!$B$15:$B$514,"<="&EOMONTH(DATE(YEAR($D$200)+INT((MONTH($D$200)+2-1)/12),MOD(MONTH($D$200)+2-1,12)+1,1),0),'📋 Movimentações'!$E$15:$E$514,"Saída",'📋 Movimentações'!$D$15:$D$514,"Lazer"),0) -> 0 | G64: =IFERROR(SUMIFS('📋 Movimentações'!$F$15:$F$514,'📋 Movimentações'!$B$15:$B$514,">="&DATE(YEAR($D$200)+INT((MONTH($D$200)+3-1)/12),MOD(MONTH($D$200)+3-1,12)+1,1),'📋 Movimentações'!$B$15:$B$514,"<="&EOMONTH(DATE(YEAR($D$200)+INT((MONTH($D$200)+3-1)/12),MOD(MONTH($D$200)+3-1,12)+1,1),0),'📋 Movimentações'!$E$15:$E$514,"Saída",'📋 Movimentações'!$D$15:$D$514,"Lazer"),0) -> 0 | H64: =IFERROR(SUMIFS('📋 Movimentações'!$F$15:$F$514,'📋 Movimentações'!$B$15:$B$514,">="&DATE(YEAR($D$200)+INT((MONTH($D$200)+4-1)/12),MOD(MONTH($D$200)+4-1,12)+1,1),'📋 Movimentações'!$B$15:$B$514,"<="&EOMONTH(DATE(YEAR($D$200)+INT((MONTH($D$200)+4-1)/12),MOD(MONTH($D$200)+4-1,12)+1,1),0),'📋 Movimentações'!$E$15:$E$514,"Saída",'📋 Movimentações'!$D$15:$D$514,"Lazer"),0) -> 0 | I64: =IFERROR(SUMIFS('📋 Movimentações'!$F$15:$F$514,'📋 Movimentações'!$B$15:$B$514,">="&DATE(YEAR($D$200)+INT((MONTH($D$200)+5-1)/12),MOD(MONTH($D$200)+5-1,12)+1,1),'📋 Movimentações'!$B$15:$B$514,"<="&EOMONTH(DATE(YEAR($D$200)+INT((MONTH($D$200)+5-1)/12),MOD(MONTH($D$200)+5-1,12)+1,1),0),'📋 Movimentações'!$E$15:$E$514,"Saída",'📋 Movimentações'!$D$15:$D$514,"Lazer"),0) -> 0 | J64: =SUM(D64,E64,F64,G64,H64,I64) -> 0
B65: Saúde / Remédios | C65: PREV | D65: 0 | E65: 0 | F65: 0 | G65: 0 | H65: 0 | I65: 0 | J65: =SUM(D65,E65,F65,G65,H65,I65) -> 0
C66: REAL | D66: =IFERROR(SUMIFS('📋 Movimentações'!$F$15:$F$514,'📋 Movimentações'!$B$15:$B$514,">="&DATE(YEAR($D$200)+INT((MONTH($D$200)+0-1)/12),MOD(MONTH($D$200)+0-1,12)+1,1),'📋 Movimentações'!$B$15:$B$514,"<="&EOMONTH(DATE(YEAR($D$200)+INT((MONTH($D$200)+0-1)/12),MOD(MONTH($D$200)+0-1,12)+1,1),0),'📋 Movimentações'!$E$15:$E$514,"Saída",'📋 Movimentações'!$D$15:$D$514,"Saúde")+SUMIFS('📋 Movimentações'!$F$15:$F$514,'📋 Movimentações'!$B$15:$B$514,">="&DATE(YEAR($D$200)+INT((MONTH($D$200)+0-1)/12),MOD(MONTH($D$200)+0-1,12)+1,1),'📋 Movimentações'!$B$15:$B$514,"<="&EOMONTH(DATE(YEAR($D$200)+INT((MONTH($D$200)+0-1)/12),MOD(MONTH($D$200)+0-1,12)+1,1),0),'📋 Movimentações'!$E$15:$E$514,"Saída",'📋 Movimentações'!$D$15:$D$514,"Remédios"),0) -> 0 | E66: =IFERROR(SUMIFS('📋 Movimentações'!$F$15:$F$514,'📋 Movimentações'!$B$15:$B$514,">="&DATE(YEAR($D$200)+INT((MONTH($D$200)+1-1)/12),MOD(MONTH($D$200)+1-1,12)+1,1),'📋 Movimentações'!$B$15:$B$514,"<="&EOMONTH(DATE(YEAR($D$200)+INT((MONTH($D$200)+1-1)/12),MOD(MONTH($D$200)+1-1,12)+1,1),0),'📋 Movimentações'!$E$15:$E$514,"Saída",'📋 Movimentações'!$D$15:$D$514,"Saúde")+SUMIFS('📋 Movimentações'!$F$15:$F$514,'📋 Movimentações'!$B$15:$B$514,">="&DATE(YEAR($D$200)+INT((MONTH($D$200)+1-1)/12),MOD(MONTH($D$200)+1-1,12)+1,1),'📋 Movimentações'!$B$15:$B$514,"<="&EOMONTH(DATE(YEAR($D$200)+INT((MONTH($D$200)+1-1)/12),MOD(MONTH($D$200)+1-1,12)+1,1),0),'📋 Movimentações'!$E$15:$E$514,"Saída",'📋 Movimentações'!$D$15:$D$514,"Remédios"),0) -> 0 | F66: =IFERROR(SUMIFS('📋 Movimentações'!$F$15:$F$514,'📋 Movimentações'!$B$15:$B$514,">="&DATE(YEAR($D$200)+INT((MONTH($D$200)+2-1)/12),MOD(MONTH($D$200)+2-1,12)+1,1),'📋 Movimentações'!$B$15:$B$514,"<="&EOMONTH(DATE(YEAR($D$200)+INT((MONTH($D$200)+2-1)/12),MOD(MONTH($D$200)+2-1,12)+1,1),0),'📋 Movimentações'!$E$15:$E$514,"Saída",'📋 Movimentações'!$D$15:$D$514,"Saúde")+SUMIFS('📋 Movimentações'!$F$15:$F$514,'📋 Movimentações'!$B$15:$B$514,">="&DATE(YEAR($D$200)+INT((MONTH($D$200)+2-1)/12),MOD(MONTH($D$200)+2-1,12)+1,1),'📋 Movimentações'!$B$15:$B$514,"<="&EOMONTH(DATE(YEAR($D$200)+INT((MONTH($D$200)+2-1)/12),MOD(MONTH($D$200)+2-1,12)+1,1),0),'📋 Movimentações'!$E$15:$E$514,"Saída",'📋 Movimentações'!$D$15:$D$514,"Remédios"),0) -> 0 | G66: =IFERROR(SUMIFS('📋 Movimentações'!$F$15:$F$514,'📋 Movimentações'!$B$15:$B$514,">="&DATE(YEAR($D$200)+INT((MONTH($D$200)+3-1)/12),MOD(MONTH($D$200)+3-1,12)+1,1),'📋 Movimentações'!$B$15:$B$514,"<="&EOMONTH(DATE(YEAR($D$200)+INT((MONTH($D$200)+3-1)/12),MOD(MONTH($D$200)+3-1,12)+1,1),0),'📋 Movimentações'!$E$15:$E$514,"Saída",'📋 Movimentações'!$D$15:$D$514,"Saúde")+SUMIFS('📋 Movimentações'!$F$15:$F$514,'📋 Movimentações'!$B$15:$B$514,">="&DATE(YEAR($D$200)+INT((MONTH($D$200)+3-1)/12),MOD(MONTH($D$200)+3-1,12)+1,1),'📋 Movimentações'!$B$15:$B$514,"<="&EOMONTH(DATE(YEAR($D$200)+INT((MONTH($D$200)+3-1)/12),MOD(MONTH($D$200)+3-1,12)+1,1),0),'📋 Movimentações'!$E$15:$E$514,"Saída",'📋 Movimentações'!$D$15:$D$514,"Remédios"),0) -> 0 | H66: =IFERROR(SUMIFS('📋 Movimentações'!$F$15:$F$514,'📋 Movimentações'!$B$15:$B$514,">="&DATE(YEAR($D$200)+INT((MONTH($D$200)+4-1)/12),MOD(MONTH($D$200)+4-1,12)+1,1),'📋 Movimentações'!$B$15:$B$514,"<="&EOMONTH(DATE(YEAR($D$200)+INT((MONTH($D$200)+4-1)/12),MOD(MONTH($D$200)+4-1,12)+1,1),0),'📋 Movimentações'!$E$15:$E$514,"Saída",'📋 Movimentações'!$D$15:$D$514,"Saúde")+SUMIFS('📋 Movimentações'!$F$15:$F$514,'📋 Movimentações'!$B$15:$B$514,">="&DATE(YEAR($D$200)+INT((MONTH($D$200)+4-1)/12),MOD(MONTH($D$200)+4-1,12)+1,1),'📋 Movimentações'!$B$15:$B$514,"<="&EOMONTH(DATE(YEAR($D$200)+INT((MONTH($D$200)+4-1)/12),MOD(MONTH($D$200)+4-1,12)+1,1),0),'📋 Movimentações'!$E$15:$E$514,"Saída",'📋 Movimentações'!$D$15:$D$514,"Remédios"),0) -> 0 | I66: =IFERROR(SUMIFS('📋 Movimentações'!$F$15:$F$514,'📋 Movimentações'!$B$15:$B$514,">="&DATE(YEAR($D$200)+INT((MONTH($D$200)+5-1)/12),MOD(MONTH($D$200)+5-1,12)+1,1),'📋 Movimentações'!$B$15:$B$514,"<="&EOMONTH(DATE(YEAR($D$200)+INT((MONTH($D$200)+5-1)/12),MOD(MONTH($D$200)+5-1,12)+1,1),0),'📋 Movimentações'!$E$15:$E$514,"Saída",'📋 Movimentações'!$D$15:$D$514,"Saúde")+SUMIFS('📋 Movimentações'!$F$15:$F$514,'📋 Movimentações'!$B$15:$B$514,">="&DATE(YEAR($D$200)+INT((MONTH($D$200)+5-1)/12),MOD(MONTH($D$200)+5-1,12)+1,1),'📋 Movimentações'!$B$15:$B$514,"<="&EOMONTH(DATE(YEAR($D$200)+INT((MONTH($D$200)+5-1)/12),MOD(MONTH($D$200)+5-1,12)+1,1),0),'📋 Movimentações'!$E$15:$E$514,"Saída",'📋 Movimentações'!$D$15:$D$514,"Remédios"),0) -> 0 | J66: =SUM(D66,E66,F66,G66,H66,I66) -> 0
B67: Compras / Roupas | C67: PREV | D67: 0 | E67: 0 | F67: 0 | G67: 0 | H67: 0 | I67: 0 | J67: =SUM(D67,E67,F67,G67,H67,I67) -> 0
C68: REAL | D68: =IFERROR(SUMIFS('📋 Movimentações'!$F$15:$F$514,'📋 Movimentações'!$B$15:$B$514,">="&DATE(YEAR($D$200)+INT((MONTH($D$200)+0-1)/12),MOD(MONTH($D$200)+0-1,12)+1,1),'📋 Movimentações'!$B$15:$B$514,"<="&EOMONTH(DATE(YEAR($D$200)+INT((MONTH($D$200)+0-1)/12),MOD(MONTH($D$200)+0-1,12)+1,1),0),'📋 Movimentações'!$E$15:$E$514,"Saída",'📋 Movimentações'!$D$15:$D$514,"Compras")+SUMIFS('📋 Movimentações'!$F$15:$F$514,'📋 Movimentações'!$B$15:$B$514,">="&DATE(YEAR($D$200)+INT((MONTH($D$200)+0-1)/12),MOD(MONTH($D$200)+0-1,12)+1,1),'📋 Movimentações'!$B$15:$B$514,"<="&EOMONTH(DATE(YEAR($D$200)+INT((MONTH($D$200)+0-1)/12),MOD(MONTH($D$200)+0-1,12)+1,1),0),'📋 Movimentações'!$E$15:$E$514,"Saída",'📋 Movimentações'!$D$15:$D$514,"Roupas"),0) -> 0 | E68: =IFERROR(SUMIFS('📋 Movimentações'!$F$15:$F$514,'📋 Movimentações'!$B$15:$B$514,">="&DATE(YEAR($D$200)+INT((MONTH($D$200)+1-1)/12),MOD(MONTH($D$200)+1-1,12)+1,1),'📋 Movimentações'!$B$15:$B$514,"<="&EOMONTH(DATE(YEAR($D$200)+INT((MONTH($D$200)+1-1)/12),MOD(MONTH($D$200)+1-1,12)+1,1),0),'📋 Movimentações'!$E$15:$E$514,"Saída",'📋 Movimentações'!$D$15:$D$514,"Compras")+SUMIFS('📋 Movimentações'!$F$15:$F$514,'📋 Movimentações'!$B$15:$B$514,">="&DATE(YEAR($D$200)+INT((MONTH($D$200)+1-1)/12),MOD(MONTH($D$200)+1-1,12)+1,1),'📋 Movimentações'!$B$15:$B$514,"<="&EOMONTH(DATE(YEAR($D$200)+INT((MONTH($D$200)+1-1)/12),MOD(MONTH($D$200)+1-1,12)+1,1),0),'📋 Movimentações'!$E$15:$E$514,"Saída",'📋 Movimentações'!$D$15:$D$514,"Roupas"),0) -> 0 | F68: =IFERROR(SUMIFS('📋 Movimentações'!$F$15:$F$514,'📋 Movimentações'!$B$15:$B$514,">="&DATE(YEAR($D$200)+INT((MONTH($D$200)+2-1)/12),MOD(MONTH($D$200)+2-1,12)+1,1),'📋 Movimentações'!$B$15:$B$514,"<="&EOMONTH(DATE(YEAR($D$200)+INT((MONTH($D$200)+2-1)/12),MOD(MONTH($D$200)+2-1,12)+1,1),0),'📋 Movimentações'!$E$15:$E$514,"Saída",'📋 Movimentações'!$D$15:$D$514,"Compras")+SUMIFS('📋 Movimentações'!$F$15:$F$514,'📋 Movimentações'!$B$15:$B$514,">="&DATE(YEAR($D$200)+INT((MONTH($D$200)+2-1)/12),MOD(MONTH($D$200)+2-1,12)+1,1),'📋 Movimentações'!$B$15:$B$514,"<="&EOMONTH(DATE(YEAR($D$200)+INT((MONTH($D$200)+2-1)/12),MOD(MONTH($D$200)+2-1,12)+1,1),0),'📋 Movimentações'!$E$15:$E$514,"Saída",'📋 Movimentações'!$D$15:$D$514,"Roupas"),0) -> 0 | G68: =IFERROR(SUMIFS('📋 Movimentações'!$F$15:$F$514,'📋 Movimentações'!$B$15:$B$514,">="&DATE(YEAR($D$200)+INT((MONTH($D$200)+3-1)/12),MOD(MONTH($D$200)+3-1,12)+1,1),'📋 Movimentações'!$B$15:$B$514,"<="&EOMONTH(DATE(YEAR($D$200)+INT((MONTH($D$200)+3-1)/12),MOD(MONTH($D$200)+3-1,12)+1,1),0),'📋 Movimentações'!$E$15:$E$514,"Saída",'📋 Movimentações'!$D$15:$D$514,"Compras")+SUMIFS('📋 Movimentações'!$F$15:$F$514,'📋 Movimentações'!$B$15:$B$514,">="&DATE(YEAR($D$200)+INT((MONTH($D$200)+3-1)/12),MOD(MONTH($D$200)+3-1,12)+1,1),'📋 Movimentações'!$B$15:$B$514,"<="&EOMONTH(DATE(YEAR($D$200)+INT((MONTH($D$200)+3-1)/12),MOD(MONTH($D$200)+3-1,12)+1,1),0),'📋 Movimentações'!$E$15:$E$514,"Saída",'📋 Movimentações'!$D$15:$D$514,"Roupas"),0) -> 0 | H68: =IFERROR(SUMIFS('📋 Movimentações'!$F$15:$F$514,'📋 Movimentações'!$B$15:$B$514,">="&DATE(YEAR($D$200)+INT((MONTH($D$200)+4-1)/12),MOD(MONTH($D$200)+4-1,12)+1,1),'📋 Movimentações'!$B$15:$B$514,"<="&EOMONTH(DATE(YEAR($D$200)+INT((MONTH($D$200)+4-1)/12),MOD(MONTH($D$200)+4-1,12)+1,1),0),'📋 Movimentações'!$E$15:$E$514,"Saída",'📋 Movimentações'!$D$15:$D$514,"Compras")+SUMIFS('📋 Movimentações'!$F$15:$F$514,'📋 Movimentações'!$B$15:$B$514,">="&DATE(YEAR($D$200)+INT((MONTH($D$200)+4-1)/12),MOD(MONTH($D$200)+4-1,12)+1,1),'📋 Movimentações'!$B$15:$B$514,"<="&EOMONTH(DATE(YEAR($D$200)+INT((MONTH($D$200)+4-1)/12),MOD(MONTH($D$200)+4-1,12)+1,1),0),'📋 Movimentações'!$E$15:$E$514,"Saída",'📋 Movimentações'!$D$15:$D$514,"Roupas"),0) -> 0 | I68: =IFERROR(SUMIFS('📋 Movimentações'!$F$15:$F$514,'📋 Movimentações'!$B$15:$B$514,">="&DATE(YEAR($D$200)+INT((MONTH($D$200)+5-1)/12),MOD(MONTH($D$200)+5-1,12)+1,1),'📋 Movimentações'!$B$15:$B$514,"<="&EOMONTH(DATE(YEAR($D$200)+INT((MONTH($D$200)+5-1)/12),MOD(MONTH($D$200)+5-1,12)+1,1),0),'📋 Movimentações'!$E$15:$E$514,"Saída",'📋 Movimentações'!$D$15:$D$514,"Compras")+SUMIFS('📋 Movimentações'!$F$15:$F$514,'📋 Movimentações'!$B$15:$B$514,">="&DATE(YEAR($D$200)+INT((MONTH($D$200)+5-1)/12),MOD(MONTH($D$200)+5-1,12)+1,1),'📋 Movimentações'!$B$15:$B$514,"<="&EOMONTH(DATE(YEAR($D$200)+INT((MONTH($D$200)+5-1)/12),MOD(MONTH($D$200)+5-1,12)+1,1),0),'📋 Movimentações'!$E$15:$E$514,"Saída",'📋 Movimentações'!$D$15:$D$514,"Roupas"),0) -> 0 | J68: =SUM(D68,E68,F68,G68,H68,I68) -> 0
B69: Remessa Brasil | C69: PREV | D69: 0 | E69: 0 | F69: 0 | G69: 0 | H69: 0 | I69: 0 | J69: =SUM(D69,E69,F69,G69,H69,I69) -> 0
C70: REAL | D70: =IFERROR(SUMIFS('📋 Movimentações'!$F$15:$F$514,'📋 Movimentações'!$B$15:$B$514,">="&DATE(YEAR($D$200)+INT((MONTH($D$200)+0-1)/12),MOD(MONTH($D$200)+0-1,12)+1,1),'📋 Movimentações'!$B$15:$B$514,"<="&EOMONTH(DATE(YEAR($D$200)+INT((MONTH($D$200)+0-1)/12),MOD(MONTH($D$200)+0-1,12)+1,1),0),'📋 Movimentações'!$E$15:$E$514,"Saída",'📋 Movimentações'!$D$15:$D$514,"Remessa Brasil"),0) -> 0 | E70: =IFERROR(SUMIFS('📋 Movimentações'!$F$15:$F$514,'📋 Movimentações'!$B$15:$B$514,">="&DATE(YEAR($D$200)+INT((MONTH($D$200)+1-1)/12),MOD(MONTH($D$200)+1-1,12)+1,1),'📋 Movimentações'!$B$15:$B$514,"<="&EOMONTH(DATE(YEAR($D$200)+INT((MONTH($D$200)+1-1)/12),MOD(MONTH($D$200)+1-1,12)+1,1),0),'📋 Movimentações'!$E$15:$E$514,"Saída",'📋 Movimentações'!$D$15:$D$514,"Remessa Brasil"),0) -> 0 | F70: =IFERROR(SUMIFS('📋 Movimentações'!$F$15:$F$514,'📋 Movimentações'!$B$15:$B$514,">="&DATE(YEAR($D$200)+INT((MONTH($D$200)+2-1)/12),MOD(MONTH($D$200)+2-1,12)+1,1),'📋 Movimentações'!$B$15:$B$514,"<="&EOMONTH(DATE(YEAR($D$200)+INT((MONTH($D$200)+2-1)/12),MOD(MONTH($D$200)+2-1,12)+1,1),0),'📋 Movimentações'!$E$15:$E$514,"Saída",'📋 Movimentações'!$D$15:$D$514,"Remessa Brasil"),0) -> 0 | G70: =IFERROR(SUMIFS('📋 Movimentações'!$F$15:$F$514,'📋 Movimentações'!$B$15:$B$514,">="&DATE(YEAR($D$200)+INT((MONTH($D$200)+3-1)/12),MOD(MONTH($D$200)+3-1,12)+1,1),'📋 Movimentações'!$B$15:$B$514,"<="&EOMONTH(DATE(YEAR($D$200)+INT((MONTH($D$200)+3-1)/12),MOD(MONTH($D$200)+3-1,12)+1,1),0),'📋 Movimentações'!$E$15:$E$514,"Saída",'📋 Movimentações'!$D$15:$D$514,"Remessa Brasil"),0) -> 0 | H70: =IFERROR(SUMIFS('📋 Movimentações'!$F$15:$F$514,'📋 Movimentações'!$B$15:$B$514,">="&DATE(YEAR($D$200)+INT((MONTH($D$200)+4-1)/12),MOD(MONTH($D$200)+4-1,12)+1,1),'📋 Movimentações'!$B$15:$B$514,"<="&EOMONTH(DATE(YEAR($D$200)+INT((MONTH($D$200)+4-1)/12),MOD(MONTH($D$200)+4-1,12)+1,1),0),'📋 Movimentações'!$E$15:$E$514,"Saída",'📋 Movimentações'!$D$15:$D$514,"Remessa Brasil"),0) -> 0 | I70: =IFERROR(SUMIFS('📋 Movimentações'!$F$15:$F$514,'📋 Movimentações'!$B$15:$B$514,">="&DATE(YEAR($D$200)+INT((MONTH($D$200)+5-1)/12),MOD(MONTH($D$200)+5-1,12)+1,1),'📋 Movimentações'!$B$15:$B$514,"<="&EOMONTH(DATE(YEAR($D$200)+INT((MONTH($D$200)+5-1)/12),MOD(MONTH($D$200)+5-1,12)+1,1),0),'📋 Movimentações'!$E$15:$E$514,"Saída",'📋 Movimentações'!$D$15:$D$514,"Remessa Brasil"),0) -> 0 | J70: =SUM(D70,E70,F70,G70,H70,I70) -> 0
B71: Igreja / Oferta | C71: PREV | D71: 0 | E71: 0 | F71: 0 | G71: 0 | H71: 0 | I71: 0 | J71: =SUM(D71,E71,F71,G71,H71,I71) -> 0
C72: REAL | D72: =IFERROR(SUMIFS('📋 Movimentações'!$F$15:$F$514,'📋 Movimentações'!$B$15:$B$514,">="&DATE(YEAR($D$200)+INT((MONTH($D$200)+0-1)/12),MOD(MONTH($D$200)+0-1,12)+1,1),'📋 Movimentações'!$B$15:$B$514,"<="&EOMONTH(DATE(YEAR($D$200)+INT((MONTH($D$200)+0-1)/12),MOD(MONTH($D$200)+0-1,12)+1,1),0),'📋 Movimentações'!$E$15:$E$514,"Saída",'📋 Movimentações'!$D$15:$D$514,"Igreja/Oferta"),0) -> 0 | E72: =IFERROR(SUMIFS('📋 Movimentações'!$F$15:$F$514,'📋 Movimentações'!$B$15:$B$514,">="&DATE(YEAR($D$200)+INT((MONTH($D$200)+1-1)/12),MOD(MONTH($D$200)+1-1,12)+1,1),'📋 Movimentações'!$B$15:$B$514,"<="&EOMONTH(DATE(YEAR($D$200)+INT((MONTH($D$200)+1-1)/12),MOD(MONTH($D$200)+1-1,12)+1,1),0),'📋 Movimentações'!$E$15:$E$514,"Saída",'📋 Movimentações'!$D$15:$D$514,"Igreja/Oferta"),0) -> 0 | F72: =IFERROR(SUMIFS('📋 Movimentações'!$F$15:$F$514,'📋 Movimentações'!$B$15:$B$514,">="&DATE(YEAR($D$200)+INT((MONTH($D$200)+2-1)/12),MOD(MONTH($D$200)+2-1,12)+1,1),'📋 Movimentações'!$B$15:$B$514,"<="&EOMONTH(DATE(YEAR($D$200)+INT((MONTH($D$200)+2-1)/12),MOD(MONTH($D$200)+2-1,12)+1,1),0),'📋 Movimentações'!$E$15:$E$514,"Saída",'📋 Movimentações'!$D$15:$D$514,"Igreja/Oferta"),0) -> 0 | G72: =IFERROR(SUMIFS('📋 Movimentações'!$F$15:$F$514,'📋 Movimentações'!$B$15:$B$514,">="&DATE(YEAR($D$200)+INT((MONTH($D$200)+3-1)/12),MOD(MONTH($D$200)+3-1,12)+1,1),'📋 Movimentações'!$B$15:$B$514,"<="&EOMONTH(DATE(YEAR($D$200)+INT((MONTH($D$200)+3-1)/12),MOD(MONTH($D$200)+3-1,12)+1,1),0),'📋 Movimentações'!$E$15:$E$514,"Saída",'📋 Movimentações'!$D$15:$D$514,"Igreja/Oferta"),0) -> 0 | H72: =IFERROR(SUMIFS('📋 Movimentações'!$F$15:$F$514,'📋 Movimentações'!$B$15:$B$514,">="&DATE(YEAR($D$200)+INT((MONTH($D$200)+4-1)/12),MOD(MONTH($D$200)+4-1,12)+1,1),'📋 Movimentações'!$B$15:$B$514,"<="&EOMONTH(DATE(YEAR($D$200)+INT((MONTH($D$200)+4-1)/12),MOD(MONTH($D$200)+4-1,12)+1,1),0),'📋 Movimentações'!$E$15:$E$514,"Saída",'📋 Movimentações'!$D$15:$D$514,"Igreja/Oferta"),0) -> 0 | I72: =IFERROR(SUMIFS('📋 Movimentações'!$F$15:$F$514,'📋 Movimentações'!$B$15:$B$514,">="&DATE(YEAR($D$200)+INT((MONTH($D$200)+5-1)/12),MOD(MONTH($D$200)+5-1,12)+1,1),'📋 Movimentações'!$B$15:$B$514,"<="&EOMONTH(DATE(YEAR($D$200)+INT((MONTH($D$200)+5-1)/12),MOD(MONTH($D$200)+5-1,12)+1,1),0),'📋 Movimentações'!$E$15:$E$514,"Saída",'📋 Movimentações'!$D$15:$D$514,"Igreja/Oferta"),0) -> 0 | J72: =SUM(D72,E72,F72,G72,H72,I72) -> 0
B73: Emergência | C73: PREV | D73: 0 | E73: 0 | F73: 0 | G73: 0 | H73: 0 | I73: 0 | J73: =SUM(D73,E73,F73,G73,H73,I73) -> 0
C74: REAL | D74: =IFERROR(SUMIFS('📋 Movimentações'!$F$15:$F$514,'📋 Movimentações'!$B$15:$B$514,">="&DATE(YEAR($D$200)+INT((MONTH($D$200)+0-1)/12),MOD(MONTH($D$200)+0-1,12)+1,1),'📋 Movimentações'!$B$15:$B$514,"<="&EOMONTH(DATE(YEAR($D$200)+INT((MONTH($D$200)+0-1)/12),MOD(MONTH($D$200)+0-1,12)+1,1),0),'📋 Movimentações'!$E$15:$E$514,"Saída",'📋 Movimentações'!$D$15:$D$514,"Emergência"),0) -> 0 | E74: =IFERROR(SUMIFS('📋 Movimentações'!$F$15:$F$514,'📋 Movimentações'!$B$15:$B$514,">="&DATE(YEAR($D$200)+INT((MONTH($D$200)+1-1)/12),MOD(MONTH($D$200)+1-1,12)+1,1),'📋 Movimentações'!$B$15:$B$514,"<="&EOMONTH(DATE(YEAR($D$200)+INT((MONTH($D$200)+1-1)/12),MOD(MONTH($D$200)+1-1,12)+1,1),0),'📋 Movimentações'!$E$15:$E$514,"Saída",'📋 Movimentações'!$D$15:$D$514,"Emergência"),0) -> 0 | F74: =IFERROR(SUMIFS('📋 Movimentações'!$F$15:$F$514,'📋 Movimentações'!$B$15:$B$514,">="&DATE(YEAR($D$200)+INT((MONTH($D$200)+2-1)/12),MOD(MONTH($D$200)+2-1,12)+1,1),'📋 Movimentações'!$B$15:$B$514,"<="&EOMONTH(DATE(YEAR($D$200)+INT((MONTH($D$200)+2-1)/12),MOD(MONTH($D$200)+2-1,12)+1,1),0),'📋 Movimentações'!$E$15:$E$514,"Saída",'📋 Movimentações'!$D$15:$D$514,"Emergência"),0) -> 0 | G74: =IFERROR(SUMIFS('📋 Movimentações'!$F$15:$F$514,'📋 Movimentações'!$B$15:$B$514,">="&DATE(YEAR($D$200)+INT((MONTH($D$200)+3-1)/12),MOD(MONTH($D$200)+3-1,12)+1,1),'📋 Movimentações'!$B$15:$B$514,"<="&EOMONTH(DATE(YEAR($D$200)+INT((MONTH($D$200)+3-1)/12),MOD(MONTH($D$200)+3-1,12)+1,1),0),'📋 Movimentações'!$E$15:$E$514,"Saída",'📋 Movimentações'!$D$15:$D$514,"Emergência"),0) -> 0 | H74: =IFERROR(SUMIFS('📋 Movimentações'!$F$15:$F$514,'📋 Movimentações'!$B$15:$B$514,">="&DATE(YEAR($D$200)+INT((MONTH($D$200)+4-1)/12),MOD(MONTH($D$200)+4-1,12)+1,1),'📋 Movimentações'!$B$15:$B$514,"<="&EOMONTH(DATE(YEAR($D$200)+INT((MONTH($D$200)+4-1)/12),MOD(MONTH($D$200)+4-1,12)+1,1),0),'📋 Movimentações'!$E$15:$E$514,"Saída",'📋 Movimentações'!$D$15:$D$514,"Emergência"),0) -> 0 | I74: =IFERROR(SUMIFS('📋 Movimentações'!$F$15:$F$514,'📋 Movimentações'!$B$15:$B$514,">="&DATE(YEAR($D$200)+INT((MONTH($D$200)+5-1)/12),MOD(MONTH($D$200)+5-1,12)+1,1),'📋 Movimentações'!$B$15:$B$514,"<="&EOMONTH(DATE(YEAR($D$200)+INT((MONTH($D$200)+5-1)/12),MOD(MONTH($D$200)+5-1,12)+1,1),0),'📋 Movimentações'!$E$15:$E$514,"Saída",'📋 Movimentações'!$D$15:$D$514,"Emergência"),0) -> 0 | J74: =SUM(D74,E74,F74,G74,H74,I74) -> 0
B75: Outros variáveis | C75: PREV | D75: 10000 | E75: 10000 | F75: 10000 | G75: 10000 | H75: 10000 | I75: 10000 | J75: =SUM(D75,E75,F75,G75,H75,I75) -> 60000
C76: REAL | D76: =IFERROR(SUMIFS('📋 Movimentações'!$F$15:$F$514,'📋 Movimentações'!$B$15:$B$514,">="&DATE(YEAR($D$200)+INT((MONTH($D$200)+0-1)/12),MOD(MONTH($D$200)+0-1,12)+1,1),'📋 Movimentações'!$B$15:$B$514,"<="&EOMONTH(DATE(YEAR($D$200)+INT((MONTH($D$200)+0-1)/12),MOD(MONTH($D$200)+0-1,12)+1,1),0),'📋 Movimentações'!$E$15:$E$514,"Saída",'📋 Movimentações'!$D$15:$D$514,"Outros"),0) -> 0 | E76: =IFERROR(SUMIFS('📋 Movimentações'!$F$15:$F$514,'📋 Movimentações'!$B$15:$B$514,">="&DATE(YEAR($D$200)+INT((MONTH($D$200)+1-1)/12),MOD(MONTH($D$200)+1-1,12)+1,1),'📋 Movimentações'!$B$15:$B$514,"<="&EOMONTH(DATE(YEAR($D$200)+INT((MONTH($D$200)+1-1)/12),MOD(MONTH($D$200)+1-1,12)+1,1),0),'📋 Movimentações'!$E$15:$E$514,"Saída",'📋 Movimentações'!$D$15:$D$514,"Outros"),0) -> 0 | F76: =IFERROR(SUMIFS('📋 Movimentações'!$F$15:$F$514,'📋 Movimentações'!$B$15:$B$514,">="&DATE(YEAR($D$200)+INT((MONTH($D$200)+2-1)/12),MOD(MONTH($D$200)+2-1,12)+1,1),'📋 Movimentações'!$B$15:$B$514,"<="&EOMONTH(DATE(YEAR($D$200)+INT((MONTH($D$200)+2-1)/12),MOD(MONTH($D$200)+2-1,12)+1,1),0),'📋 Movimentações'!$E$15:$E$514,"Saída",'📋 Movimentações'!$D$15:$D$514,"Outros"),0) -> 0 | G76: =IFERROR(SUMIFS('📋 Movimentações'!$F$15:$F$514,'📋 Movimentações'!$B$15:$B$514,">="&DATE(YEAR($D$200)+INT((MONTH($D$200)+3-1)/12),MOD(MONTH($D$200)+3-1,12)+1,1),'📋 Movimentações'!$B$15:$B$514,"<="&EOMONTH(DATE(YEAR($D$200)+INT((MONTH($D$200)+3-1)/12),MOD(MONTH($D$200)+3-1,12)+1,1),0),'📋 Movimentações'!$E$15:$E$514,"Saída",'📋 Movimentações'!$D$15:$D$514,"Outros"),0) -> 0 | H76: =IFERROR(SUMIFS('📋 Movimentações'!$F$15:$F$514,'📋 Movimentações'!$B$15:$B$514,">="&DATE(YEAR($D$200)+INT((MONTH($D$200)+4-1)/12),MOD(MONTH($D$200)+4-1,12)+1,1),'📋 Movimentações'!$B$15:$B$514,"<="&EOMONTH(DATE(YEAR($D$200)+INT((MONTH($D$200)+4-1)/12),MOD(MONTH($D$200)+4-1,12)+1,1),0),'📋 Movimentações'!$E$15:$E$514,"Saída",'📋 Movimentações'!$D$15:$D$514,"Outros"),0) -> 0 | I76: =IFERROR(SUMIFS('📋 Movimentações'!$F$15:$F$514,'📋 Movimentações'!$B$15:$B$514,">="&DATE(YEAR($D$200)+INT((MONTH($D$200)+5-1)/12),MOD(MONTH($D$200)+5-1,12)+1,1),'📋 Movimentações'!$B$15:$B$514,"<="&EOMONTH(DATE(YEAR($D$200)+INT((MONTH($D$200)+5-1)/12),MOD(MONTH($D$200)+5-1,12)+1,1),0),'📋 Movimentações'!$E$15:$E$514,"Saída",'📋 Movimentações'!$D$15:$D$514,"Outros"),0) -> 0 | J76: =SUM(D76,E76,F76,G76,H76,I76) -> 0
B77: TOTAL VARIÁVEIS | C77: ∑ | D77: =D57+D59+D61+D63+D65+D67+D69+D71+D73+D75 -> 10000 | E77: =E57+E59+E61+E63+E65+E67+E69+E71+E73+E75 -> 10000 | F77: =F57+F59+F61+F63+F65+F67+F69+F71+F73+F75 -> 10000 | G77: =G57+G59+G61+G63+G65+G67+G69+G71+G73+G75 -> 10000 | H77: =H57+H59+H61+H63+H65+H67+H69+H71+H73+H75 -> 10000 | I77: =I57+I59+I61+I63+I65+I67+I69+I71+I73+I75 -> 10000 | J77: =SUM(D77:I77) -> 60000
C78: REAL | D78: =D58+D60+D62+D64+D66+D68+D70+D72+D74+D76 -> 0 | E78: =E58+E60+E62+E64+E66+E68+E70+E72+E74+E76 -> 0 | F78: =F58+F60+F62+F64+F66+F68+F70+F72+F74+F76 -> 0 | G78: =G58+G60+G62+G64+G66+G68+G70+G72+G74+G76 -> 0 | H78: =H58+H60+H62+H64+H66+H68+H70+H72+H74+H76 -> 0 | I78: =I58+I60+I62+I64+I66+I68+I70+I72+I74+I76 -> 0 | J78: =SUM(D78:I78) -> 0
B81: 🎯 METAS — Aporte Mensal
B82: 💡 PREV = quanto você planeja guardar por mês | REAL = quanto você guardou (digite aqui) | TOTAL = acumulado
B83: 🆘 Reserva de Emergência | C83: PREV | D83: =IFERROR(IF('🎯 Metas'!I5="—",0,'🎯 Metas'!I5),0) -> 500000 | E83: =IFERROR(IF('🎯 Metas'!I5="—",0,'🎯 Metas'!I5),0) -> 500000 | F83: =IFERROR(IF('🎯 Metas'!I5="—",0,'🎯 Metas'!I5),0) -> 500000 | G83: =IFERROR(IF('🎯 Metas'!I5="—",0,'🎯 Metas'!I5),0) -> 500000 | H83: =IFERROR(IF('🎯 Metas'!I5="—",0,'🎯 Metas'!I5),0) -> 500000 | I83: =IFERROR(IF('🎯 Metas'!I5="—",0,'🎯 Metas'!I5),0) -> 500000 | J83: =IFERROR(IF('🎯 Metas'!I5="—",0,'🎯 Metas'!I5),0)*6 -> 3000000
B84: ← Digite quanto guardou por mês | C84: REAL | D84: 0 | E84: 0 | F84: 0 | G84: 0 | H84: 0 | I84: 0 | J84: ='🎯 Metas'!D5+SUM(D84,E84,F84,G84,H84,I84) -> 0
B85: Progresso — Alvo: ¥500,000 | Já guardado: ¥50,000 | C85: % | D85: =IFERROR((50000+D84)/500000,0) -> 0.1 | E85: =IFERROR((50000+D84+E84)/500000,0) -> 0.1 | F85: =IFERROR((50000+D84+E84+F84)/500000,0) -> 0.1 | G85: =IFERROR((50000+D84+E84+F84+G84)/500000,0) -> 0.1 | H85: =IFERROR((50000+D84+E84+F84+G84+H84)/500000,0) -> 0.1 | I85: =IFERROR((50000+D84+E84+F84+G84+H84+I84)/500000,0) -> 0.1 | J85: =IFERROR(J84/500000,0) -> 0
B86: ✈️ Viagem | C86: PREV | D86: =IFERROR(IF('🎯 Metas'!I6="—",0,'🎯 Metas'!I6),0) -> 0 | E86: =IFERROR(IF('🎯 Metas'!I6="—",0,'🎯 Metas'!I6),0) -> 0 | F86: =IFERROR(IF('🎯 Metas'!I6="—",0,'🎯 Metas'!I6),0) -> 0 | G86: =IFERROR(IF('🎯 Metas'!I6="—",0,'🎯 Metas'!I6),0) -> 0 | H86: =IFERROR(IF('🎯 Metas'!I6="—",0,'🎯 Metas'!I6),0) -> 0 | I86: =IFERROR(IF('🎯 Metas'!I6="—",0,'🎯 Metas'!I6),0) -> 0 | J86: =IFERROR(IF('🎯 Metas'!I6="—",0,'🎯 Metas'!I6),0)*6 -> 0
B87: ← Digite quanto guardou por mês | C87: REAL | D87: 0 | E87: 0 | F87: 0 | G87: 0 | H87: 0 | I87: 0 | J87: ='🎯 Metas'!D6+SUM(D87,E87,F87,G87,H87,I87) -> 0
B88: Progresso — Alvo: ¥300,000 | Já guardado: ¥30,000 | C88: % | D88: =IFERROR((30000+D87)/300000,0) -> 0.1 | E88: =IFERROR((30000+D87+E87)/300000,0) -> 0.1 | F88: =IFERROR((30000+D87+E87+F87)/300000,0) -> 0.1 | G88: =IFERROR((30000+D87+E87+F87+G87)/300000,0) -> 0.1 | H88: =IFERROR((30000+D87+E87+F87+G87+H87)/300000,0) -> 0.1 | I88: =IFERROR((30000+D87+E87+F87+G87+H87+I87)/300000,0) -> 0.1 | J88: =IFERROR(J87/300000,0) -> 0
B89: 🚗 Carro Novo | C89: PREV | D89: =IFERROR(IF('🎯 Metas'!I7="—",0,'🎯 Metas'!I7),0) -> 0 | E89: =IFERROR(IF('🎯 Metas'!I7="—",0,'🎯 Metas'!I7),0) -> 0 | F89: =IFERROR(IF('🎯 Metas'!I7="—",0,'🎯 Metas'!I7),0) -> 0 | G89: =IFERROR(IF('🎯 Metas'!I7="—",0,'🎯 Metas'!I7),0) -> 0 | H89: =IFERROR(IF('🎯 Metas'!I7="—",0,'🎯 Metas'!I7),0) -> 0 | I89: =IFERROR(IF('🎯 Metas'!I7="—",0,'🎯 Metas'!I7),0) -> 0 | J89: =IFERROR(IF('🎯 Metas'!I7="—",0,'🎯 Metas'!I7),0)*6 -> 0
B90: ← Digite quanto guardou por mês | C90: REAL | D90: 0 | E90: 0 | F90: 0 | G90: 0 | H90: 0 | I90: 0 | J90: ='🎯 Metas'!D7+SUM(D90,E90,F90,G90,H90,I90) -> 0
B91: Progresso — Alvo: ¥800,000 | Já guardado: ¥80,000 | C91: % | D91: =IFERROR((80000+D90)/800000,0) -> 0.1 | E91: =IFERROR((80000+D90+E90)/800000,0) -> 0.1 | F91: =IFERROR((80000+D90+E90+F90)/800000,0) -> 0.1 | G91: =IFERROR((80000+D90+E90+F90+G90)/800000,0) -> 0.1 | H91: =IFERROR((80000+D90+E90+F90+G90+H90)/800000,0) -> 0.1 | I91: =IFERROR((80000+D90+E90+F90+G90+H90+I90)/800000,0) -> 0.1 | J91: =IFERROR(J90/800000,0) -> 0
B92: 📦 Mudança / Novo Apto | C92: PREV | D92: =IFERROR(IF('🎯 Metas'!I8="—",0,'🎯 Metas'!I8),0) -> 0 | E92: =IFERROR(IF('🎯 Metas'!I8="—",0,'🎯 Metas'!I8),0) -> 0 | F92: =IFERROR(IF('🎯 Metas'!I8="—",0,'🎯 Metas'!I8),0) -> 0 | G92: =IFERROR(IF('🎯 Metas'!I8="—",0,'🎯 Metas'!I8),0) -> 0 | H92: =IFERROR(IF('🎯 Metas'!I8="—",0,'🎯 Metas'!I8),0) -> 0 | I92: =IFERROR(IF('🎯 Metas'!I8="—",0,'🎯 Metas'!I8),0) -> 0 | J92: =IFERROR(IF('🎯 Metas'!I8="—",0,'🎯 Metas'!I8),0)*6 -> 0
B93: ← Digite quanto guardou por mês | C93: REAL | D93: 0 | E93: 0 | F93: 0 | G93: 0 | H93: 0 | I93: 0 | J93: ='🎯 Metas'!D8+SUM(D93,E93,F93,G93,H93,I93) -> 0
B94: Progresso — Alvo: ¥200,000 | Já guardado: ¥0 | C94: % | D94: =IFERROR((0+D93)/200000,0) -> 0 | E94: =IFERROR((0+D93+E93)/200000,0) -> 0 | F94: =IFERROR((0+D93+E93+F93)/200000,0) -> 0 | G94: =IFERROR((0+D93+E93+F93+G93)/200000,0) -> 0 | H94: =IFERROR((0+D93+E93+F93+G93+H93)/200000,0) -> 0 | I94: =IFERROR((0+D93+E93+F93+G93+H93+I93)/200000,0) -> 0 | J94: =IFERROR(J93/200000,0) -> 0
B95: 📈 Investimento | C95: PREV | D95: =IFERROR(IF('🎯 Metas'!I9="—",0,'🎯 Metas'!I9),0) -> 0 | E95: =IFERROR(IF('🎯 Metas'!I9="—",0,'🎯 Metas'!I9),0) -> 0 | F95: =IFERROR(IF('🎯 Metas'!I9="—",0,'🎯 Metas'!I9),0) -> 0 | G95: =IFERROR(IF('🎯 Metas'!I9="—",0,'🎯 Metas'!I9),0) -> 0 | H95: =IFERROR(IF('🎯 Metas'!I9="—",0,'🎯 Metas'!I9),0) -> 0 | I95: =IFERROR(IF('🎯 Metas'!I9="—",0,'🎯 Metas'!I9),0) -> 0 | J95: =IFERROR(IF('🎯 Metas'!I9="—",0,'🎯 Metas'!I9),0)*6 -> 0
B96: ← Digite quanto guardou por mês | C96: REAL | D96: 0 | E96: 0 | F96: 0 | G96: 0 | H96: 0 | I96: 0 | J96: ='🎯 Metas'!D9+SUM(D96,E96,F96,G96,H96,I96) -> 0
B97: Progresso — Alvo: ¥1,000,000 | Já guardado: ¥100,000 | C97: % | D97: =IFERROR((100000+D96)/1000000,0) -> 0.1 | E97: =IFERROR((100000+D96+E96)/1000000,0) -> 0.1 | F97: =IFERROR((100000+D96+E96+F96)/1000000,0) -> 0.1 | G97: =IFERROR((100000+D96+E96+F96+G96)/1000000,0) -> 0.1 | H97: =IFERROR((100000+D96+E96+F96+G96+H96)/1000000,0) -> 0.1 | I97: =IFERROR((100000+D96+E96+F96+G96+H96+I96)/1000000,0) -> 0.1 | J97: =IFERROR(J96/1000000,0) -> 0
B98: 💳 Quitar Dívida | C98: PREV | D98: =IFERROR(IF('🎯 Metas'!I10="—",0,'🎯 Metas'!I10),0) -> 0 | E98: =IFERROR(IF('🎯 Metas'!I10="—",0,'🎯 Metas'!I10),0) -> 0 | F98: =IFERROR(IF('🎯 Metas'!I10="—",0,'🎯 Metas'!I10),0) -> 0 | G98: =IFERROR(IF('🎯 Metas'!I10="—",0,'🎯 Metas'!I10),0) -> 0 | H98: =IFERROR(IF('🎯 Metas'!I10="—",0,'🎯 Metas'!I10),0) -> 0 | I98: =IFERROR(IF('🎯 Metas'!I10="—",0,'🎯 Metas'!I10),0) -> 0 | J98: =IFERROR(IF('🎯 Metas'!I10="—",0,'🎯 Metas'!I10),0)*6 -> 0
B99: ← Digite quanto guardou por mês | C99: REAL | D99: 0 | E99: 0 | F99: 0 | G99: 0 | H99: 0 | I99: 0 | J99: ='🎯 Metas'!D10+SUM(D99,E99,F99,G99,H99,I99) -> 0
B100: Progresso — Alvo: ¥0 | Já guardado: ¥0 | C100: % | D100: 0 | E100: 0 | F100: 0 | G100: 0 | H100: 0 | I100: 0 | J100: 0
B101: 🛒 Compra Importante | C101: PREV | D101: =IFERROR(IF('🎯 Metas'!I11="—",0,'🎯 Metas'!I11),0) -> 0 | E101: =IFERROR(IF('🎯 Metas'!I11="—",0,'🎯 Metas'!I11),0) -> 0 | F101: =IFERROR(IF('🎯 Metas'!I11="—",0,'🎯 Metas'!I11),0) -> 0 | G101: =IFERROR(IF('🎯 Metas'!I11="—",0,'🎯 Metas'!I11),0) -> 0 | H101: =IFERROR(IF('🎯 Metas'!I11="—",0,'🎯 Metas'!I11),0) -> 0 | I101: =IFERROR(IF('🎯 Metas'!I11="—",0,'🎯 Metas'!I11),0) -> 0 | J101: =IFERROR(IF('🎯 Metas'!I11="—",0,'🎯 Metas'!I11),0)*6 -> 0
B102: ← Digite quanto guardou por mês | C102: REAL | D102: 0 | E102: 0 | F102: 0 | G102: 0 | H102: 0 | I102: 0 | J102: ='🎯 Metas'!D11+SUM(D102,E102,F102,G102,H102,I102) -> 0
B103: Progresso — Alvo: ¥0 | Já guardado: ¥0 | C103: % | D103: 0 | E103: 0 | F103: 0 | G103: 0 | H103: 0 | I103: 0 | J103: 0
B104: ⭐ Outros | C104: PREV | D104: =IFERROR(IF('🎯 Metas'!I12="—",0,'🎯 Metas'!I12),0) -> 0 | E104: =IFERROR(IF('🎯 Metas'!I12="—",0,'🎯 Metas'!I12),0) -> 0 | F104: =IFERROR(IF('🎯 Metas'!I12="—",0,'🎯 Metas'!I12),0) -> 0 | G104: =IFERROR(IF('🎯 Metas'!I12="—",0,'🎯 Metas'!I12),0) -> 0 | H104: =IFERROR(IF('🎯 Metas'!I12="—",0,'🎯 Metas'!I12),0) -> 0 | I104: =IFERROR(IF('🎯 Metas'!I12="—",0,'🎯 Metas'!I12),0) -> 0 | J104: =IFERROR(IF('🎯 Metas'!I12="—",0,'🎯 Metas'!I12),0)*6 -> 0
B105: ← Digite quanto guardou por mês | C105: REAL | D105: 0 | E105: 0 | F105: 0 | G105: 0 | H105: 0 | I105: 0 | J105: ='🎯 Metas'!D12+SUM(D105,E105,F105,G105,H105,I105) -> 0
B106: Progresso — Alvo: ¥0 | Já guardado: ¥0 | C106: % | D106: 0 | E106: 0 | F106: 0 | G106: 0 | H106: 0 | I106: 0 | J106: 0
B109: 🩺 SAÚDE FINANCEIRA
B110: Total Entradas | C110: AUTO | D110: =D20 -> 429000 | E110: =E20 -> 0 | F110: =F20 -> 0 | G110: =G20 -> 0 | H110: =H20 -> 0 | I110: =I20 -> 0 | J110: =SUM(D110,E110,F110,G110,H110,I110) -> 429000
B111: Total Fixos | C111: AUTO | D111: =D53 -> 68412 | E111: =E53 -> 0 | F111: =F53 -> 0 | G111: =G53 -> 0 | H111: =H53 -> 0 | I111: =I53 -> 0 | J111: =SUM(D111,E111,F111,G111,H111,I111) -> 68412
...

Sheet 📊 Dashboard
B2: 💹 FINANÇAS PESSOAIS | JAPÃO | I2: MÊS DE REFERÊNCIA: | L2: 2025-05
I3: ↑ Altere o mês acima para filtrar o dashboard
B7: ⬆ TOTAL ENTRADAS | F7: ⬇ TOTAL SAÍDAS | J7: 💰 SALDO DO MÊS
B8: =B71 -> 429000 | F8: =D71 -> 111572 | J8: =F71 -> 317428
B10: Receitas do mês | F10: Despesas do mês | J10: Resultado líquido
B14: 🏠 GASTOS FIXOS | F14: 🛒 GASTOS VARIÁVEIS | J14: 📈 % ECONOMIZADO
B15: =B72 -> 📊 COMPARATIVO — ÚLTIMOS 6 MESES POR CATEGORIA | F15: =D72 -> 0 | J15: =H71 -> 0.73992541
B17: Contas recorrentes | F17: Despesas do dia a dia | J17: Taxa de poupança
B21: 🩺 INDICADOR DE SAÚDE FINANCEIRA
B23: =IF(H71>=0.2,"🟢 EXCELENTE – Você está economizando mais de 20%!",IF(H71>=0.1,"🟡 BOM – Economia entre 10-20%. Continue assim!",IF(H71>0,"🟠 ATENÇÃO – Economia abaixo de 10%. Revise os gastos.",IF(H71=0,"⚪ NEUTRO – Entradas igualam saídas.", "🔴 ALERTA – Gastos superiores às entradas!")))) -> 🟢 EXCELENTE – Você está economizando mais de 20%!
B25: Economia anual estimada: | F25: =F71*12 -> 3809136 | G25: Meta de economia: | J25: ='📅 Planejamento'!B8 -> Bônus
B29: 📈 EVOLUÇÃO MENSAL (Entradas vs Saídas) | I29: 🍩 GASTOS POR CATEGORIA
B50: 🏆 TOP GASTOS DO MÊS
B51: # | C51: Descrição | F51: Categoria | J51: Valor (¥) | L51: % do Total
B52: 1 | C52: =IFERROR(INDEX('📋 Movimentações'!$B$15:$B$514,MATCH(LARGE(IF(TEXT('📋 Movimentações'!$A$4:$A$503,"yyyy-mm")=L2,IF('📋 Movimentações'!$D$15:$D$514="Saída",'📋 Movimentações'!$E$15:$E$514)),1),IF(TEXT('📋 Movimentações'!$A$4:$A$503,"yyyy-mm")=L2,IF('📋 Movimentações'!$D$15:$D$514="Saída",'📋 Movimentações'!$E$15:$E$514)),0)),"-") -> - | J52: =IFERROR(LARGE(IF(TEXT('📋 Movimentações'!$A$4:$A$503,"yyyy-mm")=L2,IF('📋 Movimentações'!$D$15:$D$514="Saída",'📋 Movimentações'!$E$15:$E$514)),1),0) -> 0 | L52: =IFERROR(J52/D71,0) -> 0
B53: 2 | C53: =IFERROR(INDEX('📋 Movimentações'!$B$15:$B$514,MATCH(LARGE(IF(TEXT('📋 Movimentações'!$A$4:$A$503,"yyyy-mm")=L2,IF('📋 Movimentações'!$D$15:$D$514="Saída",'📋 Movimentações'!$E$15:$E$514)),2),IF(TEXT('📋 Movimentações'!$A$4:$A$503,"yyyy-mm")=L2,IF('📋 Movimentações'!$D$15:$D$514="Saída",'📋 Movimentações'!$E$15:$E$514)),0)),"-") -> - | J53: =IFERROR(LARGE(IF(TEXT('📋 Movimentações'!$A$4:$A$503,"yyyy-mm")=L2,IF('📋 Movimentações'!$D$15:$D$514="Saída",'📋 Movimentações'!$E$15:$E$514)),2),0) -> 0 | L53: =IFERROR(J53/D71,0) -> 0
B54: 3 | C54: =IFERROR(INDEX('📋 Movimentações'!$B$15:$B$514,MATCH(LARGE(IF(TEXT('📋 Movimentações'!$A$4:$A$503,"yyyy-mm")=L2,IF('📋 Movimentações'!$D$15:$D$514="Saída",'📋 Movimentações'!$E$15:$E$514)),3),IF(TEXT('📋 Movimentações'!$A$4:$A$503,"yyyy-mm")=L2,IF('📋 Movimentações'!$D$15:$D$514="Saída",'📋 Movimentações'!$E$15:$E$514)),0)),"-") -> - | J54: =IFERROR(LARGE(IF(TEXT('📋 Movimentações'!$A$4:$A$503,"yyyy-mm")=L2,IF('📋 Movimentações'!$D$15:$D$514="Saída",'📋 Movimentações'!$E$15:$E$514)),3),0) -> 0 | L54: =IFERROR(J54/D71,0) -> 0
B55: 4 | C55: =IFERROR(INDEX('📋 Movimentações'!$B$15:$B$514,MATCH(LARGE(IF(TEXT('📋 Movimentações'!$A$4:$A$503,"yyyy-mm")=L2,IF('📋 Movimentações'!$D$15:$D$514="Saída",'📋 Movimentações'!$E$15:$E$514)),4),IF(TEXT('📋 Movimentações'!$A$4:$A$503,"yyyy-mm")=L2,IF('📋 Movimentações'!$D$15:$D$514="Saída",'📋 Movimentações'!$E$15:$E$514)),0)),"-") -> - | J55: =IFERROR(LARGE(IF(TEXT('📋 Movimentações'!$A$4:$A$503,"yyyy-mm")=L2,IF('📋 Movimentações'!$D$15:$D$514="Saída",'📋 Movimentações'!$E$15:$E$514)),4),0) -> 0 | L55: =IFERROR(J55/D71,0) -> 0
B56: 5 | C56: =IFERROR(INDEX('📋 Movimentações'!$B$15:$B$514,MATCH(LARGE(IF(TEXT('📋 Movimentações'!$A$4:$A$503,"yyyy-mm")=L2,IF('📋 Movimentações'!$D$15:$D$514="Saída",'📋 Movimentações'!$E$15:$E$514)),5),IF(TEXT('📋 Movimentações'!$A$4:$A$503,"yyyy-mm")=L2,IF('📋 Movimentações'!$D$15:$D$514="Saída",'📋 Movimentações'!$E$15:$E$514)),0)),"-") -> - | J56: =IFERROR(LARGE(IF(TEXT('📋 Movimentações'!$A$4:$A$503,"yyyy-mm")=L2,IF('📋 Movimentações'!$D$15:$D$514="Saída",'📋 Movimentações'!$E$15:$E$514)),5),0) -> 0 | L56: =IFERROR(J56/D71,0) -> 0
B57: 6 | C57: =IFERROR(INDEX('📋 Movimentações'!$B$15:$B$514,MATCH(LARGE(IF(TEXT('📋 Movimentações'!$A$4:$A$503,"yyyy-mm")=L2,IF('📋 Movimentações'!$D$15:$D$514="Saída",'📋 Movimentações'!$E$15:$E$514)),6),IF(TEXT('📋 Movimentações'!$A$4:$A$503,"yyyy-mm")=L2,IF('📋 Movimentações'!$D$15:$D$514="Saída",'📋 Movimentações'!$E$15:$E$514)),0)),"-") -> - | J57: =IFERROR(LARGE(IF(TEXT('📋 Movimentações'!$A$4:$A$503,"yyyy-mm")=L2,IF('📋 Movimentações'!$D$15:$D$514="Saída",'📋 Movimentações'!$E$15:$E$514)),6),0) -> 0 | L57: =IFERROR(J57/D71,0) -> 0
B58: 7 | C58: =IFERROR(INDEX('📋 Movimentações'!$B$15:$B$514,MATCH(LARGE(IF(TEXT('📋 Movimentações'!$A$4:$A$503,"yyyy-mm")=L2,IF('📋 Movimentações'!$D$15:$D$514="Saída",'📋 Movimentações'!$E$15:$E$514)),7),IF(TEXT('📋 Movimentações'!$A$4:$A$503,"yyyy-mm")=L2,IF('📋 Movimentações'!$D$15:$D$514="Saída",'📋 Movimentações'!$E$15:$E$514)),0)),"-") -> - | J58: =IFERROR(LARGE(IF(TEXT('📋 Movimentações'!$A$4:$A$503,"yyyy-mm")=L2,IF('📋 Movimentações'!$D$15:$D$514="Saída",'📋 Movimentações'!$E$15:$E$514)),7),0) -> 0 | L58: =IFERROR(J58/D71,0) -> 0
B60: 📝 OBSERVAÇÕES DO MÊS
B61: Escreva aqui suas observações, metas e lembretes do mês...
B71: =SUMIFS('📋 Movimentações'!$F$15:$F$514,'📋 Movimentações'!$B$15:$B$514,">="&$P$71,'📋 Movimentações'!$B$15:$B$514,"<="&$Q$71,'📋 Movimentações'!$E$15:$E$514,"Entrada") -> 429000 | D71: =SUMIFS('📋 Movimentações'!$F$15:$F$514,'📋 Movimentações'!$B$15:$B$514,">="&$P$71,'📋 Movimentações'!$B$15:$B$514,"<="&$Q$71,'📋 Movimentações'!$E$15:$E$514,"Saída") -> 111572 | F71: =B71-D71 -> 317428 | H71: =IFERROR(1-D71/B71,0) -> 0.73992541 | N71: =VALUE(LEFT($L$2,4)) -> 2025 | O71: =VALUE(MID($L$2,6,2)) -> 5 | P71: =DATE(VALUE(LEFT($L$2,4)),VALUE(MID($L$2,6,2)),1) -> 45778 | Q71: =EOMONTH($P$71,0) -> 45808
B72: 📊 COMPARATIVO — ÚLTIMOS 6 MESES POR CATEGORIA
A73: Mês | B73: CATEGORIA | C73: M-5 | D73: M-4 | E73: M-3 | F73: M-2 | G73: M-1 | H73: Atual | I73: Ago | J73: Set | K73: Out | L73: Nov | M73: Dez
A74: Entradas | B74: Mercado | C74: =IFERROR(SUMIFS('📋 Movimentações'!$F$15:$F$514,'📋 Movimentações'!$B$15:$B$514,">="&DATE(YEAR(P71+-150),MONTH(P71+-150),1),'📋 Movimentações'!$B$15:$B$514,"<="&EOMONTH(DATE(YEAR(P71+-150),MONTH(P71+-150),1),0),'📋 Movimentações'!$E$15:$E$514,"Saída",'📋 Movimentações'!$D$15:$D$514,"Mercado"),0) -> 0 | D74: =IFERROR(SUMIFS('📋 Movimentações'!$F$15:$F$514,'📋 Movimentações'!$B$15:$B$514,">="&DATE(YEAR(P71+-120),MONTH(P71+-120),1),'📋 Movimentações'!$B$15:$B$514,"<="&EOMONTH(DATE(YEAR(P71+-120),MONTH(P71+-120),1),0),'📋 Movimentações'!$E$15:$E$514,"Saída",'📋 Movimentações'!$D$15:$D$514,"Mercado"),0) -> 0 | E74: =IFERROR(SUMIFS('📋 Movimentações'!$F$15:$F$514,'📋 Movimentações'!$B$15:$B$514,">="&DATE(YEAR(P71+-90),MONTH(P71+-90),1),'📋 Movimentações'!$B$15:$B$514,"<="&EOMONTH(DATE(YEAR(P71+-90),MONTH(P71+-90),1),0),'📋 Movimentações'!$E$15:$E$514,"Saída",'📋 Movimentações'!$D$15:$D$514,"Mercado"),0) -> 0 | F74: =IFERROR(SUMIFS('📋 Movimentações'!$F$15:$F$514,'📋 Movimentações'!$B$15:$B$514,">="&DATE(YEAR(P71+-60),MONTH(P71+-60),1),'📋 Movimentações'!$B$15:$B$514,"<="&EOMONTH(DATE(YEAR(P71+-60),MONTH(P71+-60),1),0),'📋 Movimentações'!$E$15:$E$514,"Saída",'📋 Movimentações'!$D$15:$D$514,"Mercado"),0) -> 0 | G74: =IFERROR(SUMIFS('📋 Movimentações'!$F$15:$F$514,'📋 Movimentações'!$B$15:$B$514,">="&DATE(YEAR(P71+-30),MONTH(P71+-30),1),'📋 Movimentações'!$B$15:$B$514,"<="&EOMONTH(DATE(YEAR(P71+-30),MONTH(P71+-30),1),0),'📋 Movimentações'!$E$15:$E$514,"Saída",'📋 Movimentações'!$D$15:$D$514,"Mercado"),0) -> 0 | H74: =IFERROR(SUMIFS('📋 Movimentações'!$F$15:$F$514,'📋 Movimentações'!$B$15:$B$514,">="&DATE(YEAR(P71+0),MONTH(P71+0),1),'📋 Movimentações'!$B$15:$B$514,"<="&EOMONTH(DATE(YEAR(P71+0),MONTH(P71+0),1),0),'📋 Movimentações'!$E$15:$E$514,"Saída",'📋 Movimentações'!$D$15:$D$514,"Mercado"),0) -> 0 | I74: 298000 | J74: 305000 | K74: 290000 | L74: 295000 | M74: 310000
A75: Saídas | B75: Transporte | C75: =IFERROR(SUMIFS('📋 Movimentações'!$F$15:$F$514,'📋 Movimentações'!$B$15:$B$514,">="&DATE(YEAR(P71+-150),MONTH(P71+-150),1),'📋 Movimentações'!$B$15:$B$514,"<="&EOMONTH(DATE(YEAR(P71+-150),MONTH(P71+-150),1),0),'📋 Movimentações'!$E$15:$E$514,"Saída",'📋 Movimentações'!$D$15:$D$514,"Transporte"),0) -> 0 | D75: =IFERROR(SUMIFS('📋 Movimentações'!$F$15:$F$514,'📋 Movimentações'!$B$15:$B$514,">="&DATE(YEAR(P71+-120),MONTH(P71+-120),1),'📋 Movimentações'!$B$15:$B$514,"<="&EOMONTH(DATE(YEAR(P71+-120),MONTH(P71+-120),1),0),'📋 Movimentações'!$E$15:$E$514,"Saída",'📋 Movimentações'!$D$15:$D$514,"Transporte"),0) -> 0 | E75: =IFERROR(SUMIFS('📋 Movimentações'!$F$15:$F$514,'📋 Movimentações'!$B$15:$B$514,">="&DATE(YEAR(P71+-90),MONTH(P71+-90),1),'📋 Movimentações'!$B$15:$B$514,"<="&EOMONTH(DATE(YEAR(P71+-90),MONTH(P71+-90),1),0),'📋 Movimentações'!$E$15:$E$514,"Saída",'📋 Movimentações'!$D$15:$D$514,"Transporte"),0) -> 0 | F75: =IFERROR(SUMIFS('📋 Movimentações'!$F$15:$F$514,'📋 Movimentações'!$B$15:$B$514,">="&DATE(YEAR(P71+-60),MONTH(P71+-60),1),'📋 Movimentações'!$B$15:$B$514,"<="&EOMONTH(DATE(YEAR(P71+-60),MONTH(P71+-60),1),0),'📋 Movimentações'!$E$15:$E$514,"Saída",'📋 Movimentações'!$D$15:$D$514,"Transporte"),0) -> 0 | G75: =IFERROR(SUMIFS('📋 Movimentações'!$F$15:$F$514,'📋 Movimentações'!$B$15:$B$514,">="&DATE(YEAR(P71+-30),MONTH(P71+-30),1),'📋 Movimentações'!$B$15:$B$514,"<="&EOMONTH(DATE(YEAR(P71+-30),MONTH(P71+-30),1),0),'📋 Movimentações'!$E$15:$E$514,"Saída",'📋 Movimentações'!$D$15:$D$514,"Transporte"),0) -> 0 | H75: =IFERROR(SUMIFS('📋 Movimentações'!$F$15:$F$514,'📋 Movimentações'!$B$15:$B$514,">="&DATE(YEAR(P71+0),MONTH(P71+0),1),'📋 Movimentações'!$B$15:$B$514,"<="&EOMONTH(DATE(YEAR(P71+0),MONTH(P71+0),1),0),'📋 Movimentações'!$E$15:$E$514,"Saída",'📋 Movimentações'!$D$15:$D$514,"Transporte"),0) -> 0 | I75: 255000 | J75: 270000 | K75: 240000 | L75: 250000 | M75: 280000
A76: Economia | B76: Lazer | C76: =IFERROR(SUMIFS('📋 Movimentações'!$F$15:$F$514,'📋 Movimentações'!$B$15:$B$514,">="&DATE(YEAR(P71+-150),MONTH(P71+-150),1),'📋 Movimentações'!$B$15:$B$514,"<="&EOMONTH(DATE(YEAR(P71+-150),MONTH(P71+-150),1),0),'📋 Movimentações'!$E$15:$E$514,"Saída",'📋 Movimentações'!$D$15:$D$514,"Lazer"),0) -> 0 | D76: =IFERROR(SUMIFS('📋 Movimentações'!$F$15:$F$514,'📋 Movimentações'!$B$15:$B$514,">="&DATE(YEAR(P71+-120),MONTH(P71+-120),1),'📋 Movimentações'!$B$15:$B$514,"<="&EOMONTH(DATE(YEAR(P71+-120),MONTH(P71+-120),1),0),'📋 Movimentações'!$E$15:$E$514,"Saída",'📋 Movimentações'!$D$15:$D$514,"Lazer"),0) -> 0 | E76: =IFERROR(SUMIFS('📋 Movimentações'!$F$15:$F$514,'📋 Movimentações'!$B$15:$B$514,">="&DATE(YEAR(P71+-90),MONTH(P71+-90),1),'📋 Movimentações'!$B$15:$B$514,"<="&EOMONTH(DATE(YEAR(P71+-90),MONTH(P71+-90),1),0),'📋 Movimentações'!$E$15:$E$514,"Saída",'📋 Movimentações'!$D$15:$D$514,"Lazer"),0) -> 0 | F76: =IFERROR(SUMIFS('📋 Movimentações'!$F$15:$F$514,'📋 Movimentações'!$B$15:$B$514,">="&DATE(YEAR(P71+-60),MONTH(P71+-60),1),'📋 Movimentações'!$B$15:$B$514,"<="&EOMONTH(DATE(YEAR(P71+-60),MONTH(P71+-60),1),0),'📋 Movimentações'!$E$15:$E$514,"Saída",'📋 Movimentações'!$D$15:$D$514,"Lazer"),0) -> 0 | G76: =IFERROR(SUMIFS('📋 Movimentações'!$F$15:$F$514,'📋 Movimentações'!$B$15:$B$514,">="&DATE(YEAR(P71+-30),MONTH(P71+-30),1),'📋 Movimentações'!$B$15:$B$514,"<="&EOMONTH(DATE(YEAR(P71+-30),MONTH(P71+-30),1),0),'📋 Movimentações'!$E$15:$E$514,"Saída",'📋 Movimentações'!$D$15:$D$514,"Lazer"),0) -> 0 | H76: =IFERROR(SUMIFS('📋 Movimentações'!$F$15:$F$514,'📋 Movimentações'!$B$15:$B$514,">="&DATE(YEAR(P71+0),MONTH(P71+0),1),'📋 Movimentações'!$B$15:$B$514,"<="&EOMONTH(DATE(YEAR(P71+0),MONTH(P71+0),1),0),'📋 Movimentações'!$E$15:$E$514,"Saída",'📋 Movimentações'!$D$15:$D$514,"Lazer"),0) -> 0 | I76: 43000 | J76: 35000 | K76: 50000 | L76: 45000 | M76: 30000
A77: Categoria | B77: Remessa Brasil | C77: =IFERROR(SUMIFS('📋 Movimentações'!$F$15:$F$514,'📋 Movimentações'!$B$15:$B$514,">="&DATE(YEAR(P71+-150),MONTH(P71+-150),1),'📋 Movimentações'!$B$15:$B$514,"<="&EOMONTH(DATE(YEAR(P71+-150),MONTH(P71+-150),1),0),'📋 Movimentações'!$E$15:$E$514,"Saída",'📋 Movimentações'!$D$15:$D$514,"Remessa Brasil"),0) -> 0 | D77: =IFERROR(SUMIFS('📋 Movimentações'!$F$15:$F$514,'📋 Movimentações'!$B$15:$B$514,">="&DATE(YEAR(P71+-120),MONTH(P71+-120),1),'📋 Movimentações'!$B$15:$B$514,"<="&EOMONTH(DATE(YEAR(P71+-120),MONTH(P71+-120),1),0),'📋 Movimentações'!$E$15:$E$514,"Saída",'📋 Movimentações'!$D$15:$D$514,"Remessa Brasil"),0) -> 0 | E77: =IFERROR(SUMIFS('📋 Movimentações'!$F$15:$F$514,'📋 Movimentações'!$B$15:$B$514,">="&DATE(YEAR(P71+-90),MONTH(P71+-90),1),'📋 Movimentações'!$B$15:$B$514,"<="&EOMONTH(DATE(YEAR(P71+-90),MONTH(P71+-90),1),0),'📋 Movimentações'!$E$15:$E$514,"Saída",'📋 Movimentações'!$D$15:$D$514,"Remessa Brasil"),0) -> 0 | F77: =IFERROR(SUMIFS('📋 Movimentações'!$F$15:$F$514,'📋 Movimentações'!$B$15:$B$514,">="&DATE(YEAR(P71+-60),MONTH(P71+-60),1),'📋 Movimentações'!$B$15:$B$514,"<="&EOMONTH(DATE(YEAR(P71+-60),MONTH(P71+-60),1),0),'📋 Movimentações'!$E$15:$E$514,"Saída",'📋 Movimentações'!$D$15:$D$514,"Remessa Brasil"),0) -> 0 | G77: =IFERROR(SUMIFS('📋 Movimentações'!$F$15:$F$514,'📋 Movimentações'!$B$15:$B$514,">="&DATE(YEAR(P71+-30),MONTH(P71+-30),1),'📋 Movimentações'!$B$15:$B$514,"<="&EOMONTH(DATE(YEAR(P71+-30),MONTH(P71+-30),1),0),'📋 Movimentações'!$E$15:$E$514,"Saída",'📋 Movimentações'!$D$15:$D$514,"Remessa Brasil"),0) -> 0 | H77: =IFERROR(SUMIFS('📋 Movimentações'!$F$15:$F$514,'📋 Movimentações'!$B$15:$B$514,">="&DATE(YEAR(P71+0),MONTH(P71+0),1),'📋 Movimentações'!$B$15:$B$514,"<="&EOMONTH(DATE(YEAR(P71+0),MONTH(P71+0),1),0),'📋 Movimentações'!$E$15:$E$514,"Saída",'📋 Movimentações'!$D$15:$D$514,"Remessa Brasil"),0) -> 0
A78: Aluguel | B78: Restaurantes | C78: =IFERROR(SUMIFS('📋 Movimentações'!$F$15:$F$514,'📋 Movimentações'!$B$15:$B$514,">="&DATE(YEAR(P71+-150),MONTH(P71+-150),1),'📋 Movimentações'!$B$15:$B$514,"<="&EOMONTH(DATE(YEAR(P71+-150),MONTH(P71+-150),1),0),'📋 Movimentações'!$E$15:$E$514,"Saída",'📋 Movimentações'!$D$15:$D$514,"Restaurantes"),0) -> 0 | D78: =IFERROR(SUMIFS('📋 Movimentações'!$F$15:$F$514,'📋 Movimentações'!$B$15:$B$514,">="&DATE(YEAR(P71+-120),MONTH(P71+-120),1),'📋 Movimentações'!$B$15:$B$514,"<="&EOMONTH(DATE(YEAR(P71+-120),MONTH(P71+-120),1),0),'📋 Movimentações'!$E$15:$E$514,"Saída",'📋 Movimentações'!$D$15:$D$514,"Restaurantes"),0) -> 0 | E78: =IFERROR(SUMIFS('📋 Movimentações'!$F$15:$F$514,'📋 Movimentações'!$B$15:$B$514,">="&DATE(YEAR(P71+-90),MONTH(P71+-90),1),'📋 Movimentações'!$B$15:$B$514,"<="&EOMONTH(DATE(YEAR(P71+-90),MONTH(P71+-90),1),0),'📋 Movimentações'!$E$15:$E$514,"Saída",'📋 Movimentações'!$D$15:$D$514,"Restaurantes"),0) -> 0 | F78: =IFERROR(SUMIFS('📋 Movimentações'!$F$15:$F$514,'📋 Movimentações'!$B$15:$B$514,">="&DATE(YEAR(P71+-60),MONTH(P71+-60),1),'📋 Movimentações'!$B$15:$B$514,"<="&EOMONTH(DATE(YEAR(P71+-60),MONTH(P71+-60),1),0),'📋 Movimentações'!$E$15:$E$514,"Saída",'📋 Movimentações'!$D$15:$D$514,"Restaurantes"),0) -> 0 | G78: =IFERROR(SUMIFS('📋 Movimentações'!$F$15:$F$514,'📋 Movimentações'!$B$15:$B$514,">="&DATE(YEAR(P71+-30),MONTH(P71+-30),1),'📋 Movimentações'!$B$15:$B$514,"<="&EOMONTH(DATE(YEAR(P71+-30),MONTH(P71+-30),1),0),'📋 Movimentações'!$E$15:$E$514,"Saída",'📋 Movimentações'!$D$15:$D$514,"Restaurantes"),0) -> 0 | H78: =IFERROR(SUMIFS('📋 Movimentações'!$F$15:$F$514,'📋 Movimentações'!$B$15:$B$514,">="&DATE(YEAR(P71+0),MONTH(P71+0),1),'📋 Movimentações'!$B$15:$B$514,"<="&EOMONTH(DATE(YEAR(P71+0),MONTH(P71+0),1),0),'📋 Movimentações'!$E$15:$E$514,"Saída",'📋 Movimentações'!$D$15:$D$514,"Restaurantes"),0) -> 0
A79: Mercado | B79: 45000
A80: Carro | B80: 30000
A81: Restaurante | B81: 25000
A82: Internet/Cel | B82: 15000
A83: Lazer | B83: 20000
A84: Saúde | B84: 12000
A85: Outros | B85: 18000

Sheet 📋 Movimentações
B2: 📋 MOVIMENTAÇÕES FINANCEIRAS
B4: ⚡ LANÇAMENTO RÁPIDO — edite o valor, copie a linha para a tabela principal
B5: DATA | C5: DESCRIÇÃO | D5: CATEGORIA | E5: TIPO | F5: VALOR (¥) | G5: PAGAMENTO | H5: OBS
B6: 46169 | C6: Salário | D6: Salário | E6: Entrada | F6: 374000 | G6: Transferência Bancária | H6: ← edite valor e data, depois copie esta linha para abaixo
B7: 46169 | C7: Aluguel | D7: Aluguel | E7: Saída | F7: 30000 | G7: Débito Automático | H7: ← edite valor e data, depois copie esta linha para abaixo
B8: 46169 | C8: Mercado | D8: Mercado | E8: Saída | G8: Rakuten Pay | H8: ← edite valor e data, depois copie esta linha para abaixo
B9: 46169 | C9: Gasolina | D9: Gasolina | E9: Saída | G9: PayPay | H9: ← edite valor e data, depois copie esta linha para abaixo
B10: 46169 | C10: Konbini | D10: Konbini | E10: Saída | G10: Dinheiro | H10: ← edite valor e data, depois copie esta linha para abaixo
B11: 46169 | C11: Remessa Brasil | D11: Remessa Brasil | E11: Saída | G11: Transferência Bancária | H11: ← edite valor e data, depois copie esta linha para abaixo
B14: DATA | C14: DESCRIÇÃO | D14: CATEGORIA | E14: TIPO | F14: VALOR (¥) | G14: PAGAMENTO | H14: OBSERVAÇÕES
B15: 45802 | C15: Salário janeiro | D15: Salário | E15: Entrada | F15: 374000 | G15: Transferência Bancária
B16: 45802 | C16: Hora extra janeiro | D16: Bônus | E16: Entrada | F16: 55000 | G16: Transferência Bancária
B17: 45802 | C17: Aluguel janeiro | D17: Aluguel | E17: Saída | F17: 30000 | G17: Dinheiro
B18: 45802 | C18: Mercado | D18: Mercado | E18: Saída | F18: 0 | G18: Dinheiro | H18: Compras da semana
B19: 45802 | C19: Internet NTT | D19: Internet | E19: Saída | F19: 0 | G19: Dinheiro
B20: 45802 | C20: Celular Docomo | D20: Celular | E20: Saída | F20: 32412 | G20: Dinheiro
B21: 45802 | C21: Gasolina ENEOS | D21: Gasolina | E21: Saída | F21: 0 | G21: Dinheiro
B22: 45802 | C22: Restaurante | D22: Restaurantes | E22: Saída | F22: 0 | G22: Dinheiro
B23: 45802 | C23: Academia | D23: Academia | E23: Saída | F23: 6000 | G23: Dinheiro
B24: 45802 | C24: Konbini 7-Eleven | D24: Konbini | E24: Saída | F24: 0 | G24: Dinheiro
B25: 45802 | C25: Carro Financiamento | D25: R | E25: Saída | F25: 43160
B515: TOTAL ENTRADAS: | F515: =SUMIF(E15:E514,"Entrada",F15:F514) -> 429000
B516: TOTAL SAÍDAS: | F516: =SUMIF(E15:E514,"Saída",F15:F514) -> 111572

Sheet 🏠 Gastos Fixos
B2: 🏠 GASTOS FIXOS MENSAIS
B4: CONTA / SERVIÇO | C4: VALOR (¥) | D4: VENCIMENTO | E4: CATEGORIA | F4: STATUS | G4: OBSERVAÇÕES | H4: DIAS P/ VENCER
B5: Aluguel | C5: 30100 | D5: Dia 01 | E5: Moradia | F5: Pago | H5: =IFERROR(IF(LEFT(D5,3)="Dia",IF(VALUE(MID(D5,5,2))-DAY(TODAY())>=0,VALUE(MID(D5,5,2))-DAY(TODAY()),VALUE(MID(D5,5,2))-DAY(TODAY())+DAY(EOMONTH(TODAY(),0))),"-"),"-") -> 4
B6: Luz – TEPCO/関電 | C6: 0 | D6: Dia 20 | E6: Utilities | F6: Pendente | H6: =IFERROR(IF(LEFT(D6,3)="Dia",IF(VALUE(MID(D6,5,2))-DAY(TODAY())>=0,VALUE(MID(D6,5,2))-DAY(TODAY()),VALUE(MID(D6,5,2))-DAY(TODAY())+DAY(EOMONTH(TODAY(),0))),"-"),"-") -> 23
B7: Água – 水道 | C7: 8581 | D7: Dia 25 | E7: Utilities | F7: Pago | H7: =IFERROR(IF(LEFT(D7,3)="Dia",IF(VALUE(MID(D7,5,2))-DAY(TODAY())>=0,VALUE(MID(D7,5,2))-DAY(TODAY()),VALUE(MID(D7,5,2))-DAY(TODAY())+DAY(EOMONTH(TODAY(),0))),"-"),"-") -> 28
B8: Gás – ガス | C8: 4800 | D8: Dia 15 | E8: Utilities | F8: Pago | H8: =IFERROR(IF(LEFT(D8,3)="Dia",IF(VALUE(MID(D8,5,2))-DAY(TODAY())>=0,VALUE(MID(D8,5,2))-DAY(TODAY()),VALUE(MID(D8,5,2))-DAY(TODAY())+DAY(EOMONTH(TODAY(),0))),"-"),"-") -> 18
B9: Internet – NTT/光 | C9: 6000 | D9: Dia 27 | E9: Comunicação | F9: Pendente | H9: =IFERROR(IF(LEFT(D9,3)="Dia",IF(VALUE(MID(D9,5,2))-DAY(TODAY())>=0,VALUE(MID(D9,5,2))-DAY(TODAY()),VALUE(MID(D9,5,2))-DAY(TODAY())+DAY(EOMONTH(TODAY(),0))),"-"),"-") -> 30
B10: Celular – Docomo/AU | C10: 32412 | D10: Dia 10 | E10: Comunicação | F10: Pago | H10: =IFERROR(IF(LEFT(D10,3)="Dia",IF(VALUE(MID(D10,5,2))-DAY(TODAY())>=0,VALUE(MID(D10,5,2))-DAY(TODAY()),VALUE(MID(D10,5,2))-DAY(TODAY())+DAY(EOMONTH(TODAY(),0))),"-"),"-") -> 13
B11: Academia | C11: 6000 | D11: Dia 01 | E11: Saúde | F11: Pendente | H11: =IFERROR(IF(LEFT(D11,3)="Dia",IF(VALUE(MID(D11,5,2))-DAY(TODAY())>=0,VALUE(MID(D11,5,2))-DAY(TODAY()),VALUE(MID(D11,5,2))-DAY(TODAY())+DAY(EOMONTH(TODAY(),0))),"-"),"-") -> 4
B12: Seguro de Vida | C12: 0 | D12: Dia 01 | E12: Seguros | F12: Pendente | H12: =IFERROR(IF(LEFT(D12,3)="Dia",IF(VALUE(MID(D12,5,2))-DAY(TODAY())>=0,VALUE(MID(D12,5,2))-DAY(TODAY()),VALUE(MID(D12,5,2))-DAY(TODAY())+DAY(EOMONTH(TODAY(),0))),"-"),"-") -> 4
B13: Seguro do Carro | C13: 16000 | D13: Dia 15 | E13: Seguros | F13: Pendente | H13: =IFERROR(IF(LEFT(D13,3)="Dia",IF(VALUE(MID(D13,5,2))-DAY(TODAY())>=0,VALUE(MID(D13,5,2))-DAY(TODAY()),VALUE(MID(D13,5,2))-DAY(TODAY())+DAY(EOMONTH(TODAY(),0))),"-"),"-") -> 18
B14: Netflix / Disney+ | C14: 1000 | D14: Dia 18 | E14: Lazer | F14: Pendente | H14: =IFERROR(IF(LEFT(D14,3)="Dia",IF(VALUE(MID(D14,5,2))-DAY(TODAY())>=0,VALUE(MID(D14,5,2))-DAY(TODAY()),VALUE(MID(D14,5,2))-DAY(TODAY())+DAY(EOMONTH(TODAY(),0))),"-"),"-") -> 21
B15: Spotify | C15: 0 | D15: Dia 22 | E15: Lazer | F15: Pendente | H15: =IFERROR(IF(LEFT(D15,3)="Dia",IF(VALUE(MID(D15,5,2))-DAY(TODAY())>=0,VALUE(MID(D15,5,2))-DAY(TODAY()),VALUE(MID(D15,5,2))-DAY(TODAY())+DAY(EOMONTH(TODAY(),0))),"-"),"-") -> 25
B16: Escola / Creche | C16: 8000 | D16: Dia 01 | E16: Educação | F16: Pendente | G16: Preencha se aplicável | H16: =IFERROR(IF(LEFT(D16,3)="Dia",IF(VALUE(MID(D16,5,2))-DAY(TODAY())>=0,VALUE(MID(D16,5,2))-DAY(TODAY()),VALUE(MID(D16,5,2))-DAY(TODAY())+DAY(EOMONTH(TODAY(),0))),"-"),"-") -> 4
B17: Financiamento | C17: 43160 | D17: Dia 25 | E17: Financiamento | F17: Pago | H17: =IFERROR(IF(LEFT(D17,3)="Dia",IF(VALUE(MID(D17,5,2))-DAY(TODAY())>=0,VALUE(MID(D17,5,2))-DAY(TODAY()),VALUE(MID(D17,5,2))-DAY(TODAY())+DAY(EOMONTH(TODAY(),0))),"-"),"-") -> 28
B18: Outros | C18: 7000 | D18: - | E18: Outros | F18: Pago | H18: =IFERROR(IF(LEFT(D18,3)="Dia",IF(VALUE(MID(D18,5,2))-DAY(TODAY())>=0,VALUE(MID(D18,5,2))-DAY(TODAY()),VALUE(MID(D18,5,2))-DAY(TODAY())+DAY(EOMONTH(TODAY(),0))),"-"),"-") -> -
B21: 📊 RESUMO DOS GASTOS FIXOS
B23: Total Mensal Fixo: | C23: =SUM(C5:C18) -> 163053 | E23: Contas Pagas: | F23: =COUNTIF(F5:F18,"Pago")&" de "&COUNTA(B5:B18) -> 6 de 14
B24: Total Pago: | C24: =SUMIF(F5:F18,"Pago",C5:C18) -> 126053 | E24: Total Pendente: | F24: =SUMIF(F5:F18,"Pendente",C5:C18) -> 37000
B25: Total Atrasado: | C25: =SUMIF(F5:F18,"Atrasado",C5:C18) -> 0 | E25: % do Mês Pago: | F25: =IFERROR(SUMIF(F5:F18,"Pago",C5:C18)/SUM(C5:C18),0) -> 0.77307992
B27: 🔴 Vence em até 3 dias 🟡 Vence em até 7 dias 🟢 OK

Sheet 📅 Planejamento
B2: 📅 PLANEJAMENTO MENSAL | F2: ← Mês de referência: Dashboard L2
B4: ITEM | D4: PREVISTO (¥) | E4: REALIZADO (¥) | F4: DIFERENÇA (¥) | G4: STATUS | H4: %
B5: ▲ ENTRADAS
B6: Salário | D6: 285000 | E6: =SUMIFS('📋 Movimentações'!$F$15:$F$514,'📋 Movimentações'!$B$15:$B$514,">="&'📊 Dashboard'!$P$71,'📋 Movimentações'!$B$15:$B$514,"<="&'📊 Dashboard'!$Q$71,'📋 Movimentações'!$E$15:$E$514,"Entrada",'📋 Movimentações'!$D$15:$D$514,"Salário") -> 374000 | F6: =E6-D6 -> 89000 | G6: =IF(E6=0,"—",IF(E6>=D6,"✅ OK","⚠️ Atenção")) -> ✅ OK | H6: =IFERROR(E6/D6,0) -> 1.3122807
B7: Hora Extra | D7: 20000 | E7: =SUMIFS('📋 Movimentações'!$F$15:$F$514,'📋 Movimentações'!$B$15:$B$514,">="&'📊 Dashboard'!$P$71,'📋 Movimentações'!$B$15:$B$514,"<="&'📊 Dashboard'!$Q$71,'📋 Movimentações'!$E$15:$E$514,"Entrada",'📋 Movimentações'!$D$15:$D$514,"Hora Extra") -> 0 | F7: =E7-D7 -> -20000 | G7: =IF(E7=0,"—",IF(E7>=D7,"✅ OK","⚠️ Atenção")) -> — | H7: =IFERROR(E7/D7,0) -> 0
B8: Bônus | D8: 0 | E8: =SUMIFS('📋 Movimentações'!$F$15:$F$514,'📋 Movimentações'!$B$15:$B$514,">="&'📊 Dashboard'!$P$71,'📋 Movimentações'!$B$15:$B$514,"<="&'📊 Dashboard'!$Q$71,'📋 Movimentações'!$E$15:$E$514,"Entrada",'📋 Movimentações'!$D$15:$D$514,"Bônus") -> 55000 | F8: =E8-D8 -> 55000 | G8: =IF(E8=0,"—",IF(E8>=D8,"✅ OK","⚠️ Atenção")) -> ✅ OK | H8: =IFERROR(E8/D8,0) -> 0
B9: Arubaito/Extra | D9: 0 | E9: =SUMIFS('📋 Movimentações'!$F$15:$F$514,'📋 Movimentações'!$B$15:$B$514,">="&'📊 Dashboard'!$P$71,'📋 Movimentações'!$B$15:$B$514,"<="&'📊 Dashboard'!$Q$71,'📋 Movimentações'!$E$15:$E$514,"Entrada",'📋 Movimentações'!$D$15:$D$514,"Arubaito/Extra") -> 0 | F9: =E9-D9 -> 0 | G9: =IF(E9=0,"—",IF(E9>=D9,"✅ OK","⚠️ Atenção")) -> — | H9: =IFERROR(E9/D9,0) -> 0
B10: Reembolso | D10: 0 | E10: =SUMIFS('📋 Movimentações'!$F$15:$F$514,'📋 Movimentações'!$B$15:$B$514,">="&'📊 Dashboard'!$P$71,'📋 Movimentações'!$B$15:$B$514,"<="&'📊 Dashboard'!$Q$71,'📋 Movimentações'!$E$15:$E$514,"Entrada",'📋 Movimentações'!$D$15:$D$514,"Reembolso") -> 0 | F10: =E10-D10 -> 0 | G10: =IF(E10=0,"—",IF(E10>=D10,"✅ OK","⚠️ Atenção")) -> — | H10: =IFERROR(E10/D10,0) -> 0
B11: TOTAL ENTRADAS | D11: =D6+D7+D8+D9+D10 -> 305000 | E11: =SUMIFS('📋 Movimentações'!$F$15:$F$514,'📋 Movimentações'!$B$15:$B$514,">="&'📊 Dashboard'!$P$71,'📋 Movimentações'!$B$15:$B$514,"<="&'📊 Dashboard'!$Q$71,'📋 Movimentações'!$E$15:$E$514,"Entrada") -> 429000 | F11: =E11-D11 -> 124000 | G11: =IF(E11>=D11,"✅ OK","⚠️ Atenção") -> ✅ OK | H11: =IFERROR(E11/D11,0) -> 1.4065574
B13: 🏠 GASTOS FIXOS (puxados automaticamente da aba Gastos Fixos)
B14: 💡 Os valores abaixo são lidos direto da aba 🏠 Gastos Fixos — não precisa redigitar nada.
B15: Aluguel | D15: ='🏠 Gastos Fixos'!C5 -> 30100 | E15: =SUMIFS('📋 Movimentações'!$F$15:$F$514,'📋 Movimentações'!$B$15:$B$514,">="&'📊 Dashboard'!$P$71,'📋 Movimentações'!$B$15:$B$514,"<="&'📊 Dashboard'!$Q$71,'📋 Movimentações'!$E$15:$E$514,"Saída",'📋 Movimentações'!$D$15:$D$514,"Aluguel") -> 30000 | F15: =E15-D15 -> -100 | G15: =IF(E15=0,"—",IF(ABS(E15-D15)<=D15*0.1,"✅ OK","⚠️ Atenção")) -> ✅ OK | H15: =IFERROR(E15/D15,0) -> 0.99667774
B16: Luz | D16: ='🏠 Gastos Fixos'!C6 -> 0 | E16: =SUMIFS('📋 Movimentações'!$F$15:$F$514,'📋 Movimentações'!$B$15:$B$514,">="&'📊 Dashboard'!$P$71,'📋 Movimentações'!$B$15:$B$514,"<="&'📊 Dashboard'!$Q$71,'📋 Movimentações'!$E$15:$E$514,"Saída",'📋 Movimentações'!$D$15:$D$514,"Luz") -> 0 | F16: =E16-D16 -> 0 | G16: =IF(E16=0,"—",IF(ABS(E16-D16)<=D16*0.1,"✅ OK","⚠️ Atenção")) -> — | H16: =IFERROR(E16/D16,0) -> 0
B17: Água | D17: ='🏠 Gastos Fixos'!C7 -> 8581 | E17: =SUMIFS('📋 Movimentações'!$F$15:$F$514,'📋 Movimentações'!$B$15:$B$514,">="&'📊 Dashboard'!$P$71,'📋 Movimentações'!$B$15:$B$514,"<="&'📊 Dashboard'!$Q$71,'📋 Movimentações'!$E$15:$E$514,"Saída",'📋 Movimentações'!$D$15:$D$514,"Água") -> 0 | F17: =E17-D17 -> -8581 | G17: =IF(E17=0,"—",IF(ABS(E17-D17)<=D17*0.1,"✅ OK","⚠️ Atenção")) -> — | H17: =IFERROR(E17/D17,0) -> 0
B18: Gás | D18: ='🏠 Gastos Fixos'!C8 -> 4800 | E18: =SUMIFS('📋 Movimentações'!$F$15:$F$514,'📋 Movimentações'!$B$15:$B$514,">="&'📊 Dashboard'!$P$71,'📋 Movimentações'!$B$15:$B$514,"<="&'📊 Dashboard'!$Q$71,'📋 Movimentações'!$E$15:$E$514,"Saída",'📋 Movimentações'!$D$15:$D$514,"Gás") -> 0 | F18: =E18-D18 -> -4800 | G18: =IF(E18=0,"—",IF(ABS(E18-D18)<=D18*0.1,"✅ OK","⚠️ Atenção")) -> — | H18: =IFERROR(E18/D18,0) -> 0
B19: Internet | D19: ='🏠 Gastos Fixos'!C9 -> 6000 | E19: =SUMIFS('📋 Movimentações'!$F$15:$F$514,'📋 Movimentações'!$B$15:$B$514,">="&'📊 Dashboard'!$P$71,'📋 Movimentações'!$B$15:$B$514,"<="&'📊 Dashboard'!$Q$71,'📋 Movimentações'!$E$15:$E$514,"Saída",'📋 Movimentações'!$D$15:$D$514,"Internet") -> 0 | F19: =E19-D19 -> -6000 | G19: =IF(E19=0,"—",IF(ABS(E19-D19)<=D19*0.1,"✅ OK","⚠️ Atenção")) -> — | H19: =IFERROR(E19/D19,0) -> 0
B20: Celular | D20: ='🏠 Gastos Fixos'!C10 -> 32412 | E20: =SUMIFS('📋 Movimentações'!$F$15:$F$514,'📋 Movimentações'!$B$15:$B$514,">="&'📊 Dashboard'!$P$71,'📋 Movimentações'!$B$15:$B$514,"<="&'📊 Dashboard'!$Q$71,'📋 Movimentações'!$E$15:$E$514,"Saída",'📋 Movimentações'!$D$15:$D$514,"Celular") -> 32412 | F20: =E20-D20 -> 0 | G20: =IF(E20=0,"—",IF(ABS(E20-D20)<=D20*0.1,"✅ OK","⚠️ Atenção")) -> ✅ OK | H20: =IFERROR(E20/D20,0) -> 1
B21: Academia | D21: ='🏠 Gastos Fixos'!C11 -> 6000 | E21: =SUMIFS('📋 Movimentações'!$F$15:$F$514,'📋 Movimentações'!$B$15:$B$514,">="&'📊 Dashboard'!$P$71,'📋 Movimentações'!$B$15:$B$514,"<="&'📊 Dashboard'!$Q$71,'📋 Movimentações'!$E$15:$E$514,"Saída",'📋 Movimentações'!$D$15:$D$514,"Academia") -> 6000 | F21: =E21-D21 -> 0 | G21: =IF(E21=0,"—",IF(ABS(E21-D21)<=D21*0.1,"✅ OK","⚠️ Atenção")) -> ✅ OK | H21: =IFERROR(E21/D21,0) -> 1
B22: Seguro de Vida | D22: ='🏠 Gastos Fixos'!C12 -> 0 | E22: =SUMIFS('📋 Movimentações'!$F$15:$F$514,'📋 Movimentações'!$B$15:$B$514,">="&'📊 Dashboard'!$P$71,'📋 Movimentações'!$B$15:$B$514,"<="&'📊 Dashboard'!$Q$71,'📋 Movimentações'!$E$15:$E$514,"Saída",'📋 Movimentações'!$D$15:$D$514,"Saúde") -> 0 | F22: =E22-D22 -> 0 | G22: =IF(E22=0,"—",IF(ABS(E22-D22)<=D22*0.1,"✅ OK","⚠️ Atenção")) -> — | H22: =IFERROR(E22/D22,0) -> 0
B23: Seguro do Carro | D23: ='🏠 Gastos Fixos'!C13 -> 16000 | E23: =SUMIFS('📋 Movimentações'!$F$15:$F$514,'📋 Movimentações'!$B$15:$B$514,">="&'📊 Dashboard'!$P$71,'📋 Movimentações'!$B$15:$B$514,"<="&'📊 Dashboard'!$Q$71,'📋 Movimentações'!$E$15:$E$514,"Saída",'📋 Movimentações'!$D$15:$D$514,"Seguro do Carro") -> 0 | F23: =E23-D23 -> -16000 | G23: =IF(E23=0,"—",IF(ABS(E23-D23)<=D23*0.1,"✅ OK","⚠️ Atenção")) -> — | H23: =IFERROR(E23/D23,0) -> 0
B24: Netflix / Disney+ | D24: ='🏠 Gastos Fixos'!C14 -> 1000 | E24: =SUMIFS('📋 Movimentações'!$F$15:$F$514,'📋 Movimentações'!$B$15:$B$514,">="&'📊 Dashboard'!$P$71,'📋 Movimentações'!$B$15:$B$514,"<="&'📊 Dashboard'!$Q$71,'📋 Movimentações'!$E$15:$E$514,"Saída",'📋 Movimentações'!$D$15:$D$514,"Assinatura") -> 0 | F24: =E24-D24 -> -1000 | G24: =IF(E24=0,"—",IF(ABS(E24-D24)<=D24*0.1,"✅ OK","⚠️ Atenção")) -> — | H24: =IFERROR(E24/D24,0) -> 0
B25: Spotify | D25: ='🏠 Gastos Fixos'!C15 -> 0 | E25: =SUMIFS('📋 Movimentações'!$F$15:$F$514,'📋 Movimentações'!$B$15:$B$514,">="&'📊 Dashboard'!$P$71,'📋 Movimentações'!$B$15:$B$514,"<="&'📊 Dashboard'!$Q$71,'📋 Movimentações'!$E$15:$E$514,"Saída",'📋 Movimentações'!$D$15:$D$514,"Assinatura") -> 0 | F25: =E25-D25 -> 0 | G25: =IF(E25=0,"—",IF(ABS(E25-D25)<=D25*0.1,"✅ OK","⚠️ Atenção")) -> — | H25: =IFERROR(E25/D25,0) -> 0
B26: Escola / Creche | D26: ='🏠 Gastos Fixos'!C16 -> 8000 | E26: =SUMIFS('📋 Movimentações'!$F$15:$F$514,'📋 Movimentações'!$B$15:$B$514,">="&'📊 Dashboard'!$P$71,'📋 Movimentações'!$B$15:$B$514,"<="&'📊 Dashboard'!$Q$71,'📋 Movimentações'!$E$15:$E$514,"Saída",'📋 Movimentações'!$D$15:$D$514,"Escola/Creche") -> 0 | F26: =E26-D26 -> -8000 | G26: =IF(E26=0,"—",IF(ABS(E26-D26)<=D26*0.1,"✅ OK","⚠️ Atenção")) -> — | H26: =IFERROR(E26/D26,0) -> 0
B27: Financiamento | D27: ='🏠 Gastos Fixos'!C17 -> 43160 | E27: =SUMIFS('📋 Movimentações'!$F$15:$F$514,'📋 Movimentações'!$B$15:$B$514,">="&'📊 Dashboard'!$P$71,'📋 Movimentações'!$B$15:$B$514,"<="&'📊 Dashboard'!$Q$71,'📋 Movimentações'!$E$15:$E$514,"Saída",'📋 Movimentações'!$D$15:$D$514,"Outros") -> 0 | F27: =E27-D27 -> -43160 | G27: =IF(E27=0,"—",IF(ABS(E27-D27)<=D27*0.1,"✅ OK","⚠️ Atenção")) -> — | H27: =IFERROR(E27/D27,0) -> 0
B28: Outros fixos | D28: ='🏠 Gastos Fixos'!C18 -> 7000 | E28: =SUMIFS('📋 Movimentações'!$F$15:$F$514,'📋 Movimentações'!$B$15:$B$514,">="&'📊 Dashboard'!$P$71,'📋 Movimentações'!$B$15:$B$514,"<="&'📊 Dashboard'!$Q$71,'📋 Movimentações'!$E$15:$E$514,"Saída",'📋 Movimentações'!$D$15:$D$514,"Outros") -> 0 | F28: =E28-D28 -> -7000 | G28: =IF(E28=0,"—",IF(ABS(E28-D28)<=D28*0.1,"✅ OK","⚠️ Atenção")) -> — | H28: =IFERROR(E28/D28,0) -> 0
B29: TOTAL FIXOS | D29: ='🏠 Gastos Fixos'!C23 -> 163053 | E29: =E15+E16+E17+E18+E19+E20+E21+E22+E23+E24+E25+E26+E27+E28 -> 68412 | F29: =E29-D29 -> -94641 | G29: =IF(E29>=D29,"✅ OK","⚠️ Atenção") -> ⚠️ Atenção | H29: =IFERROR(E29/D29,0) -> 0.4195691
B31: 🛒 GASTOS VARIÁVEIS (defina o limite abaixo — realizado vem automático)
B32: Mercado / Konbini | D32: ='🗂 Ichiran'!D57 -> 0 | E32: =SUMIFS('📋 Movimentações'!$F$15:$F$514,'📋 Movimentações'!$B$15:$B$514,">="&'📊 Dashboard'!$P$71,'📋 Movimentações'!$B$15:$B$514,"<="&'📊 Dashboard'!$Q$71,'📋 Movimentações'!$E$15:$E$514,"Saída",'📋 Movimentações'!$D$15:$D$514,"Mercado")+SUMIFS('📋 Movimentações'!$F$15:$F$514,'📋 Movimentações'!$B$15:$B$514,">="&'📊 Dashboard'!$P$71,'📋 Movimentações'!$B$15:$B$514,"<="&'📊 Dashboard'!$Q$71,'📋 Movimentações'!$E$15:$E$514,"Saída",'📋 Movimentações'!$D$15:$D$514,"Konbini") -> 0 | F32: =E32-D32 -> 0 | G32: =IF(E32=0,"—",IF(E32<=D32,"✅ OK","🔴 Limite!")) -> — | H32: =IFERROR(E32/D32,0) -> 0
B33: Transporte | D33: ='🗂 Ichiran'!D59 -> 0 | E33: =SUMIFS('📋 Movimentações'!$F$15:$F$514,'📋 Movimentações'!$B$15:$B$514,">="&'📊 Dashboard'!$P$71,'📋 Movimentações'!$B$15:$B$514,"<="&'📊 Dashboard'!$Q$71,'📋 Movimentações'!$E$15:$E$514,"Saída",'📋 Movimentações'!$D$15:$D$514,"Gasolina")+SUMIFS('📋 Movimentações'!$F$15:$F$514,'📋 Movimentações'!$B$15:$B$514,">="&'📊 Dashboard'!$P$71,'📋 Movimentações'!$B$15:$B$514,"<="&'📊 Dashboard'!$Q$71,'📋 Movimentações'!$E$15:$E$514,"Saída",'📋 Movimentações'!$D$15:$D$514,"Pedágio")+SUMIFS('📋 Movimentações'!$F$15:$F$514,'📋 Movimentações'!$B$15:$B$514,">="&'📊 Dashboard'!$P$71,'📋 Movimentações'!$B$15:$B$514,"<="&'📊 Dashboard'!$Q$71,'📋 Movimentações'!$E$15:$E$514,"Saída",'📋 Movimentações'!$D$15:$D$514,"Estacionamento") -> 0 | F33: =E33-D33 -> 0 | G33: =IF(E33=0,"—",IF(E33<=D33,"✅ OK","🔴 Limite!")) -> — | H33: =IFERROR(E33/D33,0) -> 0
B34: Restaurantes | D34: ='🗂 Ichiran'!D61 -> 0 | E34: =SUMIFS('📋 Movimentações'!$F$15:$F$514,'📋 Movimentações'!$B$15:$B$514,">="&'📊 Dashboard'!$P$71,'📋 Movimentações'!$B$15:$B$514,"<="&'📊 Dashboard'!$Q$71,'📋 Movimentações'!$E$15:$E$514,"Saída",'📋 Movimentações'!$D$15:$D$514,"Restaurantes") -> 0 | F34: =E34-D34 -> 0 | G34: =IF(E34=0,"—",IF(E34<=D34,"✅ OK","🔴 Limite!")) -> — | H34: =IFERROR(E34/D34,0) -> 0
B35: Lazer | D35: ='🗂 Ichiran'!D63 -> 0 | E35: =SUMIFS('📋 Movimentações'!$F$15:$F$514,'📋 Movimentações'!$B$15:$B$514,">="&'📊 Dashboard'!$P$71,'📋 Movimentações'!$B$15:$B$514,"<="&'📊 Dashboard'!$Q$71,'📋 Movimentações'!$E$15:$E$514,"Saída",'📋 Movimentações'!$D$15:$D$514,"Lazer") -> 0 | F35: =E35-D35 -> 0 | G35: =IF(E35=0,"—",IF(E35<=D35,"✅ OK","🔴 Limite!")) -> — | H35: =IFERROR(E35/D35,0) -> 0
B36: Saúde / Remédios | D36: ='🗂 Ichiran'!D65 -> 0 | E36: =SUMIFS('📋 Movimentações'!$F$15:$F$514,'📋 Movimentações'!$B$15:$B$514,">="&'📊 Dashboard'!$P$71,'📋 Movimentações'!$B$15:$B$514,"<="&'📊 Dashboard'!$Q$71,'📋 Movimentações'!$E$15:$E$514,"Saída",'📋 Movimentações'!$D$15:$D$514,"Saúde")+SUMIFS('📋 Movimentações'!$F$15:$F$514,'📋 Movimentações'!$B$15:$B$514,">="&'📊 Dashboard'!$P$71,'📋 Movimentações'!$B$15:$B$514,"<="&'📊 Dashboard'!$Q$71,'📋 Movimentações'!$E$15:$E$514,"Saída",'📋 Movimentações'!$D$15:$D$514,"Remédios") -> 0 | F36: =E36-D36 -> 0 | G36: =IF(E36=0,"—",IF(E36<=D36,"✅ OK","🔴 Limite!")) -> — | H36: =IFERROR(E36/D36,0) -> 0
B37: Compras / Roupas | D37: ='🗂 Ichiran'!D67 -> 0 | E37: =SUMIFS('📋 Movimentações'!$F$15:$F$514,'📋 Movimentações'!$B$15:$B$514,">="&'📊 Dashboard'!$P$71,'📋 Movimentações'!$B$15:$B$514,"<="&'📊 Dashboard'!$Q$71,'📋 Movimentações'!$E$15:$E$514,"Saída",'📋 Movimentações'!$D$15:$D$514,"Compras")+SUMIFS('📋 Movimentações'!$F$15:$F$514,'📋 Movimentações'!$B$15:$B$514,">="&'📊 Dashboard'!$P$71,'📋 Movimentações'!$B$15:$B$514,"<="&'📊 Dashboard'!$Q$71,'📋 Movimentações'!$E$15:$E$514,"Saída",'📋 Movimentações'!$D$15:$D$514,"Roupas") -> 0 | F37: =E37-D37 -> 0 | G37: =IF(E37=0,"—",IF(E37<=D37,"✅ OK","🔴 Limite!")) -> — | H37: =IFERROR(E37/D37,0) -> 0
B38: Remessa Brasil | D38: ='🗂 Ichiran'!D69 -> 0 | E38: =SUMIFS('📋 Movimentações'!$F$15:$F$514,'📋 Movimentações'!$B$15:$B$514,">="&'📊 Dashboard'!$P$71,'📋 Movimentações'!$B$15:$B$514,"<="&'📊 Dashboard'!$Q$71,'📋 Movimentações'!$E$15:$E$514,"Saída",'📋 Movimentações'!$D$15:$D$514,"Remessa Brasil") -> 0 | F38: =E38-D38 -> 0 | G38: =IF(E38=0,"—",IF(E38<=D38,"✅ OK","🔴 Limite!")) -> — | H38: =IFERROR(E38/D38,0) -> 0
B39: Igreja / Oferta | D39: ='🗂 Ichiran'!D71 -> 0 | E39: =SUMIFS('📋 Movimentações'!$F$15:$F$514,'📋 Movimentações'!$B$15:$B$514,">="&'📊 Dashboard'!$P$71,'📋 Movimentações'!$B$15:$B$514,"<="&'📊 Dashboard'!$Q$71,'📋 Movimentações'!$E$15:$E$514,"Saída",'📋 Movimentações'!$D$15:$D$514,"Igreja/Oferta") -> 0 | F39: =E39-D39 -> 0 | G39: =IF(E39=0,"—",IF(E39<=D39,"✅ OK","🔴 Limite!")) -> — | H39: =IFERROR(E39/D39,0) -> 0
B40: Emergência | D40: ='🗂 Ichiran'!D73 -> 0 | E40: =SUMIFS('📋 Movimentações'!$F$15:$F$514,'📋 Movimentações'!$B$15:$B$514,">="&'📊 Dashboard'!$P$71,'📋 Movimentações'!$B$15:$B$514,"<="&'📊 Dashboard'!$Q$71,'📋 Movimentações'!$E$15:$E$514,"Saída",'📋 Movimentações'!$D$15:$D$514,"Emergência") -> 0 | F40: =E40-D40 -> 0 | G40: =IF(E40=0,"—",IF(E40<=D40,"✅ OK","🔴 Limite!")) -> — | H40: =IFERROR(E40/D40,0) -> 0
B41: Outros variáveis | D41: ='🗂 Ichiran'!D75 -> 10000 | E41: =SUMIFS('📋 Movimentações'!$F$15:$F$514,'📋 Movimentações'!$B$15:$B$514,">="&'📊 Dashboard'!$P$71,'📋 Movimentações'!$B$15:$B$514,"<="&'📊 Dashboard'!$Q$71,'📋 Movimentações'!$E$15:$E$514,"Saída",'📋 Movimentações'!$D$15:$D$514,"Outros") -> 0 | F41: =E41-D41 -> -10000 | G41: =IF(E41=0,"—",IF(E41<=D41,"✅ OK","🔴 Limite!")) -> — | H41: =IFERROR(E41/D41,0) -> 0
B42: TOTAL VARIÁVEIS | D42: =D32+D33+D34+D35+D36+D37+D38+D39+D40+D41 -> 10000 | E42: =SUMIFS('📋 Movimentações'!$F$15:$F$514,'📋 Movimentações'!$B$15:$B$514,">="&'📊 Dashboard'!$P$71,'📋 Movimentações'!$B$15:$B$514,"<="&'📊 Dashboard'!$Q$71,'📋 Movimentações'!$E$15:$E$514,"Saída")-E29 -> 43160 | F42: =E42-D42 -> 33160 | G42: =IF(E42<=D42,"✅ OK","🔴 Limite!") -> 🔴 Limite! | H42: =IFERROR(E42/D42,0) -> 4.316
B44: 💰 RESULTADO DO MÊS
B45: Total Entradas | D45: =D11 -> 305000 | E45: =E11 -> 429000 | F45: =E45-D45 -> 124000 | G45: =IF(E45>=D45,"✅ OK","⚠️ Atenção") -> ✅ OK | H45: =IFERROR(E45/D45,0) -> 1.4065574
B46: Total Saídas | D46: =D29+D42 -> 173053 | E46: =E29+E42 -> 111572 | F46: =E46-D46 -> -61481 | G46: =IF(E46>=D46,"✅ OK","⚠️ Atenção") -> ⚠️ Atenção | H46: =IFERROR(E46/D46,0) -> 0.64472734
B47: Saldo do Mês | D47: =D45-D46 -> 131947 | E47: =E45-E46 -> 317428 | F47: =E47-D47 -> 185481 | G47: =IF(E47>=D47,"✅ OK","⚠️ Atenção") -> ✅ OK | H47: =IFERROR(E47/D47,0) -> 2.4057235
B49: 🎯 POUPAR P/ METAS (calculado automaticamente da aba Metas)
B50: 🆘 Reserva de Emergência | D50: =IFERROR(IF('🎯 Metas'!I5="—",0,'🎯 Metas'!I5),0) -> 500000 | E50: 0 | F50: =E50-D50 -> -500000 | G50: =IF(D50=0,"—",IF(E50>=D50,"✅ OK","⚠️ Atenção")) -> ⚠️ Atenção | H50: =IFERROR(E50/D50,0) -> 0
B51: ✈️ Viagem ao Brasil | D51: =IFERROR(IF('🎯 Metas'!I6="—",0,'🎯 Metas'!I6),0) -> 0 | E51: 0 | F51: =E51-D51 -> 0 | G51: =IF(D51=0,"—",IF(E51>=D51,"✅ OK","⚠️ Atenção")) -> — | H51: =IFERROR(E51/D51,0) -> 0
B52: 🚗 Carro Novo | D52: =IFERROR(IF('🎯 Metas'!I7="—",0,'🎯 Metas'!I7),0) -> 0 | E52: 0 | F52: =E52-D52 -> 0 | G52: =IF(D52=0,"—",IF(E52>=D52,"✅ OK","⚠️ Atenção")) -> — | H52: =IFERROR(E52/D52,0) -> 0
B53: 📦 Mudança / Novo Apto | D53: =IFERROR(IF('🎯 Metas'!I8="—",0,'🎯 Metas'!I8),0) -> 0 | E53: 0 | F53: =E53-D53 -> 0 | G53: =IF(D53=0,"—",IF(E53>=D53,"✅ OK","⚠️ Atenção")) -> — | H53: =IFERROR(E53/D53,0) -> 0
B54: 📈 Investimento | D54: =IFERROR(IF('🎯 Metas'!I9="—",0,'🎯 Metas'!I9),0) -> 0 | E54: 0 | F54: =E54-D54 -> 0 | G54: =IF(D54=0,"—",IF(E54>=D54,"✅ OK","⚠️ Atenção")) -> — | H54: =IFERROR(E54/D54,0) -> 0
B55: 💳 Quitar Dívida | D55: =IFERROR(IF('🎯 Metas'!I10="—",0,'🎯 Metas'!I10),0) -> 0 | E55: 0 | F55: =E55-D55 -> 0 | G55: =IF(D55=0,"—",IF(E55>=D55,"✅ OK","⚠️ Atenção")) -> — | H55: =IFERROR(E55/D55,0) -> 0
B56: 🛒 Compra Importante | D56: =IFERROR(IF('🎯 Metas'!I11="—",0,'🎯 Metas'!I11),0) -> 0 | E56: 0 | F56: =E56-D56 -> 0 | G56: =IF(D56=0,"—",IF(E56>=D56,"✅ OK","⚠️ Atenção")) -> — | H56: =IFERROR(E56/D56,0) -> 0
B57: ⭐ Outros | D57: =IFERROR(IF('🎯 Metas'!I12="—",0,'🎯 Metas'!I12),0) -> 0 | E57: 0 | F57: =E57-D57 -> 0 | G57: =IF(D57=0,"—",IF(E57>=D57,"✅ OK","⚠️ Atenção")) -> — | H57: =IFERROR(E57/D57,0) -> 0
B58: TOTAL P/ METAS | D58: =D50+D51+D52+D53+D54+D55+D56+D57 -> 500000 | E58: =E50+E51+E52+E53+E54+E55+E56+E57 -> 0 | F58: =E58-D58 -> -500000 | G58: =IF(E58>=D58,"✅ OK","⚠️ Atenção") -> ⚠️ Atenção | H58: =IFERROR(E58/D58,0) -> 0
B60: =IF('📊 Dashboard'!F71>=0,"✅ MÊS POSITIVO — Saldo de ¥"&TEXT('📊 Dashboard'!F71,"#,##0")&". Parabéns!","🔴 MÊS NEGATIVO — Gastos superaram a renda em ¥"&TEXT(ABS('📊 Dashboard'!F71),"#,##0")&". Revise seus gastos.") -> ✅ MÊS POSITIVO — Saldo de ¥317,428. Parabéns!

Sheet 🎯 Metas
B2: 🎯 METAS FINANCEIRAS
B4: META | C4: VALOR ALVO (¥) | D4: ATUAL (¥) | E4: FALTA (¥) | F4: PRAZO | G4: PROGRESSO | H4: PRIORIDADE | I4: ¥/MÊS NECESSÁRIO
B5: 🆘 Reserva de Emergência | C5: 500000 | D5: 0 | E5: =MAX(C5-D5,0) -> 500000 | F5: 2025-12 | G5: =IFERROR(D5/C5,0) -> 0 | H5: 🔴 Alta | I5: =IFERROR(IF(OR(F5="-",F5=""),"—",CEILING(MAX(E5,0)/MAX((VALUE(LEFT(F5,4))-YEAR(TODAY()))*12+VALUE(MID(F5,6,2))-MONTH(TODAY()),1),1)),"-") -> 500000
B6: ✈️ Viagem | C6: 0 | D6: 0 | E6: =MAX(C6-D6,0) -> 0 | F6: 2026-03 | G6: =IFERROR(D6/C6,0) -> 0 | H6: 🟡 Média | I6: =IFERROR(IF(OR(F6="-",F6=""),"—",CEILING(MAX(E6,0)/MAX((VALUE(LEFT(F6,4))-YEAR(TODAY()))*12+VALUE(MID(F6,6,2))-MONTH(TODAY()),1),1)),"-") -> 0
B7: 🚗 Carro Novo | C7: 0 | D7: 0 | E7: =MAX(C7-D7,0) -> 0 | F7: 2027-01 | G7: =IFERROR(D7/C7,0) -> 0 | H7: 🟢 Baixa | I7: =IFERROR(IF(OR(F7="-",F7=""),"—",CEILING(MAX(E7,0)/MAX((VALUE(LEFT(F7,4))-YEAR(TODAY()))*12+VALUE(MID(F7,6,2))-MONTH(TODAY()),1),1)),"-") -> 0
B8: 📦 Mudança / Novo Apto | C8: 0 | D8: 0 | E8: =MAX(C8-D8,0) -> 0 | F8: 2025-06 | G8: =IFERROR(D8/C8,0) -> 0 | H8: 🟡 Média | I8: =IFERROR(IF(OR(F8="-",F8=""),"—",CEILING(MAX(E8,0)/MAX((VALUE(LEFT(F8,4))-YEAR(TODAY()))*12+VALUE(MID(F8,6,2))-MONTH(TODAY()),1),1)),"-") -> 0
B9: 📈 Investimento | C9: 0 | D9: 0 | E9: =MAX(C9-D9,0) -> 0 | F9: 2028-12 | G9: =IFERROR(D9/C9,0) -> 0 | H9: 🟡 Média | I9: =IFERROR(IF(OR(F9="-",F9=""),"—",CEILING(MAX(E9,0)/MAX((VALUE(LEFT(F9,4))-YEAR(TODAY()))*12+VALUE(MID(F9,6,2))-MONTH(TODAY()),1),1)),"-") -> 0
B10: 💳 Quitar Dívida | C10: 0 | D10: 0 | E10: =MAX(C10-D10,0) -> 0 | F10: - | G10: =IFERROR(D10/C10,0) -> 0 | H10: 🔴 Alta | I10: =IFERROR(IF(OR(F10="-",F10=""),"—",CEILING(MAX(E10,0)/MAX((VALUE(LEFT(F10,4))-YEAR(TODAY()))*12+VALUE(MID(F10,6,2))-MONTH(TODAY()),1),1)),"-") -> —
B11: 🛒 Compra Importante | C11: 0 | D11: 0 | E11: =MAX(C11-D11,0) -> 0 | F11: - | G11: =IFERROR(D11/C11,0) -> 0 | H11: 🟢 Baixa | I11: =IFERROR(IF(OR(F11="-",F11=""),"—",CEILING(MAX(E11,0)/MAX((VALUE(LEFT(F11,4))-YEAR(TODAY()))*12+VALUE(MID(F11,6,2))-MONTH(TODAY()),1),1)),"-") -> —
B12: ⭐ Outros | C12: 0 | D12: 0 | E12: =MAX(C12-D12,0) -> 0 | F12: - | G12: =IFERROR(D12/C12,0) -> 0 | H12: 🟢 Baixa | I12: =IFERROR(IF(OR(F12="-",F12=""),"—",CEILING(MAX(E12,0)/MAX((VALUE(LEFT(F12,4))-YEAR(TODAY()))*12+VALUE(MID(F12,6,2))-MONTH(TODAY()),1),1)),"-") -> —
B15: Total a acumular: | C15: =SUM(C5:C12) -> 500000 | D15: =SUM(D5:D12) -> 0 | E15: =C15-D15 -> 500000

Sheet 📆 Resumo Anual
B2: 📆 RESUMO ANUAL — EVOLUÇÃO DOS 12 MESES
N3: 2025
B5: CATEGORIA | C5: Jan | D5: Fev | E5: Mar | F5: Abr | G5: Mai | H5: Jun | I5: Jul | J5: Ago | K5: Set | L5: Out | M5: Nov | N5: Dez | O5: TOTAL
B6: ── ENTRADAS ──
B7: Salário | C7: =SUMIFS('📋 Movimentações'!$F$15:$F$514,'📋 Movimentações'!$B$15:$B$514,">="&DATE($N$3,1,1),'📋 Movimentações'!$B$15:$B$514,"<="&EOMONTH(DATE($N$3,1,1),0),'📋 Movimentações'!$E$15:$E$514,"Entrada",'📋 Movimentações'!$D$15:$D$514,"Salário") -> 0 | D7: =SUMIFS('📋 Movimentações'!$F$15:$F$514,'📋 Movimentações'!$B$15:$B$514,">="&DATE($N$3,2,1),'📋 Movimentações'!$B$15:$B$514,"<="&EOMONTH(DATE($N$3,2,1),0),'📋 Movimentações'!$E$15:$E$514,"Entrada",'📋 Movimentações'!$D$15:$D$514,"Salário") -> 0 | E7: =SUMIFS('📋 Movimentações'!$F$15:$F$514,'📋 Movimentações'!$B$15:$B$514,">="&DATE($N$3,3,1),'📋 Movimentações'!$B$15:$B$514,"<="&EOMONTH(DATE($N$3,3,1),0),'📋 Movimentações'!$E$15:$E$514,"Entrada",'📋 Movimentações'!$D$15:$D$514,"Salário") -> 0 | F7: =SUMIFS('📋 Movimentações'!$F$15:$F$514,'📋 Movimentações'!$B$15:$B$514,">="&DATE($N$3,4,1),'📋 Movimentações'!$B$15:$B$514,"<="&EOMONTH(DATE($N$3,4,1),0),'📋 Movimentações'!$E$15:$E$514,"Entrada",'📋 Movimentações'!$D$15:$D$514,"Salário") -> 0 | G7: =SUMIFS('📋 Movimentações'!$F$15:$F$514,'📋 Movimentações'!$B$15:$B$514,">="&DATE($N$3,5,1),'📋 Movimentações'!$B$15:$B$514,"<="&EOMONTH(DATE($N$3,5,1),0),'📋 Movimentações'!$E$15:$E$514,"Entrada",'📋 Movimentações'!$D$15:$D$514,"Salário") -> 374000 | H7: =SUMIFS('📋 Movimentações'!$F$15:$F$514,'📋 Movimentações'!$B$15:$B$514,">="&DATE($N$3,6,1),'📋 Movimentações'!$B$15:$B$514,"<="&EOMONTH(DATE($N$3,6,1),0),'📋 Movimentações'!$E$15:$E$514,"Entrada",'📋 Movimentações'!$D$15:$D$514,"Salário") -> 0 | I7: =SUMIFS('📋 Movimentações'!$F$15:$F$514,'📋 Movimentações'!$B$15:$B$514,">="&DATE($N$3,7,1),'📋 Movimentações'!$B$15:$B$514,"<="&EOMONTH(DATE($N$3,7,1),0),'📋 Movimentações'!$E$15:$E$514,"Entrada",'📋 Movimentações'!$D$15:$D$514,"Salário") -> 0 | J7: =SUMIFS('📋 Movimentações'!$F$15:$F$514,'📋 Movimentações'!$B$15:$B$514,">="&DATE($N$3,8,1),'📋 Movimentações'!$B$15:$B$514,"<="&EOMONTH(DATE($N$3,8,1),0),'📋 Movimentações'!$E$15:$E$514,"Entrada",'📋 Movimentações'!$D$15:$D$514,"Salário") -> 0 | K7: =SUMIFS('📋 Movimentações'!$F$15:$F$514,'📋 Movimentações'!$B$15:$B$514,">="&DATE($N$3,9,1),'📋 Movimentações'!$B$15:$B$514,"<="&EOMONTH(DATE($N$3,9,1),0),'📋 Movimentações'!$E$15:$E$514,"Entrada",'📋 Movimentações'!$D$15:$D$514,"Salário") -> 0 | L7: =SUMIFS('📋 Movimentações'!$F$15:$F$514,'📋 Movimentações'!$B$15:$B$514,">="&DATE($N$3,10,1),'📋 Movimentações'!$B$15:$B$514,"<="&EOMONTH(DATE($N$3,10,1),0),'📋 Movimentações'!$E$15:$E$514,"Entrada",'📋 Movimentações'!$D$15:$D$514,"Salário") -> 0 | M7: =SUMIFS('📋 Movimentações'!$F$15:$F$514,'📋 Movimentações'!$B$15:$B$514,">="&DATE($N$3,11,1),'📋 Movimentações'!$B$15:$B$514,"<="&EOMONTH(DATE($N$3,11,1),0),'📋 Movimentações'!$E$15:$E$514,"Entrada",'📋 Movimentações'!$D$15:$D$514,"Salário") -> 0 | N7: =SUMIFS('📋 Movimentações'!$F$15:$F$514,'📋 Movimentações'!$B$15:$B$514,">="&DATE($N$3,12,1),'📋 Movimentações'!$B$15:$B$514,"<="&EOMONTH(DATE($N$3,12,1),0),'📋 Movimentações'!$E$15:$E$514,"Entrada",'📋 Movimentações'!$D$15:$D$514,"Salário") -> 0 | O7: =SUM(C7,D7,E7,F7,G7,H7,I7,J7,K7,L7,M7,N7) -> 374000
B8: Hora Extra | C8: =SUMIFS('📋 Movimentações'!$F$15:$F$514,'📋 Movimentações'!$B$15:$B$514,">="&DATE($N$3,1,1),'📋 Movimentações'!$B$15:$B$514,"<="&EOMONTH(DATE($N$3,1,1),0),'📋 Movimentações'!$E$15:$E$514,"Entrada",'📋 Movimentações'!$D$15:$D$514,"Hora Extra") -> 0 | D8: =SUMIFS('📋 Movimentações'!$F$15:$F$514,'📋 Movimentações'!$B$15:$B$514,">="&DATE($N$3,2,1),'📋 Movimentações'!$B$15:$B$514,"<="&EOMONTH(DATE($N$3,2,1),0),'📋 Movimentações'!$E$15:$E$514,"Entrada",'📋 Movimentações'!$D$15:$D$514,"Hora Extra") -> 0 | E8: =SUMIFS('📋 Movimentações'!$F$15:$F$514,'📋 Movimentações'!$B$15:$B$514,">="&DATE($N$3,3,1),'📋 Movimentações'!$B$15:$B$514,"<="&EOMONTH(DATE($N$3,3,1),0),'📋 Movimentações'!$E$15:$E$514,"Entrada",'📋 Movimentações'!$D$15:$D$514,"Hora Extra") -> 0 | F8: =SUMIFS('📋 Movimentações'!$F$15:$F$514,'📋 Movimentações'!$B$15:$B$514,">="&DATE($N$3,4,1),'📋 Movimentações'!$B$15:$B$514,"<="&EOMONTH(DATE($N$3,4,1),0),'📋 Movimentações'!$E$15:$E$514,"Entrada",'📋 Movimentações'!$D$15:$D$514,"Hora Extra") -> 0 | G8: =SUMIFS('📋 Movimentações'!$F$15:$F$514,'📋 Movimentações'!$B$15:$B$514,">="&DATE($N$3,5,1),'📋 Movimentações'!$B$15:$B$514,"<="&EOMONTH(DATE($N$3,5,1),0),'📋 Movimentações'!$E$15:$E$514,"Entrada",'📋 Movimentações'!$D$15:$D$514,"Hora Extra") -> 0 | H8: =SUMIFS('📋 Movimentações'!$F$15:$F$514,'📋 Movimentações'!$B$15:$B$514,">="&DATE($N$3,6,1),'📋 Movimentações'!$B$15:$B$514,"<="&EOMONTH(DATE($N$3,6,1),0),'📋 Movimentações'!$E$15:$E$514,"Entrada",'📋 Movimentações'!$D$15:$D$514,"Hora Extra") -> 0 | I8: =SUMIFS('📋 Movimentações'!$F$15:$F$514,'📋 Movimentações'!$B$15:$B$514,">="&DATE($N$3,7,1),'📋 Movimentações'!$B$15:$B$514,"<="&EOMONTH(DATE($N$3,7,1),0),'📋 Movimentações'!$E$15:$E$514,"Entrada",'📋 Movimentações'!$D$15:$D$514,"Hora Extra") -> 0 | J8: =SUMIFS('📋 Movimentações'!$F$15:$F$514,'📋 Movimentações'!$B$15:$B$514,">="&DATE($N$3,8,1),'📋 Movimentações'!$B$15:$B$514,"<="&EOMONTH(DATE($N$3,8,1),0),'📋 Movimentações'!$E$15:$E$514,"Entrada",'📋 Movimentações'!$D$15:$D$514,"Hora Extra") -> 0 | K8: =SUMIFS('📋 Movimentações'!$F$15:$F$514,'📋 Movimentações'!$B$15:$B$514,">="&DATE($N$3,9,1),'📋 Movimentações'!$B$15:$B$514,"<="&EOMONTH(DATE($N$3,9,1),0),'📋 Movimentações'!$E$15:$E$514,"Entrada",'📋 Movimentações'!$D$15:$D$514,"Hora Extra") -> 0 | L8: =SUMIFS('📋 Movimentações'!$F$15:$F$514,'📋 Movimentações'!$B$15:$B$514,">="&DATE($N$3,10,1),'📋 Movimentações'!$B$15:$B$514,"<="&EOMONTH(DATE($N$3,10,1),0),'📋 Movimentações'!$E$15:$E$514,"Entrada",'📋 Movimentações'!$D$15:$D$514,"Hora Extra") -> 0 | M8: =SUMIFS('📋 Movimentações'!$F$15:$F$514,'📋 Movimentações'!$B$15:$B$514,">="&DATE($N$3,11,1),'📋 Movimentações'!$B$15:$B$514,"<="&EOMONTH(DATE($N$3,11,1),0),'📋 Movimentações'!$E$15:$E$514,"Entrada",'📋 Movimentações'!$D$15:$D$514,"Hora Extra") -> 0 | N8: =SUMIFS('📋 Movimentações'!$F$15:$F$514,'📋 Movimentações'!$B$15:$B$514,">="&DATE($N$3,12,1),'📋 Movimentações'!$B$15:$B$514,"<="&EOMONTH(DATE($N$3,12,1),0),'📋 Movimentações'!$E$15:$E$514,"Entrada",'📋 Movimentações'!$D$15:$D$514,"Hora Extra") -> 0 | O8: =SUM(C8,D8,E8,F8,G8,H8,I8,J8,K8,L8,M8,N8) -> 0
B9: Bônus | C9: =SUMIFS('📋 Movimentações'!$F$15:$F$514,'📋 Movimentações'!$B$15:$B$514,">="&DATE($N$3,1,1),'📋 Movimentações'!$B$15:$B$514,"<="&EOMONTH(DATE($N$3,1,1),0),'📋 Movimentações'!$E$15:$E$514,"Entrada",'📋 Movimentações'!$D$15:$D$514,"Bônus") -> 0 | D9: =SUMIFS('📋 Movimentações'!$F$15:$F$514,'📋 Movimentações'!$B$15:$B$514,">="&DATE($N$3,2,1),'📋 Movimentações'!$B$15:$B$514,"<="&EOMONTH(DATE($N$3,2,1),0),'📋 Movimentações'!$E$15:$E$514,"Entrada",'📋 Movimentações'!$D$15:$D$514,"Bônus") -> 0 | E9: =SUMIFS('📋 Movimentações'!$F$15:$F$514,'📋 Movimentações'!$B$15:$B$514,">="&DATE($N$3,3,1),'📋 Movimentações'!$B$15:$B$514,"<="&EOMONTH(DATE($N$3,3,1),0),'📋 Movimentações'!$E$15:$E$514,"Entrada",'📋 Movimentações'!$D$15:$D$514,"Bônus") -> 0 | F9: =SUMIFS('📋 Movimentações'!$F$15:$F$514,'📋 Movimentações'!$B$15:$B$514,">="&DATE($N$3,4,1),'📋 Movimentações'!$B$15:$B$514,"<="&EOMONTH(DATE($N$3,4,1),0),'📋 Movimentações'!$E$15:$E$514,"Entrada",'📋 Movimentações'!$D$15:$D$514,"Bônus") -> 0 | G9: =SUMIFS('📋 Movimentações'!$F$15:$F$514,'📋 Movimentações'!$B$15:$B$514,">="&DATE($N$3,5,1),'📋 Movimentações'!$B$15:$B$514,"<="&EOMONTH(DATE($N$3,5,1),0),'📋 Movimentações'!$E$15:$E$514,"Entrada",'📋 Movimentações'!$D$15:$D$514,"Bônus") -> 55000 | H9: =SUMIFS('📋 Movimentações'!$F$15:$F$514,'📋 Movimentações'!$B$15:$B$514,">="&DATE($N$3,6,1),'📋 Movimentações'!$B$15:$B$514,"<="&EOMONTH(DATE($N$3,6,1),0),'📋 Movimentações'!$E$15:$E$514,"Entrada",'📋 Movimentações'!$D$15:$D$514,"Bônus") -> 0 | I9: =SUMIFS('📋 Movimentações'!$F$15:$F$514,'📋 Movimentações'!$B$15:$B$514,">="&DATE($N$3,7,1),'📋 Movimentações'!$B$15:$B$514,"<="&EOMONTH(DATE($N$3,7,1),0),'📋 Movimentações'!$E$15:$E$514,"Entrada",'📋 Movimentações'!$D$15:$D$514,"Bônus") -> 0 | J9: =SUMIFS('📋 Movimentações'!$F$15:$F$514,'📋 Movimentações'!$B$15:$B$514,">="&DATE($N$3,8,1),'📋 Movimentações'!$B$15:$B$514,"<="&EOMONTH(DATE($N$3,8,1),0),'📋 Movimentações'!$E$15:$E$514,"Entrada",'📋 Movimentações'!$D$15:$D$514,"Bônus") -> 0 | K9: =SUMIFS('📋 Movimentações'!$F$15:$F$514,'📋 Movimentações'!$B$15:$B$514,">="&DATE($N$3,9,1),'📋 Movimentações'!$B$15:$B$514,"<="&EOMONTH(DATE($N$3,9,1),0),'📋 Movimentações'!$E$15:$E$514,"Entrada",'📋 Movimentações'!$D$15:$D$514,"Bônus") -> 0 | L9: =SUMIFS('📋 Movimentações'!$F$15:$F$514,'📋 Movimentações'!$B$15:$B$514,">="&DATE($N$3,10,1),'📋 Movimentações'!$B$15:$B$514,"<="&EOMONTH(DATE($N$3,10,1),0),'📋 Movimentações'!$E$15:$E$514,"Entrada",'📋 Movimentações'!$D$15:$D$514,"Bônus") -> 0 | M9: =SUMIFS('📋 Movimentações'!$F$15:$F$514,'📋 Movimentações'!$B$15:$B$514,">="&DATE($N$3,11,1),'📋 Movimentações'!$B$15:$B$514,"<="&EOMONTH(DATE($N$3,11,1),0),'📋 Movimentações'!$E$15:$E$514,"Entrada",'📋 Movimentações'!$D$15:$D$514,"Bônus") -> 0 | N9: =SUMIFS('📋 Movimentações'!$F$15:$F$514,'📋 Movimentações'!$B$15:$B$514,">="&DATE($N$3,12,1),'📋 Movimentações'!$B$15:$B$514,"<="&EOMONTH(DATE($N$3,12,1),0),'📋 Movimentações'!$E$15:$E$514,"Entrada",'📋 Movimentações'!$D$15:$D$514,"Bônus") -> 0 | O9: =SUM(C9,D9,E9,F9,G9,H9,I9,J9,K9,L9,M9,N9) -> 55000
B10: Total Entradas | C10: =SUMIFS('📋 Movimentações'!$F$15:$F$514,'📋 Movimentações'!$B$15:$B$514,">="&DATE($N$3,1,1),'📋 Movimentações'!$B$15:$B$514,"<="&EOMONTH(DATE($N$3,1,1),0),'📋 Movimentações'!$E$15:$E$514,"Entrada") -> 0 | D10: =SUMIFS('📋 Movimentações'!$F$15:$F$514,'📋 Movimentações'!$B$15:$B$514,">="&DATE($N$3,2,1),'📋 Movimentações'!$B$15:$B$514,"<="&EOMONTH(DATE($N$3,2,1),0),'📋 Movimentações'!$E$15:$E$514,"Entrada") -> 0 | E10: =SUMIFS('📋 Movimentações'!$F$15:$F$514,'📋 Movimentações'!$B$15:$B$514,">="&DATE($N$3,3,1),'📋 Movimentações'!$B$15:$B$514,"<="&EOMONTH(DATE($N$3,3,1),0),'📋 Movimentações'!$E$15:$E$514,"Entrada") -> 0 | F10: =SUMIFS('📋 Movimentações'!$F$15:$F$514,'📋 Movimentações'!$B$15:$B$514,">="&DATE($N$3,4,1),'📋 Movimentações'!$B$15:$B$514,"<="&EOMONTH(DATE($N$3,4,1),0),'📋 Movimentações'!$E$15:$E$514,"Entrada") -> 0 | G10: =SUMIFS('📋 Movimentações'!$F$15:$F$514,'📋 Movimentações'!$B$15:$B$514,">="&DATE($N$3,5,1),'📋 Movimentações'!$B$15:$B$514,"<="&EOMONTH(DATE($N$3,5,1),0),'📋 Movimentações'!$E$15:$E$514,"Entrada") -> 429000 | H10: =SUMIFS('📋 Movimentações'!$F$15:$F$514,'📋 Movimentações'!$B$15:$B$514,">="&DATE($N$3,6,1),'📋 Movimentações'!$B$15:$B$514,"<="&EOMONTH(DATE($N$3,6,1),0),'📋 Movimentações'!$E$15:$E$514,"Entrada") -> 0 | I10: =SUMIFS('📋 Movimentações'!$F$15:$F$514,'📋 Movimentações'!$B$15:$B$514,">="&DATE($N$3,7,1),'📋 Movimentações'!$B$15:$B$514,"<="&EOMONTH(DATE($N$3,7,1),0),'📋 Movimentações'!$E$15:$E$514,"Entrada") -> 0 | J10: =SUMIFS('📋 Movimentações'!$F$15:$F$514,'📋 Movimentações'!$B$15:$B$514,">="&DATE($N$3,8,1),'📋 Movimentações'!$B$15:$B$514,"<="&EOMONTH(DATE($N$3,8,1),0),'📋 Movimentações'!$E$15:$E$514,"Entrada") -> 0 | K10: =SUMIFS('📋 Movimentações'!$F$15:$F$514,'📋 Movimentações'!$B$15:$B$514,">="&DATE($N$3,9,1),'📋 Movimentações'!$B$15:$B$514,"<="&EOMONTH(DATE($N$3,9,1),0),'📋 Movimentações'!$E$15:$E$514,"Entrada") -> 0 | L10: =SUMIFS('📋 Movimentações'!$F$15:$F$514,'📋 Movimentações'!$B$15:$B$514,">="&DATE($N$3,10,1),'📋 Movimentações'!$B$15:$B$514,"<="&EOMONTH(DATE($N$3,10,1),0),'📋 Movimentações'!$E$15:$E$514,"Entrada") -> 0 | M10: =SUMIFS('📋 Movimentações'!$F$15:$F$514,'📋 Movimentações'!$B$15:$B$514,">="&DATE($N$3,11,1),'📋 Movimentações'!$B$15:$B$514,"<="&EOMONTH(DATE($N$3,11,1),0),'📋 Movimentações'!$E$15:$E$514,"Entrada") -> 0 | N10: =SUMIFS('📋 Movimentações'!$F$15:$F$514,'📋 Movimentações'!$B$15:$B$514,">="&DATE($N$3,12,1),'📋 Movimentações'!$B$15:$B$514,"<="&EOMONTH(DATE($N$3,12,1),0),'📋 Movimentações'!$E$15:$E$514,"Entrada") -> 0 | O10: =SUM(C10,D10,E10,F10,G10,H10,I10,J10,K10,L10,M10,N10) -> 429000
B11: ── SAÍDAS ──
B12: Aluguel | C12: =SUMIFS('📋 Movimentações'!$F$15:$F$514,'📋 Movimentações'!$B$15:$B$514,">="&DATE($N$3,1,1),'📋 Movimentações'!$B$15:$B$514,"<="&EOMONTH(DATE($N$3,1,1),0),'📋 Movimentações'!$E$15:$E$514,"Saída",'📋 Movimentações'!$D$15:$D$514,"Aluguel") -> 0 | D12: =SUMIFS('📋 Movimentações'!$F$15:$F$514,'📋 Movimentações'!$B$15:$B$514,">="&DATE($N$3,2,1),'📋 Movimentações'!$B$15:$B$514,"<="&EOMONTH(DATE($N$3,2,1),0),'📋 Movimentações'!$E$15:$E$514,"Saída",'📋 Movimentações'!$D$15:$D$514,"Aluguel") -> 0 | E12: =SUMIFS('📋 Movimentações'!$F$15:$F$514,'📋 Movimentações'!$B$15:$B$514,">="&DATE($N$3,3,1),'📋 Movimentações'!$B$15:$B$514,"<="&EOMONTH(DATE($N$3,3,1),0),'📋 Movimentações'!$E$15:$E$514,"Saída",'📋 Movimentações'!$D$15:$D$514,"Aluguel") -> 0 | F12: =SUMIFS('📋 Movimentações'!$F$15:$F$514,'📋 Movimentações'!$B$15:$B$514,">="&DATE($N$3,4,1),'📋 Movimentações'!$B$15:$B$514,"<="&EOMONTH(DATE($N$3,4,1),0),'📋 Movimentações'!$E$15:$E$514,"Saída",'📋 Movimentações'!$D$15:$D$514,"Aluguel") -> 0 | G12: =SUMIFS('📋 Movimentações'!$F$15:$F$514,'📋 Movimentações'!$B$15:$B$514,">="&DATE($N$3,5,1),'📋 Movimentações'!$B$15:$B$514,"<="&EOMONTH(DATE($N$3,5,1),0),'📋 Movimentações'!$E$15:$E$514,"Saída",'📋 Movimentações'!$D$15:$D$514,"Aluguel") -> 30000 | H12: =SUMIFS('📋 Movimentações'!$F$15:$F$514,'📋 Movimentações'!$B$15:$B$514,">="&DATE($N$3,6,1),'📋 Movimentações'!$B$15:$B$514,"<="&EOMONTH(DATE($N$3,6,1),0),'📋 Movimentações'!$E$15:$E$514,"Saída",'📋 Movimentações'!$D$15:$D$514,"Aluguel") -> 0 | I12: =SUMIFS('📋 Movimentações'!$F$15:$F$514,'📋 Movimentações'!$B$15:$B$514,">="&DATE($N$3,7,1),'📋 Movimentações'!$B$15:$B$514,"<="&EOMONTH(DATE($N$3,7,1),0),'📋 Movimentações'!$E$15:$E$514,"Saída",'📋 Movimentações'!$D$15:$D$514,"Aluguel") -> 0 | J12: =SUMIFS('📋 Movimentações'!$F$15:$F$514,'📋 Movimentações'!$B$15:$B$514,">="&DATE($N$3,8,1),'📋 Movimentações'!$B$15:$B$514,"<="&EOMONTH(DATE($N$3,8,1),0),'📋 Movimentações'!$E$15:$E$514,"Saída",'📋 Movimentações'!$D$15:$D$514,"Aluguel") -> 0 | K12: =SUMIFS('📋 Movimentações'!$F$15:$F$514,'📋 Movimentações'!$B$15:$B$514,">="&DATE($N$3,9,1),'📋 Movimentações'!$B$15:$B$514,"<="&EOMONTH(DATE($N$3,9,1),0),'📋 Movimentações'!$E$15:$E$514,"Saída",'📋 Movimentações'!$D$15:$D$514,"Aluguel") -> 0 | L12: =SUMIFS('📋 Movimentações'!$F$15:$F$514,'📋 Movimentações'!$B$15:$B$514,">="&DATE($N$3,10,1),'📋 Movimentações'!$B$15:$B$514,"<="&EOMONTH(DATE($N$3,10,1),0),'📋 Movimentações'!$E$15:$E$514,"Saída",'📋 Movimentações'!$D$15:$D$514,"Aluguel") -> 0 | M12: =SUMIFS('📋 Movimentações'!$F$15:$F$514,'📋 Movimentações'!$B$15:$B$514,">="&DATE($N$3,11,1),'📋 Movimentações'!$B$15:$B$514,"<="&EOMONTH(DATE($N$3,11,1),0),'📋 Movimentações'!$E$15:$E$514,"Saída",'📋 Movimentações'!$D$15:$D$514,"Aluguel") -> 0 | N12: =SUMIFS('📋 Movimentações'!$F$15:$F$514,'📋 Movimentações'!$B$15:$B$514,">="&DATE($N$3,12,1),'📋 Movimentações'!$B$15:$B$514,"<="&EOMONTH(DATE($N$3,12,1),0),'📋 Movimentações'!$E$15:$E$514,"Saída",'📋 Movimentações'!$D$15:$D$514,"Aluguel") -> 0 | O12: =SUM(C12,D12,E12,F12,G12,H12,I12,J12,K12,L12,M12,N12) -> 30000
B13: Mercado/Konbini | C13: =SUMIFS('📋 Movimentações'!$F$15:$F$514,'📋 Movimentações'!$B$15:$B$514,">="&DATE($N$3,1,1),'📋 Movimentações'!$B$15:$B$514,"<="&EOMONTH(DATE($N$3,1,1),0),'📋 Movimentações'!$E$15:$E$514,"Saída",'📋 Movimentações'!$D$15:$D$514,"Mercado") -> 0 | D13: =SUMIFS('📋 Movimentações'!$F$15:$F$514,'📋 Movimentações'!$B$15:$B$514,">="&DATE($N$3,2,1),'📋 Movimentações'!$B$15:$B$514,"<="&EOMONTH(DATE($N$3,2,1),0),'📋 Movimentações'!$E$15:$E$514,"Saída",'📋 Movimentações'!$D$15:$D$514,"Mercado") -> 0 | E13: =SUMIFS('📋 Movimentações'!$F$15:$F$514,'📋 Movimentações'!$B$15:$B$514,">="&DATE($N$3,3,1),'📋 Movimentações'!$B$15:$B$514,"<="&EOMONTH(DATE($N$3,3,1),0),'📋 Movimentações'!$E$15:$E$514,"Saída",'📋 Movimentações'!$D$15:$D$514,"Mercado") -> 0 | F13: =SUMIFS('📋 Movimentações'!$F$15:$F$514,'📋 Movimentações'!$B$15:$B$514,">="&DATE($N$3,4,1),'📋 Movimentações'!$B$15:$B$514,"<="&EOMONTH(DATE($N$3,4,1),0),'📋 Movimentações'!$E$15:$E$514,"Saída",'📋 Movimentações'!$D$15:$D$514,"Mercado") -> 0 | G13: =SUMIFS('📋 Movimentações'!$F$15:$F$514,'📋 Movimentações'!$B$15:$B$514,">="&DATE($N$3,5,1),'📋 Movimentações'!$B$15:$B$514,"<="&EOMONTH(DATE($N$3,5,1),0),'📋 Movimentações'!$E$15:$E$514,"Saída",'📋 Movimentações'!$D$15:$D$514,"Mercado") -> 0 | H13: =SUMIFS('📋 Movimentações'!$F$15:$F$514,'📋 Movimentações'!$B$15:$B$514,">="&DATE($N$3,6,1),'📋 Movimentações'!$B$15:$B$514,"<="&EOMONTH(DATE($N$3,6,1),0),'📋 Movimentações'!$E$15:$E$514,"Saída",'📋 Movimentações'!$D$15:$D$514,"Mercado") -> 0 | I13: =SUMIFS('📋 Movimentações'!$F$15:$F$514,'📋 Movimentações'!$B$15:$B$514,">="&DATE($N$3,7,1),'📋 Movimentações'!$B$15:$B$514,"<="&EOMONTH(DATE($N$3,7,1),0),'📋 Movimentações'!$E$15:$E$514,"Saída",'📋 Movimentações'!$D$15:$D$514,"Mercado") -> 0 | J13: =SUMIFS('📋 Movimentações'!$F$15:$F$514,'📋 Movimentações'!$B$15:$B$514,">="&DATE($N$3,8,1),'📋 Movimentações'!$B$15:$B$514,"<="&EOMONTH(DATE($N$3,8,1),0),'📋 Movimentações'!$E$15:$E$514,"Saída",'📋 Movimentações'!$D$15:$D$514,"Mercado") -> 0 | K13: =SUMIFS('📋 Movimentações'!$F$15:$F$514,'📋 Movimentações'!$B$15:$B$514,">="&DATE($N$3,9,1),'📋 Movimentações'!$B$15:$B$514,"<="&EOMONTH(DATE($N$3,9,1),0),'📋 Movimentações'!$E$15:$E$514,"Saída",'📋 Movimentações'!$D$15:$D$514,"Mercado") -> 0 | L13: =SUMIFS('📋 Movimentações'!$F$15:$F$514,'📋 Movimentações'!$B$15:$B$514,">="&DATE($N$3,10,1),'📋 Movimentações'!$B$15:$B$514,"<="&EOMONTH(DATE($N$3,10,1),0),'📋 Movimentações'!$E$15:$E$514,"Saída",'📋 Movimentações'!$D$15:$D$514,"Mercado") -> 0 | M13: =SUMIFS('📋 Movimentações'!$F$15:$F$514,'📋 Movimentações'!$B$15:$B$514,">="&DATE($N$3,11,1),'📋 Movimentações'!$B$15:$B$514,"<="&EOMONTH(DATE($N$3,11,1),0),'📋 Movimentações'!$E$15:$E$514,"Saída",'📋 Movimentações'!$D$15:$D$514,"Mercado") -> 0 | N13: =SUMIFS('📋 Movimentações'!$F$15:$F$514,'📋 Movimentações'!$B$15:$B$514,">="&DATE($N$3,12,1),'📋 Movimentações'!$B$15:$B$514,"<="&EOMONTH(DATE($N$3,12,1),0),'📋 Movimentações'!$E$15:$E$514,"Saída",'📋 Movimentações'!$D$15:$D$514,"Mercado") -> 0 | O13: =SUM(C13,D13,E13,F13,G13,H13,I13,J13,K13,L13,M13,N13) -> 0
B14: Transporte | C14: =SUMIFS('📋 Movimentações'!$F$15:$F$514,'📋 Movimentações'!$B$15:$B$514,">="&DATE($N$3,1,1),'📋 Movimentações'!$B$15:$B$514,"<="&EOMONTH(DATE($N$3,1,1),0),'📋 Movimentações'!$E$15:$E$514,"Saída",'📋 Movimentações'!$D$15:$D$514,"Gasolina") -> 0 | D14: =SUMIFS('📋 Movimentações'!$F$15:$F$514,'📋 Movimentações'!$B$15:$B$514,">="&DATE($N$3,2,1),'📋 Movimentações'!$B$15:$B$514,"<="&EOMONTH(DATE($N$3,2,1),0),'📋 Movimentações'!$E$15:$E$514,"Saída",'📋 Movimentações'!$D$15:$D$514,"Gasolina") -> 0 | E14: =SUMIFS('📋 Movimentações'!$F$15:$F$514,'📋 Movimentações'!$B$15:$B$514,">="&DATE($N$3,3,1),'📋 Movimentações'!$B$15:$B$514,"<="&EOMONTH(DATE($N$3,3,1),0),'📋 Movimentações'!$E$15:$E$514,"Saída",'📋 Movimentações'!$D$15:$D$514,"Gasolina") -> 0 | F14: =SUMIFS('📋 Movimentações'!$F$15:$F$514,'📋 Movimentações'!$B$15:$B$514,">="&DATE($N$3,4,1),'📋 Movimentações'!$B$15:$B$514,"<="&EOMONTH(DATE($N$3,4,1),0),'📋 Movimentações'!$E$15:$E$514,"Saída",'📋 Movimentações'!$D$15:$D$514,"Gasolina") -> 0 | G14: =SUMIFS('📋 Movimentações'!$F$15:$F$514,'📋 Movimentações'!$B$15:$B$514,">="&DATE($N$3,5,1),'📋 Movimentações'!$B$15:$B$514,"<="&EOMONTH(DATE($N$3,5,1),0),'📋 Movimentações'!$E$15:$E$514,"Saída",'📋 Movimentações'!$D$15:$D$514,"Gasolina") -> 0 | H14: =SUMIFS('📋 Movimentações'!$F$15:$F$514,'📋 Movimentações'!$B$15:$B$514,">="&DATE($N$3,6,1),'📋 Movimentações'!$B$15:$B$514,"<="&EOMONTH(DATE($N$3,6,1),0),'📋 Movimentações'!$E$15:$E$514,"Saída",'📋 Movimentações'!$D$15:$D$514,"Gasolina") -> 0 | I14: =SUMIFS('📋 Movimentações'!$F$15:$F$514,'📋 Movimentações'!$B$15:$B$514,">="&DATE($N$3,7,1),'📋 Movimentações'!$B$15:$B$514,"<="&EOMONTH(DATE($N$3,7,1),0),'📋 Movimentações'!$E$15:$E$514,"Saída",'📋 Movimentações'!$D$15:$D$514,"Gasolina") -> 0 | J14: =SUMIFS('📋 Movimentações'!$F$15:$F$514,'📋 Movimentações'!$B$15:$B$514,">="&DATE($N$3,8,1),'📋 Movimentações'!$B$15:$B$514,"<="&EOMONTH(DATE($N$3,8,1),0),'📋 Movimentações'!$E$15:$E$514,"Saída",'📋 Movimentações'!$D$15:$D$514,"Gasolina") -> 0 | K14: =SUMIFS('📋 Movimentações'!$F$15:$F$514,'📋 Movimentações'!$B$15:$B$514,">="&DATE($N$3,9,1),'📋 Movimentações'!$B$15:$B$514,"<="&EOMONTH(DATE($N$3,9,1),0),'📋 Movimentações'!$E$15:$E$514,"Saída",'📋 Movimentações'!$D$15:$D$514,"Gasolina") -> 0 | L14: =SUMIFS('📋 Movimentações'!$F$15:$F$514,'📋 Movimentações'!$B$15:$B$514,">="&DATE($N$3,10,1),'📋 Movimentações'!$B$15:$B$514,"<="&EOMONTH(DATE($N$3,10,1),0),'📋 Movimentações'!$E$15:$E$514,"Saída",'📋 Movimentações'!$D$15:$D$514,"Gasolina") -> 0 | M14: =SUMIFS('📋 Movimentações'!$F$15:$F$514,'📋 Movimentações'!$B$15:$B$514,">="&DATE($N$3,11,1),'📋 Movimentações'!$B$15:$B$514,"<="&EOMONTH(DATE($N$3,11,1),0),'📋 Movimentações'!$E$15:$E$514,"Saída",'📋 Movimentações'!$D$15:$D$514,"Gasolina") -> 0 | N14: =SUMIFS('📋 Movimentações'!$F$15:$F$514,'📋 Movimentações'!$B$15:$B$514,">="&DATE($N$3,12,1),'📋 Movimentações'!$B$15:$B$514,"<="&EOMONTH(DATE($N$3,12,1),0),'📋 Movimentações'!$E$15:$E$514,"Saída",'📋 Movimentações'!$D$15:$D$514,"Gasolina") -> 0 | O14: =SUM(C14,D14,E14,F14,G14,H14,I14,J14,K14,L14,M14,N14) -> 0
B15: Lazer | C15: =SUMIFS('📋 Movimentações'!$F$15:$F$514,'📋 Movimentações'!$B$15:$B$514,">="&DATE($N$3,1,1),'📋 Movimentações'!$B$15:$B$514,"<="&EOMONTH(DATE($N$3,1,1),0),'📋 Movimentações'!$E$15:$E$514,"Saída",'📋 Movimentações'!$D$15:$D$514,"Lazer") -> 0 | D15: =SUMIFS('📋 Movimentações'!$F$15:$F$514,'📋 Movimentações'!$B$15:$B$514,">="&DATE($N$3,2,1),'📋 Movimentações'!$B$15:$B$514,"<="&EOMONTH(DATE($N$3,2,1),0),'📋 Movimentações'!$E$15:$E$514,"Saída",'📋 Movimentações'!$D$15:$D$514,"Lazer") -> 0 | E15: =SUMIFS('📋 Movimentações'!$F$15:$F$514,'📋 Movimentações'!$B$15:$B$514,">="&DATE($N$3,3,1),'📋 Movimentações'!$B$15:$B$514,"<="&EOMONTH(DATE($N$3,3,1),0),'📋 Movimentações'!$E$15:$E$514,"Saída",'📋 Movimentações'!$D$15:$D$514,"Lazer") -> 0 | F15: =SUMIFS('📋 Movimentações'!$F$15:$F$514,'📋 Movimentações'!$B$15:$B$514,">="&DATE($N$3,4,1),'📋 Movimentações'!$B$15:$B$514,"<="&EOMONTH(DATE($N$3,4,1),0),'📋 Movimentações'!$E$15:$E$514,"Saída",'📋 Movimentações'!$D$15:$D$514,"Lazer") -> 0 | G15: =SUMIFS('📋 Movimentações'!$F$15:$F$514,'📋 Movimentações'!$B$15:$B$514,">="&DATE($N$3,5,1),'📋 Movimentações'!$B$15:$B$514,"<="&EOMONTH(DATE($N$3,5,1),0),'📋 Movimentações'!$E$15:$E$514,"Saída",'📋 Movimentações'!$D$15:$D$514,"Lazer") -> 0 | H15: =SUMIFS('📋 Movimentações'!$F$15:$F$514,'📋 Movimentações'!$B$15:$B$514,">="&DATE($N$3,6,1),'📋 Movimentações'!$B$15:$B$514,"<="&EOMONTH(DATE($N$3,6,1),0),'📋 Movimentações'!$E$15:$E$514,"Saída",'📋 Movimentações'!$D$15:$D$514,"Lazer") -> 0 | I15: =SUMIFS('📋 Movimentações'!$F$15:$F$514,'📋 Movimentações'!$B$15:$B$514,">="&DATE($N$3,7,1),'📋 Movimentações'!$B$15:$B$514,"<="&EOMONTH(DATE($N$3,7,1),0),'📋 Movimentações'!$E$15:$E$514,"Saída",'📋 Movimentações'!$D$15:$D$514,"Lazer") -> 0 | J15: =SUMIFS('📋 Movimentações'!$F$15:$F$514,'📋 Movimentações'!$B$15:$B$514,">="&DATE($N$3,8,1),'📋 Movimentações'!$B$15:$B$514,"<="&EOMONTH(DATE($N$3,8,1),0),'📋 Movimentações'!$E$15:$E$514,"Saída",'📋 Movimentações'!$D$15:$D$514,"Lazer") -> 0 | K15: =SUMIFS('📋 Movimentações'!$F$15:$F$514,'📋 Movimentações'!$B$15:$B$514,">="&DATE($N$3,9,1),'📋 Movimentações'!$B$15:$B$514,"<="&EOMONTH(DATE($N$3,9,1),0),'📋 Movimentações'!$E$15:$E$514,"Saída",'📋 Movimentações'!$D$15:$D$514,"Lazer") -> 0 | L15: =SUMIFS('📋 Movimentações'!$F$15:$F$514,'📋 Movimentações'!$B$15:$B$514,">="&DATE($N$3,10,1),'📋 Movimentações'!$B$15:$B$514,"<="&EOMONTH(DATE($N$3,10,1),0),'📋 Movimentações'!$E$15:$E$514,"Saída",'📋 Movimentações'!$D$15:$D$514,"Lazer") -> 0 | M15: =SUMIFS('📋 Movimentações'!$F$15:$F$514,'📋 Movimentações'!$B$15:$B$514,">="&DATE($N$3,11,1),'📋 Movimentações'!$B$15:$B$514,"<="&EOMONTH(DATE($N$3,11,1),0),'📋 Movimentações'!$E$15:$E$514,"Saída",'📋 Movimentações'!$D$15:$D$514,"Lazer") -> 0 | N15: =SUMIFS('📋 Movimentações'!$F$15:$F$514,'📋 Movimentações'!$B$15:$B$514,">="&DATE($N$3,12,1),'📋 Movimentações'!$B$15:$B$514,"<="&EOMONTH(DATE($N$3,12,1),0),'📋 Movimentações'!$E$15:$E$514,"Saída",'📋 Movimentações'!$D$15:$D$514,"Lazer") -> 0 | O15: =SUM(C15,D15,E15,F15,G15,H15,I15,J15,K15,L15,M15,N15) -> 0
B16: Remessa Brasil | C16: =SUMIFS('📋 Movimentações'!$F$15:$F$514,'📋 Movimentações'!$B$15:$B$514,">="&DATE($N$3,1,1),'📋 Movimentações'!$B$15:$B$514,"<="&EOMONTH(DATE($N$3,1,1),0),'📋 Movimentações'!$E$15:$E$514,"Saída",'📋 Movimentações'!$D$15:$D$514,"Remessa Brasil") -> 0 | D16: =SUMIFS('📋 Movimentações'!$F$15:$F$514,'📋 Movimentações'!$B$15:$B$514,">="&DATE($N$3,2,1),'📋 Movimentações'!$B$15:$B$514,"<="&EOMONTH(DATE($N$3,2,1),0),'📋 Movimentações'!$E$15:$E$514,"Saída",'📋 Movimentações'!$D$15:$D$514,"Remessa Brasil") -> 0 | E16: =SUMIFS('📋 Movimentações'!$F$15:$F$514,'📋 Movimentações'!$B$15:$B$514,">="&DATE($N$3,3,1),'📋 Movimentações'!$B$15:$B$514,"<="&EOMONTH(DATE($N$3,3,1),0),'📋 Movimentações'!$E$15:$E$514,"Saída",'📋 Movimentações'!$D$15:$D$514,"Remessa Brasil") -> 0 | F16: =SUMIFS('📋 Movimentações'!$F$15:$F$514,'📋 Movimentações'!$B$15:$B$514,">="&DATE($N$3,4,1),'📋 Movimentações'!$B$15:$B$514,"<="&EOMONTH(DATE($N$3,4,1),0),'📋 Movimentações'!$E$15:$E$514,"Saída",'📋 Movimentações'!$D$15:$D$514,"Remessa Brasil") -> 0 | G16: =SUMIFS('📋 Movimentações'!$F$15:$F$514,'📋 Movimentações'!$B$15:$B$514,">="&DATE($N$3,5,1),'📋 Movimentações'!$B$15:$B$514,"<="&EOMONTH(DATE($N$3,5,1),0),'📋 Movimentações'!$E$15:$E$514,"Saída",'📋 Movimentações'!$D$15:$D$514,"Remessa Brasil") -> 0 | H16: =SUMIFS('📋 Movimentações'!$F$15:$F$514,'📋 Movimentações'!$B$15:$B$514,">="&DATE($N$3,6,1),'📋 Movimentações'!$B$15:$B$514,"<="&EOMONTH(DATE($N$3,6,1),0),'📋 Movimentações'!$E$15:$E$514,"Saída",'📋 Movimentações'!$D$15:$D$514,"Remessa Brasil") -> 0 | I16: =SUMIFS('📋 Movimentações'!$F$15:$F$514,'📋 Movimentações'!$B$15:$B$514,">="&DATE($N$3,7,1),'📋 Movimentações'!$B$15:$B$514,"<="&EOMONTH(DATE($N$3,7,1),0),'📋 Movimentações'!$E$15:$E$514,"Saída",'📋 Movimentações'!$D$15:$D$514,"Remessa Brasil") -> 0 | J16: =SUMIFS('📋 Movimentações'!$F$15:$F$514,'📋 Movimentações'!$B$15:$B$514,">="&DATE($N$3,8,1),'📋 Movimentações'!$B$15:$B$514,"<="&EOMONTH(DATE($N$3,8,1),0),'📋 Movimentações'!$E$15:$E$514,"Saída",'📋 Movimentações'!$D$15:$D$514,"Remessa Brasil") -> 0 | K16: =SUMIFS('📋 Movimentações'!$F$15:$F$514,'📋 Movimentações'!$B$15:$B$514,">="&DATE($N$3,9,1),'📋 Movimentações'!$B$15:$B$514,"<="&EOMONTH(DATE($N$3,9,1),0),'📋 Movimentações'!$E$15:$E$514,"Saída",'📋 Movimentações'!$D$15:$D$514,"Remessa Brasil") -> 0 | L16: =SUMIFS('📋 Movimentações'!$F$15:$F$514,'📋 Movimentações'!$B$15:$B$514,">="&DATE($N$3,10,1),'📋 Movimentações'!$B$15:$B$514,"<="&EOMONTH(DATE($N$3,10,1),0),'📋 Movimentações'!$E$15:$E$514,"Saída",'📋 Movimentações'!$D$15:$D$514,"Remessa Brasil") -> 0 | M16: =SUMIFS('📋 Movimentações'!$F$15:$F$514,'📋 Movimentações'!$B$15:$B$514,">="&DATE($N$3,11,1),'📋 Movimentações'!$B$15:$B$514,"<="&EOMONTH(DATE($N$3,11,1),0),'📋 Movimentações'!$E$15:$E$514,"Saída",'📋 Movimentações'!$D$15:$D$514,"Remessa Brasil") -> 0 | N16: =SUMIFS('📋 Movimentações'!$F$15:$F$514,'📋 Movimentações'!$B$15:$B$514,">="&DATE($N$3,12,1),'📋 Movimentações'!$B$15:$B$514,"<="&EOMONTH(DATE($N$3,12,1),0),'📋 Movimentações'!$E$15:$E$514,"Saída",'📋 Movimentações'!$D$15:$D$514,"Remessa Brasil") -> 0 | O16: =SUM(C16,D16,E16,F16,G16,H16,I16,J16,K16,L16,M16,N16) -> 0
B17: Total Saídas | C17: =SUMIFS('📋 Movimentações'!$F$15:$F$514,'📋 Movimentações'!$B$15:$B$514,">="&DATE($N$3,1,1),'📋 Movimentações'!$B$15:$B$514,"<="&EOMONTH(DATE($N$3,1,1),0),'📋 Movimentações'!$E$15:$E$514,"Saída") -> 0 | D17: =SUMIFS('📋 Movimentações'!$F$15:$F$514,'📋 Movimentações'!$B$15:$B$514,">="&DATE($N$3,2,1),'📋 Movimentações'!$B$15:$B$514,"<="&EOMONTH(DATE($N$3,2,1),0),'📋 Movimentações'!$E$15:$E$514,"Saída") -> 0 | E17: =SUMIFS('📋 Movimentações'!$F$15:$F$514,'📋 Movimentações'!$B$15:$B$514,">="&DATE($N$3,3,1),'📋 Movimentações'!$B$15:$B$514,"<="&EOMONTH(DATE($N$3,3,1),0),'📋 Movimentações'!$E$15:$E$514,"Saída") -> 0 | F17: =SUMIFS('📋 Movimentações'!$F$15:$F$514,'📋 Movimentações'!$B$15:$B$514,">="&DATE($N$3,4,1),'📋 Movimentações'!$B$15:$B$514,"<="&EOMONTH(DATE($N$3,4,1),0),'📋 Movimentações'!$E$15:$E$514,"Saída") -> 0 | G17: =SUMIFS('📋 Movimentações'!$F$15:$F$514,'📋 Movimentações'!$B$15:$B$514,">="&DATE($N$3,5,1),'📋 Movimentações'!$B$15:$B$514,"<="&EOMONTH(DATE($N$3,5,1),0),'📋 Movimentações'!$E$15:$E$514,"Saída") -> 111572 | H17: =SUMIFS('📋 Movimentações'!$F$15:$F$514,'📋 Movimentações'!$B$15:$B$514,">="&DATE($N$3,6,1),'📋 Movimentações'!$B$15:$B$514,"<="&EOMONTH(DATE($N$3,6,1),0),'📋 Movimentações'!$E$15:$E$514,"Saída") -> 0 | I17: =SUMIFS('📋 Movimentações'!$F$15:$F$514,'📋 Movimentações'!$B$15:$B$514,">="&DATE($N$3,7,1),'📋 Movimentações'!$B$15:$B$514,"<="&EOMONTH(DATE($N$3,7,1),0),'📋 Movimentações'!$E$15:$E$514,"Saída") -> 0 | J17: =SUMIFS('📋 Movimentações'!$F$15:$F$514,'📋 Movimentações'!$B$15:$B$514,">="&DATE($N$3,8,1),'📋 Movimentações'!$B$15:$B$514,"<="&EOMONTH(DATE($N$3,8,1),0),'📋 Movimentações'!$E$15:$E$514,"Saída") -> 0 | K17: =SUMIFS('📋 Movimentações'!$F$15:$F$514,'📋 Movimentações'!$B$15:$B$514,">="&DATE($N$3,9,1),'📋 Movimentações'!$B$15:$B$514,"<="&EOMONTH(DATE($N$3,9,1),0),'📋 Movimentações'!$E$15:$E$514,"Saída") -> 0 | L17: =SUMIFS('📋 Movimentações'!$F$15:$F$514,'📋 Movimentações'!$B$15:$B$514,">="&DATE($N$3,10,1),'📋 Movimentações'!$B$15:$B$514,"<="&EOMONTH(DATE($N$3,10,1),0),'📋 Movimentações'!$E$15:$E$514,"Saída") -> 0 | M17: =SUMIFS('📋 Movimentações'!$F$15:$F$514,'📋 Movimentações'!$B$15:$B$514,">="&DATE($N$3,11,1),'📋 Movimentações'!$B$15:$B$514,"<="&EOMONTH(DATE($N$3,11,1),0),'📋 Movimentações'!$E$15:$E$514,"Saída") -> 0 | N17: =SUMIFS('📋 Movimentações'!$F$15:$F$514,'📋 Movimentações'!$B$15:$B$514,">="&DATE($N$3,12,1),'📋 Movimentações'!$B$15:$B$514,"<="&EOMONTH(DATE($N$3,12,1),0),'📋 Movimentações'!$E$15:$E$514,"Saída") -> 0 | O17: =SUM(C17,D17,E17,F17,G17,H17,I17,J17,K17,L17,M17,N17) -> 111572
B18: ── RESULTADO ──
B19: Economia | C19: =C10-C17 -> 0 | D19: =D10-D17 -> 0 | E19: =E10-E17 -> 0 | F19: =F10-F17 -> 0 | G19: =G10-G17 -> 317428 | H19: =H10-H17 -> 0 | I19: =I10-I17 -> 0 | J19: =J10-J17 -> 0 | ... N19: =N10-N17 -> 0 | O19: =SUM(C19,D19,E19,F19,G19,H19,I19,J19,K19,L19,M19,N19) -> 317428
B20: % Economizado | C20: =IFERROR(C19/C10,0) -> 0 | D20: =IFERROR(D19/D10,0) -> 0 | E20: =IFERROR(E19/E10,0) -> 0 | F20: =IFERROR(F19/F10,0) -> 0 | G20: =IFERROR(G19/G10,0) -> 0.73992541 | H20: =IFERROR(H19/H10,0) -> 0 | I20: =IFERROR(I19/I10,0) -> 0 | J20: =IFERROR(J19/J10,0) -> 0 | ... O20: =IFERROR(O19/O10,0) -> 0.73992541
B22: 📈 EVOLUÇÃO ANUAL — Entradas, Saídas e Economia

Sheet 💡 Simulador
B2: 💡 SIMULADOR DE ECONOMIA
B5: ⚙️ PARÂMETROS
B6: Renda mensal atual (¥): | C6: 285000 | D6: ← Digite aqui
B7: Gastos fixos mensais (¥): | C7: 130000 | D7: ← Digite aqui
B8: Quanto pretende guardar/mês (¥): | C8: 30000 | D8: ← Digite aqui
B9: Rendimento anual estimado (%): | C9: 0.03 | D9: ← Digite aqui
B10: Já tenho guardado (¥): | C10: 0 | D10: ← Digite aqui
B12: 📊 PROJEÇÃO DE ACÚMULO
B13: PERÍODO | C13: POUPADO (¥) | D13: RENDIMENTO (¥) | E13: TOTAL ACUM. (¥) | F13: SOBRA LIVRE (¥)
B14: 3 meses | C14: =3*$C$8 -> 90000 | D14: =E14-C14-$C$10 -> 222 | E14: =ROUND($C$10*(1+$C$9/12)^3+$C$8*((1+$C$9/12)^3-1)/($C$9/12+0.0000001),0) -> 90222 | F14: =($C$6-$C$7-$C$8)*3 -> 375000
B15: 6 meses | C15: =6*$C$8 -> 180000 | D15: =E15-C15-$C$10 -> 1122 | E15: =ROUND($C$10*(1+$C$9/12)^6+$C$8*((1+$C$9/12)^6-1)/($C$9/12+0.0000001),0) -> 181122 | F15: =($C$6-$C$7-$C$8)*6 -> 750000
B16: 12 meses | C16: =12*$C$8 -> 360000 | D16: =E16-C16-$C$10 -> 4977 | E16: =ROUND($C$10*(1+$C$9/12)^12+$C$8*((1+$C$9/12)^12-1)/($C$9/12+0.0000001),0) -> 364977 | F16: =($C$6-$C$7-$C$8)*12 -> 1500000
B17: 18 meses | C17: =18*$C$8 -> 540000 | D17: =E17-C17-$C$10 -> 11607 | E17: =ROUND($C$10*(1+$C$9/12)^18+$C$8*((1+$C$9/12)^18-1)/($C$9/12+0.0000001),0) -> 551607 | F17: =($C$6-$C$7-$C$8)*18 -> 2250000
B18: 24 meses | C18: =24*$C$8 -> 720000 | D18: =E18-C18-$C$10 -> 21055 | E18: =ROUND($C$10*(1+$C$9/12)^24+$C$8*((1+$C$9/12)^24-1)/($C$9/12+0.0000001),0) -> 741055 | F18: =($C$6-$C$7-$C$8)*24 -> 3000000
B19: 36 meses | C19: =36*$C$8 -> 1080000 | D19: =E19-C19-$C$10 -> 48572 | E19: =ROUND($C$10*(1+$C$9/12)^36+$C$8*((1+$C$9/12)^36-1)/($C$9/12+0.0000001),0) -> 1128572 | F19: =($C$6-$C$7-$C$8)*36 -> 4500000
B20: 48 meses | C20: =48*$C$8 -> 1440000 | D20: =E20-C20-$C$10 -> 87875 | E20: =ROUND($C$10*(1+$C$9/12)^48+$C$8*((1+$C$9/12)^48-1)/($C$9/12+0.0000001),0) -> 1527875 | F20: =($C$6-$C$7-$C$8)*48 -> 6000000
B21: 60 meses | C21: =60*$C$8 -> 1800000 | D21: =E21-C21-$C$10 -> 139324 | E21: =ROUND($C$10*(1+$C$9/12)^60+$C$8*((1+$C$9/12)^60-1)/($C$9/12+0.0000001),0) -> 1939324 | F21: =($C$6-$C$7-$C$8)*60 -> 7500000
B23: 💡 Altere os valores em C6:C10 para simular diferentes cenários. O rendimento usa juros compostos mensais.
